Workbook

Sheet README
A1: Earnings by Sector — Peer Comp Workbook
A2: Software (99 names) and Semiconductors (139 names) quarterly earnings analysis vs peers: revenue growth, $ added QoQ/YoY, margin expansion, operating leverage, FCF margin expansion, and NTM estimate revisions.
A4: HOW TO REFRESH
A5: 1. Open this file in Excel on a machine with the Bloomberg Add-in (terminal) logged in.
A6: 2. Bloomberg ribbon > Refresh All (or Ctrl+Alt+F9). The BQL spills and BDP calls will populate; the first refresh pulls ~950 BQL queries + ~1,900 BDP fields, so give it a few minutes.
A7: 3. All analysis sheets (Metrics, Dashboard, Focus) recalculate automatically from the data sheets.
A9: SHEET GUIDE
A10: Tickers — the only input sheet: both peer lists. Row order here drives every other sheet.
A11: SW/Semi Rev, OpInc, FCF — raw quarterly data via one BQL spill per ticker (FPO −13 … +2, USD mm).
A12: SW/Semi Revisions — NTM (1BF) consensus revenue & EPS now vs 1M/3M/6M ago, and the % revisions.
A13: SW/Semi Metrics — computed grids: YoY/QoQ growth, $ added, op margin & expansion, op income growth, incremental margin (operating leverage), LTM FCF margin & expansion.
A14: SW/Semi Dashboard — one row per name, latest-quarter snapshot of every metric + revision columns, with peer median / quartiles on top and color scales.
... A40: • Sorting the Dashboard keeps each row internally consistent, but re-sorting is manual after a refresh.

Sheet Tickers
A1: Ticker Lists (edit here — every other sheet reads these cells) | H1: ⚠ Cells blank? This is a LIVE Bloomberg workbook — it has no saved data until its first refresh. Open it in desktop Excel on your Bloomberg terminal PC (add-in logged in), then Bloomberg ribbon ▸ Refresh All (or Ctrl+Alt+F9), wait a few minutes, and save. See README.
A2: Blue cells are inputs. Row order here = row order on every data/metric/dashboard sheet. If you add names, insert rows INSIDE the list on this sheet and copy formulas down on the sector sheets.
A4: Software (99 tickers) | D4: Semiconductors (139 tickers)
A5: GOOG US Equity | D5: STM US Equity
A6: MSFT US Equity | D6: ARM US Equity
A7: ORCL US Equity | D7: 1347 HK Equity
A8: AMD US Equity | D8: 981 HK Equity
A9: SAP GY Equity | D9: TSM US Equity
A10: ARM US Equity | D10: UMC US Equity
A11: CRM US Equity | D11: 000660 KS Equity
A12: SHOP US Equity | D12: SIMO US Equity
A13: PANW US Equity | D13: 005930 KS Equity
A14: CRWD US Equity | D14: 285A JP Equity
A15: INTU US Equity | D15: PSTG US Equity
... A103: SPT US Equity | D103: 2313 TT Equity
D104: 3189 TT Equity
A105: =COUNTA(A5:A103)&" tickers" | D105: AMAT US Equity
D106: 3711 TT Equity
D107: TXN US Equity
D108: 6799 TT Equity
D109: NVDA US Equity
D110: 1560 TT Equity
D111: AVGO US Equity
D112: MSFT US Equity
D113: AMZN US Equity
D114: 3443 TT Equity
D115: 6515 TT Equity
D116: 2360 TT Equity
D117: GOOG US Equity
... D143: 3680 TT Equity
D145: =COUNTA(D5:D143)&" tickers"

Sheet SW Dashboard
A1: Software — Earnings Comp Dashboard (latest reported quarter) | H1: ⚠ Cells blank? This is a LIVE Bloomberg workbook — it has no saved data until its first refresh. Open it in desktop Excel on your Bloomberg terminal PC (add-in logged in), then Bloomberg ribbon ▸ Refresh All (or Ctrl+Alt+F9), wait a few minutes, and save. See README.
A2: USD mm unless noted. Every row reads the same-numbered row on the data/metric sheets. FPO 0 = each company's own latest reported quarter. Estimate-based columns note (Est).
A4: Ticker | B4: Latest Rpt Qtr | C4: Revenue LQ (USD mm) | D4: Rev YoY % | E4: Rev YoY % (prior qtr) | F4: Accel / (Decel) (pp) | G4: Rev QoQ % | H4: $ Added QoQ (mm) | I4: $ Added YoY (mm) | J4: Next Qtr YoY % (Est) | K4: Op Margin % | L4: OpM Δ YoY (bps) | M4: Op Inc YoY % | N4: Incr OpM % (Op Leverage) | O4: Op Lev (x) | P4: FCF Margin LTM % | Q4: FCF Margin Δ YoY (bps) | R4: NTM Rev Rev Δ1M % | S4: NTM Rev Rev Δ3M % | T4: NTM Rev Rev Δ6M % | U4: NTM EPS Rev Δ1M % | V4: NTM EPS Rev Δ3M % | W4: NTM EPS Rev Δ6M % | X4: Rank: Rev YoY | Y4: Rank: NTM Rev Δ3M
A5: Peer Median | C5: =IFERROR(MEDIAN(C8:C106),"") | D5: =IFERROR(MEDIAN(D8:D106),"") | E5: =IFERROR(MEDIAN(E8:E106),"") | F5: =IFERROR(MEDIAN(F8:F106),"") | G5: =IFERROR(MEDIAN(G8:G106),"") | H5: =IFERROR(MEDIAN(H8:H106),"") | I5: =IFERROR(MEDIAN(I8:I106),"") | J5: =IFERROR(MEDIAN(J8:J106),"") | ... W5: =IFERROR(MEDIAN(W8:W106),"")
A6: Top Quartile (75th) | C6: =IFERROR(QUARTILE(C8:C106,3),"") | D6: =IFERROR(QUARTILE(D8:D106,3),"") | E6: =IFERROR(QUARTILE(E8:E106,3),"") | F6: =IFERROR(QUARTILE(F8:F106,3),"") | G6: =IFERROR(QUARTILE(G8:G106,3),"") | H6: =IFERROR(QUARTILE(H8:H106,3),"") | I6: =IFERROR(QUARTILE(I8:I106,3),"") | J6: =IFERROR(QUARTILE(J8:J106,3),"") | ... W6: =IFERROR(QUARTILE(W8:W106,3),"")
A7: Bottom Quartile (25th) | C7: =IFERROR(QUARTILE(C8:C106,1),"") | D7: =IFERROR(QUARTILE(D8:D106,1),"") | E7: =IFERROR(QUARTILE(E8:E106,1),"") | F7: =IFERROR(QUARTILE(F8:F106,1),"") | G7: =IFERROR(QUARTILE(G8:G106,1),"") | H7: =IFERROR(QUARTILE(H8:H106,1),"") | I7: =IFERROR(QUARTILE(I8:I106,1),"") | J7: =IFERROR(QUARTILE(J8:J106,1),"") | ... W7: =IFERROR(QUARTILE(W8:W106,1),"")
A8: ='SW Rev'!$A5 | B8: ='SW Rev'!$B5 | C8: =IF(ISNUMBER('SW Rev'!P5),'SW Rev'!P5,"") | D8: ='SW Metrics'!L108 | E8: ='SW Metrics'!K108 | F8: =IF(OR(D8="",E8=""),"",D8-E8) | G8: ='SW Metrics'!L210 | H8: ='SW Metrics'!L414 | I8: ='SW Metrics'!L312 | J8: ='SW Metrics'!M108 | K8: ='SW Metrics'!L516 | L8: ='SW Metrics'!L618 | M8: ='SW Metrics'!L720 | N8: ='SW Metrics'!L822 | O8: =IFERROR(IF(AND(N(D8)>0,N(M8)>0),M8/D8,""),"") | P8: ='SW Metrics'!L924 | Q8: ='SW Metrics'!L1026 | R8: ='SW Revisions'!G6 | S8: ='SW Revisions'!H6 | T8: ='SW Revisions'!I6 | U8: ='SW Revisions'!O6 | V8: ='SW Revisions'!P6 | W8: ='SW Revisions'!Q6 | X8: =IFERROR(RANK(D8,D$8:D$106),"") | Y8: =IFERROR(RANK(S8,S$8:S$106),"")
A9: ='SW Rev'!$A6 | B9: ='SW Rev'!$B6 | C9: =IF(ISNUMBER('SW Rev'!P6),'SW Rev'!P6,"") | D9: ='SW Metrics'!L109 | E9: ='SW Metrics'!K109 | F9: =IF(OR(D9="",E9=""),"",D9-E9) | G9: ='SW Metrics'!L211 | H9: ='SW Metrics'!L415 | I9: ='SW Metrics'!L313 | J9: ='SW Metrics'!M109 | K9: ='SW Metrics'!L517 | L9: ='SW Metrics'!L619 | M9: ='SW Metrics'!L721 | N9: ='SW Metrics'!L823 | O9: =IFERROR(IF(AND(N(D9)>0,N(M9)>0),M9/D9,""),"") | P9: ='SW Metrics'!L925 | Q9: ='SW Metrics'!L1027 | R9: ='SW Revisions'!G7 | S9: ='SW Revisions'!H7 | T9: ='SW Revisions'!I7 | U9: ='SW Revisions'!O7 | V9: ='SW Revisions'!P7 | W9: ='SW Revisions'!Q7 | X9: =IFERROR(RANK(D9,D$8:D$106),"") | Y9: =IFERROR(RANK(S9,S$8:S$106),"")
A10: ='SW Rev'!$A7 | B10: ='SW Rev'!$B7 | C10: =IF(ISNUMBER('SW Rev'!P7),'SW Rev'!P7,"") | D10: ='SW Metrics'!L110 | E10: ='SW Metrics'!K110 | F10: =IF(OR(D10="",E10=""),"",D10-E10) | G10: ='SW Metrics'!L212 | H10: ='SW Metrics'!L416 | I10: ='SW Metrics'!L314 | J10: ='SW Metrics'!M110 | K10: ='SW Metrics'!L518 | L10: ='SW Metrics'!L620 | M10: ='SW Metrics'!L722 | N10: ='SW Metrics'!L824 | O10: =IFERROR(IF(AND(N(D10)>0,N(M10)>0),M10/D10,""),"") | P10: ='SW Metrics'!L926 | Q10: ='SW Metrics'!L1028 | R10: ='SW Revisions'!G8 | S10: ='SW Revisions'!H8 | T10: ='SW Revisions'!I8 | U10: ='SW Revisions'!O8 | V10: ='SW Revisions'!P8 | W10: ='SW Revisions'!Q8 | X10: =IFERROR(RANK(D10,D$8:D$106),"") | Y10: =IFERROR(RANK(S10,S$8:S$106),"")
A11: ='SW Rev'!$A8 | B11: ='SW Rev'!$B8 | C11: =IF(ISNUMBER('SW Rev'!P8),'SW Rev'!P8,"") | D11: ='SW Metrics'!L111 | E11: ='SW Metrics'!K111 | F11: =IF(OR(D11="",E11=""),"",D11-E11) | G11: ='SW Metrics'!L213 | H11: ='SW Metrics'!L417 | I11: ='SW Metrics'!L315 | J11: ='SW Metrics'!M111 | K11: ='SW Metrics'!L519 | L11: ='SW Metrics'!L621 | M11: ='SW Metrics'!L723 | N11: ='SW Metrics'!L825 | O11: =IFERROR(IF(AND(N(D11)>0,N(M11)>0),M11/D11,""),"") | P11: ='SW Metrics'!L927 | Q11: ='SW Metrics'!L1029 | R11: ='SW Revisions'!G9 | S11: ='SW Revisions'!H9 | T11: ='SW Revisions'!I9 | U11: ='SW Revisions'!O9 | V11: ='SW Revisions'!P9 | W11: ='SW Revisions'!Q9 | X11: =IFERROR(RANK(D11,D$8:D$106),"") | Y11: =IFERROR(RANK(S11,S$8:S$106),"")
A12: ='SW Rev'!$A9 | B12: ='SW Rev'!$B9 | C12: =IF(ISNUMBER('SW Rev'!P9),'SW Rev'!P9,"") | D12: ='SW Metrics'!L112 | E12: ='SW Metrics'!K112 | F12: =IF(OR(D12="",E12=""),"",D12-E12) | G12: ='SW Metrics'!L214 | H12: ='SW Metrics'!L418 | I12: ='SW Metrics'!L316 | J12: ='SW Metrics'!M112 | K12: ='SW Metrics'!L520 | L12: ='SW Metrics'!L622 | M12: ='SW Metrics'!L724 | N12: ='SW Metrics'!L826 | O12: =IFERROR(IF(AND(N(D12)>0,N(M12)>0),M12/D12,""),"") | P12: ='SW Metrics'!L928 | Q12: ='SW Metrics'!L1030 | R12: ='SW Revisions'!G10 | S12: ='SW Revisions'!H10 | T12: ='SW Revisions'!I10 | U12: ='SW Revisions'!O10 | V12: ='SW Revisions'!P10 | W12: ='SW Revisions'!Q10 | X12: =IFERROR(RANK(D12,D$8:D$106),"") | Y12: =IFERROR(RANK(S12,S$8:S$106),"")
A13: ='SW Rev'!$A10 | B13: ='SW Rev'!$B10 | C13: =IF(ISNUMBER('SW Rev'!P10),'SW Rev'!P10,"") | D13: ='SW Metrics'!L113 | E13: ='SW Metrics'!K113 | F13: =IF(OR(D13="",E13=""),"",D13-E13) | G13: ='SW Metrics'!L215 | H13: ='SW Metrics'!L419 | I13: ='SW Metrics'!L317 | J13: ='SW Metrics'!M113 | K13: ='SW Metrics'!L521 | L13: ='SW Metrics'!L623 | M13: ='SW Metrics'!L725 | N13: ='SW Metrics'!L827 | O13: =IFERROR(IF(AND(N(D13)>0,N(M13)>0),M13/D13,""),"") | P13: ='SW Metrics'!L929 | Q13: ='SW Metrics'!L1031 | R13: ='SW Revisions'!G11 | S13: ='SW Revisions'!H11 | T13: ='SW Revisions'!I11 | U13: ='SW Revisions'!O11 | V13: ='SW Revisions'!P11 | W13: ='SW Revisions'!Q11 | X13: =IFERROR(RANK(D13,D$8:D$106),"") | Y13: =IFERROR(RANK(S13,S$8:S$106),"")
A14: ='SW Rev'!$A11 | B14: ='SW Rev'!$B11 | C14: =IF(ISNUMBER('SW Rev'!P11),'SW Rev'!P11,"") | D14: ='SW Metrics'!L114 | E14: ='SW Metrics'!K114 | F14: =IF(OR(D14="",E14=""),"",D14-E14) | G14: ='SW Metrics'!L216 | H14: ='SW Metrics'!L420 | I14: ='SW Metrics'!L318 | J14: ='SW Metrics'!M114 | K14: ='SW Metrics'!L522 | L14: ='SW Metrics'!L624 | M14: ='SW Metrics'!L726 | N14: ='SW Metrics'!L828 | O14: =IFERROR(IF(AND(N(D14)>0,N(M14)>0),M14/D14,""),"") | P14: ='SW Metrics'!L930 | Q14: ='SW Metrics'!L1032 | R14: ='SW Revisions'!G12 | S14: ='SW Revisions'!H12 | T14: ='SW Revisions'!I12 | U14: ='SW Revisions'!O12 | V14: ='SW Revisions'!P12 | W14: ='SW Revisions'!Q12 | X14: =IFERROR(RANK(D14,D$8:D$106),"") | Y14: =IFERROR(RANK(S14,S$8:S$106),"")
A15: ='SW Rev'!$A12 | B15: ='SW Rev'!$B12 | C15: =IF(ISNUMBER('SW Rev'!P12),'SW Rev'!P12,"") | D15: ='SW Metrics'!L115 | E15: ='SW Metrics'!K115 | F15: =IF(OR(D15="",E15=""),"",D15-E15) | G15: ='SW Metrics'!L217 | H15: ='SW Metrics'!L421 | I15: ='SW Metrics'!L319 | J15: ='SW Metrics'!M115 | K15: ='SW Metrics'!L523 | L15: ='SW Metrics'!L625 | M15: ='SW Metrics'!L727 | N15: ='SW Metrics'!L829 | O15: =IFERROR(IF(AND(N(D15)>0,N(M15)>0),M15/D15,""),"") | P15: ='SW Metrics'!L931 | Q15: ='SW Metrics'!L1033 | R15: ='SW Revisions'!G13 | S15: ='SW Revisions'!H13 | T15: ='SW Revisions'!I13 | U15: ='SW Revisions'!O13 | V15: ='SW Revisions'!P13 | W15: ='SW Revisions'!Q13 | X15: =IFERROR(RANK(D15,D$8:D$106),"") | Y15: =IFERROR(RANK(S15,S$8:S$106),"")
A16: ='SW Rev'!$A13 | B16: ='SW Rev'!$B13 | C16: =IF(ISNUMBER('SW Rev'!P13),'SW Rev'!P13,"") | D16: ='SW Metrics'!L116 | E16: ='SW Metrics'!K116 | F16: =IF(OR(D16="",E16=""),"",D16-E16) | G16: ='SW Metrics'!L218 | H16: ='SW Metrics'!L422 | I16: ='SW Metrics'!L320 | J16: ='SW Metrics'!M116 | K16: ='SW Metrics'!L524 | L16: ='SW Metrics'!L626 | M16: ='SW Metrics'!L728 | N16: ='SW Metrics'!L830 | O16: =IFERROR(IF(AND(N(D16)>0,N(M16)>0),M16/D16,""),"") | P16: ='SW Metrics'!L932 | Q16: ='SW Metrics'!L1034 | R16: ='SW Revisions'!G14 | S16: ='SW Revisions'!H14 | T16: ='SW Revisions'!I14 | U16: ='SW Revisions'!O14 | V16: ='SW Revisions'!P14 | W16: ='SW Revisions'!Q14 | X16: =IFERROR(RANK(D16,D$8:D$106),"") | Y16: =IFERROR(RANK(S16,S$8:S$106),"")
A17: ='SW Rev'!$A14 | B17: ='SW Rev'!$B14 | C17: =IF(ISNUMBER('SW Rev'!P14),'SW Rev'!P14,"") | D17: ='SW Metrics'!L117 | E17: ='SW Metrics'!K117 | F17: =IF(OR(D17="",E17=""),"",D17-E17) | G17: ='SW Metrics'!L219 | H17: ='SW Metrics'!L423 | I17: ='SW Metrics'!L321 | J17: ='SW Metrics'!M117 | K17: ='SW Metrics'!L525 | L17: ='SW Metrics'!L627 | M17: ='SW Metrics'!L729 | N17: ='SW Metrics'!L831 | O17: =IFERROR(IF(AND(N(D17)>0,N(M17)>0),M17/D17,""),"") | P17: ='SW Metrics'!L933 | Q17: ='SW Metrics'!L1035 | R17: ='SW Revisions'!G15 | S17: ='SW Revisions'!H15 | T17: ='SW Revisions'!I15 | U17: ='SW Revisions'!O15 | V17: ='SW Revisions'!P15 | W17: ='SW Revisions'!Q15 | X17: =IFERROR(RANK(D17,D$8:D$106),"") | Y17: =IFERROR(RANK(S17,S$8:S$106),"")
A18: ='SW Rev'!$A15 | B18: ='SW Rev'!$B15 | C18: =IF(ISNUMBER('SW Rev'!P15),'SW Rev'!P15,"") | D18: ='SW Metrics'!L118 | E18: ='SW Metrics'!K118 | F18: =IF(OR(D18="",E18=""),"",D18-E18) | G18: ='SW Metrics'!L220 | H18: ='SW Metrics'!L424 | I18: ='SW Metrics'!L322 | J18: ='SW Metrics'!M118 | K18: ='SW Metrics'!L526 | L18: ='SW Metrics'!L628 | M18: ='SW Metrics'!L730 | N18: ='SW Metrics'!L832 | O18: =IFERROR(IF(AND(N(D18)>0,N(M18)>0),M18/D18,""),"") | P18: ='SW Metrics'!L934 | Q18: ='SW Metrics'!L1036 | R18: ='SW Revisions'!G16 | S18: ='SW Revisions'!H16 | T18: ='SW Revisions'!I16 | U18: ='SW Revisions'!O16 | V18: ='SW Revisions'!P16 | W18: ='SW Revisions'!Q16 | X18: =IFERROR(RANK(D18,D$8:D$106),"") | Y18: =IFERROR(RANK(S18,S$8:S$106),"")
A19: ='SW Rev'!$A16 | B19: ='SW Rev'!$B16 | C19: =IF(ISNUMBER('SW Rev'!P16),'SW Rev'!P16,"") | D19: ='SW Metrics'!L119 | E19: ='SW Metrics'!K119 | F19: =IF(OR(D19="",E19=""),"",D19-E19) | G19: ='SW Metrics'!L221 | H19: ='SW Metrics'!L425 | I19: ='SW Metrics'!L323 | J19: ='SW Metrics'!M119 | K19: ='SW Metrics'!L527 | L19: ='SW Metrics'!L629 | M19: ='SW Metrics'!L731 | N19: ='SW Metrics'!L833 | O19: =IFERROR(IF(AND(N(D19)>0,N(M19)>0),M19/D19,""),"") | P19: ='SW Metrics'!L935 | Q19: ='SW Metrics'!L1037 | R19: ='SW Revisions'!G17 | S19: ='SW Revisions'!H17 | T19: ='SW Revisions'!I17 | U19: ='SW Revisions'!O17 | V19: ='SW Revisions'!P17 | W19: ='SW Revisions'!Q17 | X19: =IFERROR(RANK(D19,D$8:D$106),"") | Y19: =IFERROR(RANK(S19,S$8:S$106),"")
... A106: ='SW Rev'!$A103 | B106: ='SW Rev'!$B103 | C106: =IF(ISNUMBER('SW Rev'!P103),'SW Rev'!P103,"") | D106: ='SW Metrics'!L206 | E106: ='SW Metrics'!K206 | F106: =IF(OR(D106="",E106=""),"",D106-E106) | G106: ='SW Metrics'!L308 | H106: ='SW Metrics'!L512 | I106: ='SW Metrics'!L410 | J106: ='SW Metrics'!M206 | K106: ='SW Metrics'!L614 | L106: ='SW Metrics'!L716 | M106: ='SW Metrics'!L818 | N106: ='SW Metrics'!L920 | O106: =IFERROR(IF(AND(N(D106)>0,N(M106)>0),M106/D106,""),"") | P106: ='SW Metrics'!L1022 | Q106: ='SW Metrics'!L1124 | R106: ='SW Revisions'!G104 | S106: ='SW Revisions'!H104 | T106: ='SW Revisions'!I104 | U106: ='SW Revisions'!O104 | V106: ='SW Revisions'!P104 | W106: ='SW Revisions'!Q104 | X106: =IFERROR(RANK(D106,D$8:D$106),"") | Y106: =IFERROR(RANK(S106,S$8:S$106),"")

Sheet SW Focus
A1: Software — Single-Name vs Peers | H1: ⚠ Cells blank? This is a LIVE Bloomberg workbook — it has no saved data until its first refresh. Open it in desktop Excel on your Bloomberg terminal PC (add-in logged in), then Bloomberg ribbon ▸ Refresh All (or Ctrl+Alt+F9), wait a few minutes, and save. See README.
A2: Type any ticker from the Tickers sheet into the yellow cell. Each metric shows the company, the peer-set median (computed over the full list, selected name included), and the gap. Columns aligned by FPO (company's own fiscal quarters).
A4: Company (edit): | B4: ZM US Equity | C4: =IFERROR("Latest reported qtr: "&INDEX('SW Rev'!$B$5:$B$103,MATCH($B$4,'SW Rev'!$A$5:$A$103,0)),"⚠ ticker not found in Tickers list")
A6: Metric | B6: Series | C6: FPO -9 | D6: FPO -8 | E6: FPO -7 | F6: FPO -6 | G6: FPO -5 | H6: FPO -4 | I6: FPO -3 | J6: FPO -2 | K6: FPO -1 | L6: FPO 0 (latest rpt) | M6: FPO +1E | N6: FPO +2E
A7: Revenue (USD mm) | B7: Company | C7: =IFERROR(INDEX('SW Metrics'!$C$6:$C$104,MATCH($B$4,'SW Metrics'!$A$6:$A$104,0)),"") | D7: =IFERROR(INDEX('SW Metrics'!$D$6:$D$104,MATCH($B$4,'SW Metrics'!$A$6:$A$104,0)),"") | E7: =IFERROR(INDEX('SW Metrics'!$E$6:$E$104,MATCH($B$4,'SW Metrics'!$A$6:$A$104,0)),"") | F7: =IFERROR(INDEX('SW Metrics'!$F$6:$F$104,MATCH($B$4,'SW Metrics'!$A$6:$A$104,0)),"") | G7: =IFERROR(INDEX('SW Metrics'!$G$6:$G$104,MATCH($B$4,'SW Metrics'!$A$6:$A$104,0)),"") | H7: =IFERROR(INDEX('SW Metrics'!$H$6:$H$104,MATCH($B$4,'SW Metrics'!$A$6:$A$104,0)),"") | I7: =IFERROR(INDEX('SW Metrics'!$I$6:$I$104,MATCH($B$4,'SW Metrics'!$A$6:$A$104,0)),"") | J7: =IFERROR(INDEX('SW Metrics'!$J$6:$J$104,MATCH($B$4,'SW Metrics'!$A$6:$A$104,0)),"") | K7: =IFERROR(INDEX('SW Metrics'!$K$6:$K$104,MATCH($B$4,'SW Metrics'!$A$6:$A$104,0)),"") | L7: =IFERROR(INDEX('SW Metrics'!$L$6:$L$104,MATCH($B$4,'SW Metrics'!$A$6:$A$104,0)),"") | M7: =IFERROR(INDEX('SW Metrics'!$M$6:$M$104,MATCH($B$4,'SW Metrics'!$A$6:$A$104,0)),"") | N7: =IFERROR(INDEX('SW Metrics'!$N$6:$N$104,MATCH($B$4,'SW Metrics'!$A$6:$A$104,0)),"")
B8: Peer median | C8: =IFERROR(MEDIAN('SW Metrics'!$C$6:$C$104),"") | D8: =IFERROR(MEDIAN('SW Metrics'!$D$6:$D$104),"") | E8: =IFERROR(MEDIAN('SW Metrics'!$E$6:$E$104),"") | F8: =IFERROR(MEDIAN('SW Metrics'!$F$6:$F$104),"") | G8: =IFERROR(MEDIAN('SW Metrics'!$G$6:$G$104),"") | H8: =IFERROR(MEDIAN('SW Metrics'!$H$6:$H$104),"") | I8: =IFERROR(MEDIAN('SW Metrics'!$I$6:$I$104),"") | J8: =IFERROR(MEDIAN('SW Metrics'!$J$6:$J$104),"") | K8: =IFERROR(MEDIAN('SW Metrics'!$K$6:$K$104),"") | L8: =IFERROR(MEDIAN('SW Metrics'!$L$6:$L$104),"") | M8: =IFERROR(MEDIAN('SW Metrics'!$M$6:$M$104),"") | N8: =IFERROR(MEDIAN('SW Metrics'!$N$6:$N$104),"")
B9: vs median | C9: =IF(OR(C7="",C8=""),"",C7-C8) | D9: =IF(OR(D7="",D8=""),"",D7-D8) | E9: =IF(OR(E7="",E8=""),"",E7-E8) | F9: =IF(OR(F7="",F8=""),"",F7-F8) | G9: =IF(OR(G7="",G8=""),"",G7-G8) | H9: =IF(OR(H7="",H8=""),"",H7-H8) | I9: =IF(OR(I7="",I8=""),"",I7-I8) | J9: =IF(OR(J7="",J8=""),"",J7-J8) | ... N9: =IF(OR(N7="",N8=""),"",N7-N8)
A11: Revenue growth YoY % | B11: Company | C11: =IFERROR(INDEX('SW Metrics'!$C$108:$C$206,MATCH($B$4,'SW Metrics'!$A$108:$A$206,0)),"") | D11: =IFERROR(INDEX('SW Metrics'!$D$108:$D$206,MATCH($B$4,'SW Metrics'!$A$108:$A$206,0)),"") | E11: =IFERROR(INDEX('SW Metrics'!$E$108:$E$206,MATCH($B$4,'SW Metrics'!$A$108:$A$206,0)),"") | F11: =IFERROR(INDEX('SW Metrics'!$F$108:$F$206,MATCH($B$4,'SW Metrics'!$A$108:$A$206,0)),"") | G11: =IFERROR(INDEX('SW Metrics'!$G$108:$G$206,MATCH($B$4,'SW Metrics'!$A$108:$A$206,0)),"") | H11: =IFERROR(INDEX('SW Metrics'!$H$108:$H$206,MATCH($B$4,'SW Metrics'!$A$108:$A$206,0)),"") | I11: =IFERROR(INDEX('SW Metrics'!$I$108:$I$206,MATCH($B$4,'SW Metrics'!$A$108:$A$206,0)),"") | J11: =IFERROR(INDEX('SW Metrics'!$J$108:$J$206,MATCH($B$4,'SW Metrics'!$A$108:$A$206,0)),"") | K11: =IFERROR(INDEX('SW Metrics'!$K$108:$K$206,MATCH($B$4,'SW Metrics'!$A$108:$A$206,0)),"") | L11: =IFERROR(INDEX('SW Metrics'!$L$108:$L$206,MATCH($B$4,'SW Metrics'!$A$108:$A$206,0)),"") | M11: =IFERROR(INDEX('SW Metrics'!$M$108:$M$206,MATCH($B$4,'SW Metrics'!$A$108:$A$206,0)),"") | N11: =IFERROR(INDEX('SW Metrics'!$N$108:$N$206,MATCH($B$4,'SW Metrics'!$A$108:$A$206,0)),"")
B12: Peer median | C12: =IFERROR(MEDIAN('SW Metrics'!$C$108:$C$206),"") | D12: =IFERROR(MEDIAN('SW Metrics'!$D$108:$D$206),"") | E12: =IFERROR(MEDIAN('SW Metrics'!$E$108:$E$206),"") | F12: =IFERROR(MEDIAN('SW Metrics'!$F$108:$F$206),"") | G12: =IFERROR(MEDIAN('SW Metrics'!$G$108:$G$206),"") | H12: =IFERROR(MEDIAN('SW Metrics'!$H$108:$H$206),"") | I12: =IFERROR(MEDIAN('SW Metrics'!$I$108:$I$206),"") | J12: =IFERROR(MEDIAN('SW Metrics'!$J$108:$J$206),"") | K12: =IFERROR(MEDIAN('SW Metrics'!$K$108:$K$206),"") | L12: =IFERROR(MEDIAN('SW Metrics'!$L$108:$L$206),"") | M12: =IFERROR(MEDIAN('SW Metrics'!$M$108:$M$206),"") | N12: =IFERROR(MEDIAN('SW Metrics'!$N$108:$N$206),"")
B13: vs median | C13: =IF(OR(C11="",C12=""),"",C11-C12) | D13: =IF(OR(D11="",D12=""),"",D11-D12) | E13: =IF(OR(E11="",E12=""),"",E11-E12) | F13: =IF(OR(F11="",F12=""),"",F11-F12) | G13: =IF(OR(G11="",G12=""),"",G11-G12) | H13: =IF(OR(H11="",H12=""),"",H11-H12) | I13: =IF(OR(I11="",I12=""),"",I11-I12) | J13: =IF(OR(J11="",J12=""),"",J11-J12) | ... N13: =IF(OR(N11="",N12=""),"",N11-N12)
A15: Revenue growth QoQ % | B15: Company | C15: =IFERROR(INDEX('SW Metrics'!$C$210:$C$308,MATCH($B$4,'SW Metrics'!$A$210:$A$308,0)),"") | D15: =IFERROR(INDEX('SW Metrics'!$D$210:$D$308,MATCH($B$4,'SW Metrics'!$A$210:$A$308,0)),"") | E15: =IFERROR(INDEX('SW Metrics'!$E$210:$E$308,MATCH($B$4,'SW Metrics'!$A$210:$A$308,0)),"") | F15: =IFERROR(INDEX('SW Metrics'!$F$210:$F$308,MATCH($B$4,'SW Metrics'!$A$210:$A$308,0)),"") | G15: =IFERROR(INDEX('SW Metrics'!$G$210:$G$308,MATCH($B$4,'SW Metrics'!$A$210:$A$308,0)),"") | H15: =IFERROR(INDEX('SW Metrics'!$H$210:$H$308,MATCH($B$4,'SW Metrics'!$A$210:$A$308,0)),"") | I15: =IFERROR(INDEX('SW Metrics'!$I$210:$I$308,MATCH($B$4,'SW Metrics'!$A$210:$A$308,0)),"") | J15: =IFERROR(INDEX('SW Metrics'!$J$210:$J$308,MATCH($B$4,'SW Metrics'!$A$210:$A$308,0)),"") | K15: =IFERROR(INDEX('SW Metrics'!$K$210:$K$308,MATCH($B$4,'SW Metrics'!$A$210:$A$308,0)),"") | L15: =IFERROR(INDEX('SW Metrics'!$L$210:$L$308,MATCH($B$4,'SW Metrics'!$A$210:$A$308,0)),"") | M15: =IFERROR(INDEX('SW Metrics'!$M$210:$M$308,MATCH($B$4,'SW Metrics'!$A$210:$A$308,0)),"") | N15: =IFERROR(INDEX('SW Metrics'!$N$210:$N$308,MATCH($B$4,'SW Metrics'!$A$210:$A$308,0)),"")
B16: Peer median | C16: =IFERROR(MEDIAN('SW Metrics'!$C$210:$C$308),"") | D16: =IFERROR(MEDIAN('SW Metrics'!$D$210:$D$308),"") | E16: =IFERROR(MEDIAN('SW Metrics'!$E$210:$E$308),"") | F16: =IFERROR(MEDIAN('SW Metrics'!$F$210:$F$308),"") | G16: =IFERROR(MEDIAN('SW Metrics'!$G$210:$G$308),"") | H16: =IFERROR(MEDIAN('SW Metrics'!$H$210:$H$308),"") | I16: =IFERROR(MEDIAN('SW Metrics'!$I$210:$I$308),"") | J16: =IFERROR(MEDIAN('SW Metrics'!$J$210:$J$308),"") | K16: =IFERROR(MEDIAN('SW Metrics'!$K$210:$K$308),"") | L16: =IFERROR(MEDIAN('SW Metrics'!$L$210:$L$308),"") | M16: =IFERROR(MEDIAN('SW Metrics'!$M$210:$M$308),"") | N16: =IFERROR(MEDIAN('SW Metrics'!$N$210:$N$308),"")
B17: vs median | C17: =IF(OR(C15="",C16=""),"",C15-C16) | D17: =IF(OR(D15="",D16=""),"",D15-D16) | E17: =IF(OR(E15="",E16=""),"",E15-E16) | F17: =IF(OR(F15="",F16=""),"",F15-F16) | G17: =IF(OR(G15="",G16=""),"",G15-G16) | H17: =IF(OR(H15="",H16=""),"",H15-H16) | I17: =IF(OR(I15="",I16=""),"",I15-I16) | J17: =IF(OR(J15="",J16=""),"",J15-J16) | ... N17: =IF(OR(N15="",N16=""),"",N15-N16)
A19: $ Added YoY (USD mm) | B19: Company | C19: =IFERROR(INDEX('SW Metrics'!$C$312:$C$410,MATCH($B$4,'SW Metrics'!$A$312:$A$410,0)),"") | D19: =IFERROR(INDEX('SW Metrics'!$D$312:$D$410,MATCH($B$4,'SW Metrics'!$A$312:$A$410,0)),"") | E19: =IFERROR(INDEX('SW Metrics'!$E$312:$E$410,MATCH($B$4,'SW Metrics'!$A$312:$A$410,0)),"") | F19: =IFERROR(INDEX('SW Metrics'!$F$312:$F$410,MATCH($B$4,'SW Metrics'!$A$312:$A$410,0)),"") | G19: =IFERROR(INDEX('SW Metrics'!$G$312:$G$410,MATCH($B$4,'SW Metrics'!$A$312:$A$410,0)),"") | H19: =IFERROR(INDEX('SW Metrics'!$H$312:$H$410,MATCH($B$4,'SW Metrics'!$A$312:$A$410,0)),"") | I19: =IFERROR(INDEX('SW Metrics'!$I$312:$I$410,MATCH($B$4,'SW Metrics'!$A$312:$A$410,0)),"") | J19: =IFERROR(INDEX('SW Metrics'!$J$312:$J$410,MATCH($B$4,'SW Metrics'!$A$312:$A$410,0)),"") | K19: =IFERROR(INDEX('SW Metrics'!$K$312:$K$410,MATCH($B$4,'SW Metrics'!$A$312:$A$410,0)),"") | L19: =IFERROR(INDEX('SW Metrics'!$L$312:$L$410,MATCH($B$4,'SW Metrics'!$A$312:$A$410,0)),"") | M19: =IFERROR(INDEX('SW Metrics'!$M$312:$M$410,MATCH($B$4,'SW Metrics'!$A$312:$A$410,0)),"") | N19: =IFERROR(INDEX('SW Metrics'!$N$312:$N$410,MATCH($B$4,'SW Metrics'!$A$312:$A$410,0)),"")
B20: Peer median | C20: =IFERROR(MEDIAN('SW Metrics'!$C$312:$C$410),"") | D20: =IFERROR(MEDIAN('SW Metrics'!$D$312:$D$410),"") | E20: =IFERROR(MEDIAN('SW Metrics'!$E$312:$E$410),"") | F20: =IFERROR(MEDIAN('SW Metrics'!$F$312:$F$410),"") | G20: =IFERROR(MEDIAN('SW Metrics'!$G$312:$G$410),"") | H20: =IFERROR(MEDIAN('SW Metrics'!$H$312:$H$410),"") | I20: =IFERROR(MEDIAN('SW Metrics'!$I$312:$I$410),"") | J20: =IFERROR(MEDIAN('SW Metrics'!$J$312:$J$410),"") | K20: =IFERROR(MEDIAN('SW Metrics'!$K$312:$K$410),"") | L20: =IFERROR(MEDIAN('SW Metrics'!$L$312:$L$410),"") | M20: =IFERROR(MEDIAN('SW Metrics'!$M$312:$M$410),"") | N20: =IFERROR(MEDIAN('SW Metrics'!$N$312:$N$410),"")
B21: vs median | C21: =IF(OR(C19="",C20=""),"",C19-C20) | D21: =IF(OR(D19="",D20=""),"",D19-D20) | E21: =IF(OR(E19="",E20=""),"",E19-E20) | F21: =IF(OR(F19="",F20=""),"",F19-F20) | G21: =IF(OR(G19="",G20=""),"",G19-G20) | H21: =IF(OR(H19="",H20=""),"",H19-H20) | I21: =IF(OR(I19="",I20=""),"",I19-I20) | J21: =IF(OR(J19="",J20=""),"",J19-J20) | ... N21: =IF(OR(N19="",N20=""),"",N19-N20)
A23: $ Added QoQ (USD mm) | B23: Company | C23: =IFERROR(INDEX('SW Metrics'!$C$414:$C$512,MATCH($B$4,'SW Metrics'!$A$414:$A$512,0)),"") | D23: =IFERROR(INDEX('SW Metrics'!$D$414:$D$512,MATCH($B$4,'SW Metrics'!$A$414:$A$512,0)),"") | E23: =IFERROR(INDEX('SW Metrics'!$E$414:$E$512,MATCH($B$4,'SW Metrics'!$A$414:$A$512,0)),"") | F23: =IFERROR(INDEX('SW Metrics'!$F$414:$F$512,MATCH($B$4,'SW Metrics'!$A$414:$A$512,0)),"") | G23: =IFERROR(INDEX('SW Metrics'!$G$414:$G$512,MATCH($B$4,'SW Metrics'!$A$414:$A$512,0)),"") | H23: =IFERROR(INDEX('SW Metrics'!$H$414:$H$512,MATCH($B$4,'SW Metrics'!$A$414:$A$512,0)),"") | I23: =IFERROR(INDEX('SW Metrics'!$I$414:$I$512,MATCH($B$4,'SW Metrics'!$A$414:$A$512,0)),"") | J23: =IFERROR(INDEX('SW Metrics'!$J$414:$J$512,MATCH($B$4,'SW Metrics'!$A$414:$A$512,0)),"") | K23: =IFERROR(INDEX('SW Metrics'!$K$414:$K$512,MATCH($B$4,'SW Metrics'!$A$414:$A$512,0)),"") | L23: =IFERROR(INDEX('SW Metrics'!$L$414:$L$512,MATCH($B$4,'SW Metrics'!$A$414:$A$512,0)),"") | M23: =IFERROR(INDEX('SW Metrics'!$M$414:$M$512,MATCH($B$4,'SW Metrics'!$A$414:$A$512,0)),"") | N23: =IFERROR(INDEX('SW Metrics'!$N$414:$N$512,MATCH($B$4,'SW Metrics'!$A$414:$A$512,0)),"")
B24: Peer median | C24: =IFERROR(MEDIAN('SW Metrics'!$C$414:$C$512),"") | D24: =IFERROR(MEDIAN('SW Metrics'!$D$414:$D$512),"") | E24: =IFERROR(MEDIAN('SW Metrics'!$E$414:$E$512),"") | F24: =IFERROR(MEDIAN('SW Metrics'!$F$414:$F$512),"") | G24: =IFERROR(MEDIAN('SW Metrics'!$G$414:$G$512),"") | H24: =IFERROR(MEDIAN('SW Metrics'!$H$414:$H$512),"") | I24: =IFERROR(MEDIAN('SW Metrics'!$I$414:$I$512),"") | J24: =IFERROR(MEDIAN('SW Metrics'!$J$414:$J$512),"") | K24: =IFERROR(MEDIAN('SW Metrics'!$K$414:$K$512),"") | L24: =IFERROR(MEDIAN('SW Metrics'!$L$414:$L$512),"") | M24: =IFERROR(MEDIAN('SW Metrics'!$M$414:$M$512),"") | N24: =IFERROR(MEDIAN('SW Metrics'!$N$414:$N$512),"")
B25: vs median | C25: =IF(OR(C23="",C24=""),"",C23-C24) | D25: =IF(OR(D23="",D24=""),"",D23-D24) | E25: =IF(OR(E23="",E24=""),"",E23-E24) | F25: =IF(OR(F23="",F24=""),"",F23-F24) | G25: =IF(OR(G23="",G24=""),"",G23-G24) | H25: =IF(OR(H23="",H24=""),"",H23-H24) | I25: =IF(OR(I23="",I24=""),"",I23-I24) | J25: =IF(OR(J23="",J24=""),"",J23-J24) | ... N25: =IF(OR(N23="",N24=""),"",N23-N24)
A27: Op margin % | B27: Company | C27: =IFERROR(INDEX('SW Metrics'!$C$516:$C$614,MATCH($B$4,'SW Metrics'!$A$516:$A$614,0)),"") | D27: =IFERROR(INDEX('SW Metrics'!$D$516:$D$614,MATCH($B$4,'SW Metrics'!$A$516:$A$614,0)),"") | E27: =IFERROR(INDEX('SW Metrics'!$E$516:$E$614,MATCH($B$4,'SW Metrics'!$A$516:$A$614,0)),"") | F27: =IFERROR(INDEX('SW Metrics'!$F$516:$F$614,MATCH($B$4,'SW Metrics'!$A$516:$A$614,0)),"") | G27: =IFERROR(INDEX('SW Metrics'!$G$516:$G$614,MATCH($B$4,'SW Metrics'!$A$516:$A$614,0)),"") | H27: =IFERROR(INDEX('SW Metrics'!$H$516:$H$614,MATCH($B$4,'SW Metrics'!$A$516:$A$614,0)),"") | I27: =IFERROR(INDEX('SW Metrics'!$I$516:$I$614,MATCH($B$4,'SW Metrics'!$A$516:$A$614,0)),"") | J27: =IFERROR(INDEX('SW Metrics'!$J$516:$J$614,MATCH($B$4,'SW Metrics'!$A$516:$A$614,0)),"") | K27: =IFERROR(INDEX('SW Metrics'!$K$516:$K$614,MATCH($B$4,'SW Metrics'!$A$516:$A$614,0)),"") | L27: =IFERROR(INDEX('SW Metrics'!$L$516:$L$614,MATCH($B$4,'SW Metrics'!$A$516:$A$614,0)),"") | M27: =IFERROR(INDEX('SW Metrics'!$M$516:$M$614,MATCH($B$4,'SW Metrics'!$A$516:$A$614,0)),"") | N27: =IFERROR(INDEX('SW Metrics'!$N$516:$N$614,MATCH($B$4,'SW Metrics'!$A$516:$A$614,0)),"")
B28: Peer median | C28: =IFERROR(MEDIAN('SW Metrics'!$C$516:$C$614),"") | D28: =IFERROR(MEDIAN('SW Metrics'!$D$516:$D$614),"") | E28: =IFERROR(MEDIAN('SW Metrics'!$E$516:$E$614),"") | F28: =IFERROR(MEDIAN('SW Metrics'!$F$516:$F$614),"") | G28: =IFERROR(MEDIAN('SW Metrics'!$G$516:$G$614),"") | H28: =IFERROR(MEDIAN('SW Metrics'!$H$516:$H$614),"") | I28: =IFERROR(MEDIAN('SW Metrics'!$I$516:$I$614),"") | J28: =IFERROR(MEDIAN('SW Metrics'!$J$516:$J$614),"") | K28: =IFERROR(MEDIAN('SW Metrics'!$K$516:$K$614),"") | L28: =IFERROR(MEDIAN('SW Metrics'!$L$516:$L$614),"") | M28: =IFERROR(MEDIAN('SW Metrics'!$M$516:$M$614),"") | N28: =IFERROR(MEDIAN('SW Metrics'!$N$516:$N$614),"")
B29: vs median | C29: =IF(OR(C27="",C28=""),"",C27-C28) | D29: =IF(OR(D27="",D28=""),"",D27-D28) | E29: =IF(OR(E27="",E28=""),"",E27-E28) | F29: =IF(OR(F27="",F28=""),"",F27-F28) | G29: =IF(OR(G27="",G28=""),"",G27-G28) | H29: =IF(OR(H27="",H28=""),"",H27-H28) | I29: =IF(OR(I27="",I28=""),"",I27-I28) | J29: =IF(OR(J27="",J28=""),"",J27-J28) | ... N29: =IF(OR(N27="",N28=""),"",N27-N28)
A31: Op margin Δ YoY (bps) | B31: Company | C31: =IFERROR(INDEX('SW Metrics'!$C$618:$C$716,MATCH($B$4,'SW Metrics'!$A$618:$A$716,0)),"") | D31: =IFERROR(INDEX('SW Metrics'!$D$618:$D$716,MATCH($B$4,'SW Metrics'!$A$618:$A$716,0)),"") | E31: =IFERROR(INDEX('SW Metrics'!$E$618:$E$716,MATCH($B$4,'SW Metrics'!$A$618:$A$716,0)),"") | F31: =IFERROR(INDEX('SW Metrics'!$F$618:$F$716,MATCH($B$4,'SW Metrics'!$A$618:$A$716,0)),"") | G31: =IFERROR(INDEX('SW Metrics'!$G$618:$G$716,MATCH($B$4,'SW Metrics'!$A$618:$A$716,0)),"") | H31: =IFERROR(INDEX('SW Metrics'!$H$618:$H$716,MATCH($B$4,'SW Metrics'!$A$618:$A$716,0)),"") | I31: =IFERROR(INDEX('SW Metrics'!$I$618:$I$716,MATCH($B$4,'SW Metrics'!$A$618:$A$716,0)),"") | J31: =IFERROR(INDEX('SW Metrics'!$J$618:$J$716,MATCH($B$4,'SW Metrics'!$A$618:$A$716,0)),"") | K31: =IFERROR(INDEX('SW Metrics'!$K$618:$K$716,MATCH($B$4,'SW Metrics'!$A$618:$A$716,0)),"") | L31: =IFERROR(INDEX('SW Metrics'!$L$618:$L$716,MATCH($B$4,'SW Metrics'!$A$618:$A$716,0)),"") | M31: =IFERROR(INDEX('SW Metrics'!$M$618:$M$716,MATCH($B$4,'SW Metrics'!$A$618:$A$716,0)),"") | N31: =IFERROR(INDEX('SW Metrics'!$N$618:$N$716,MATCH($B$4,'SW Metrics'!$A$618:$A$716,0)),"")
B32: Peer median | C32: =IFERROR(MEDIAN('SW Metrics'!$C$618:$C$716),"") | D32: =IFERROR(MEDIAN('SW Metrics'!$D$618:$D$716),"") | E32: =IFERROR(MEDIAN('SW Metrics'!$E$618:$E$716),"") | F32: =IFERROR(MEDIAN('SW Metrics'!$F$618:$F$716),"") | G32: =IFERROR(MEDIAN('SW Metrics'!$G$618:$G$716),"") | H32: =IFERROR(MEDIAN('SW Metrics'!$H$618:$H$716),"") | I32: =IFERROR(MEDIAN('SW Metrics'!$I$618:$I$716),"") | J32: =IFERROR(MEDIAN('SW Metrics'!$J$618:$J$716),"") | K32: =IFERROR(MEDIAN('SW Metrics'!$K$618:$K$716),"") | L32: =IFERROR(MEDIAN('SW Metrics'!$L$618:$L$716),"") | M32: =IFERROR(MEDIAN('SW Metrics'!$M$618:$M$716),"") | N32: =IFERROR(MEDIAN('SW Metrics'!$N$618:$N$716),"")
B33: vs median | C33: =IF(OR(C31="",C32=""),"",C31-C32) | D33: =IF(OR(D31="",D32=""),"",D31-D32) | E33: =IF(OR(E31="",E32=""),"",E31-E32) | F33: =IF(OR(F31="",F32=""),"",F31-F32) | G33: =IF(OR(G31="",G32=""),"",G31-G32) | H33: =IF(OR(H31="",H32=""),"",H31-H32) | I33: =IF(OR(I31="",I32=""),"",I31-I32) | J33: =IF(OR(J31="",J32=""),"",J31-J32) | ... N33: =IF(OR(N31="",N32=""),"",N31-N32)
A35: Op income YoY % | B35: Company | C35: =IFERROR(INDEX('SW Metrics'!$C$720:$C$818,MATCH($B$4,'SW Metrics'!$A$720:$A$818,0)),"") | D35: =IFERROR(INDEX('SW Metrics'!$D$720:$D$818,MATCH($B$4,'SW Metrics'!$A$720:$A$818,0)),"") | E35: =IFERROR(INDEX('SW Metrics'!$E$720:$E$818,MATCH($B$4,'SW Metrics'!$A$720:$A$818,0)),"") | F35: =IFERROR(INDEX('SW Metrics'!$F$720:$F$818,MATCH($B$4,'SW Metrics'!$A$720:$A$818,0)),"") | G35: =IFERROR(INDEX('SW Metrics'!$G$720:$G$818,MATCH($B$4,'SW Metrics'!$A$720:$A$818,0)),"") | H35: =IFERROR(INDEX('SW Metrics'!$H$720:$H$818,MATCH($B$4,'SW Metrics'!$A$720:$A$818,0)),"") | I35: =IFERROR(INDEX('SW Metrics'!$I$720:$I$818,MATCH($B$4,'SW Metrics'!$A$720:$A$818,0)),"") | J35: =IFERROR(INDEX('SW Metrics'!$J$720:$J$818,MATCH($B$4,'SW Metrics'!$A$720:$A$818,0)),"") | K35: =IFERROR(INDEX('SW Metrics'!$K$720:$K$818,MATCH($B$4,'SW Metrics'!$A$720:$A$818,0)),"") | L35: =IFERROR(INDEX('SW Metrics'!$L$720:$L$818,MATCH($B$4,'SW Metrics'!$A$720:$A$818,0)),"") | M35: =IFERROR(INDEX('SW Metrics'!$M$720:$M$818,MATCH($B$4,'SW Metrics'!$A$720:$A$818,0)),"") | N35: =IFERROR(INDEX('SW Metrics'!$N$720:$N$818,MATCH($B$4,'SW Metrics'!$A$720:$A$818,0)),"")
B36: Peer median | C36: =IFERROR(MEDIAN('SW Metrics'!$C$720:$C$818),"") | D36: =IFERROR(MEDIAN('SW Metrics'!$D$720:$D$818),"") | E36: =IFERROR(MEDIAN('SW Metrics'!$E$720:$E$818),"") | F36: =IFERROR(MEDIAN('SW Metrics'!$F$720:$F$818),"") | G36: =IFERROR(MEDIAN('SW Metrics'!$G$720:$G$818),"") | H36: =IFERROR(MEDIAN('SW Metrics'!$H$720:$H$818),"") | I36: =IFERROR(MEDIAN('SW Metrics'!$I$720:$I$818),"") | J36: =IFERROR(MEDIAN('SW Metrics'!$J$720:$J$818),"") | K36: =IFERROR(MEDIAN('SW Metrics'!$K$720:$K$818),"") | L36: =IFERROR(MEDIAN('SW Metrics'!$L$720:$L$818),"") | M36: =IFERROR(MEDIAN('SW Metrics'!$M$720:$M$818),"") | N36: =IFERROR(MEDIAN('SW Metrics'!$N$720:$N$818),"")
B37: vs median | C37: =IF(OR(C35="",C36=""),"",C35-C36) | D37: =IF(OR(D35="",D36=""),"",D35-D36) | E37: =IF(OR(E35="",E36=""),"",E35-E36) | F37: =IF(OR(F35="",F36=""),"",F35-F36) | G37: =IF(OR(G35="",G36=""),"",G35-G36) | H37: =IF(OR(H35="",H36=""),"",H35-H36) | I37: =IF(OR(I35="",I36=""),"",I35-I36) | J37: =IF(OR(J35="",J36=""),"",J35-J36) | ... N37: =IF(OR(N35="",N36=""),"",N35-N36)
A39: Incremental OpM % (leverage) | B39: Company | C39: =IFERROR(INDEX('SW Metrics'!$C$822:$C$920,MATCH($B$4,'SW Metrics'!$A$822:$A$920,0)),"") | D39: =IFERROR(INDEX('SW Metrics'!$D$822:$D$920,MATCH($B$4,'SW Metrics'!$A$822:$A$920,0)),"") | E39: =IFERROR(INDEX('SW Metrics'!$E$822:$E$920,MATCH($B$4,'SW Metrics'!$A$822:$A$920,0)),"") | F39: =IFERROR(INDEX('SW Metrics'!$F$822:$F$920,MATCH($B$4,'SW Metrics'!$A$822:$A$920,0)),"") | G39: =IFERROR(INDEX('SW Metrics'!$G$822:$G$920,MATCH($B$4,'SW Metrics'!$A$822:$A$920,0)),"") | H39: =IFERROR(INDEX('SW Metrics'!$H$822:$H$920,MATCH($B$4,'SW Metrics'!$A$822:$A$920,0)),"") | I39: =IFERROR(INDEX('SW Metrics'!$I$822:$I$920,MATCH($B$4,'SW Metrics'!$A$822:$A$920,0)),"") | J39: =IFERROR(INDEX('SW Metrics'!$J$822:$J$920,MATCH($B$4,'SW Metrics'!$A$822:$A$920,0)),"") | K39: =IFERROR(INDEX('SW Metrics'!$K$822:$K$920,MATCH($B$4,'SW Metrics'!$A$822:$A$920,0)),"") | L39: =IFERROR(INDEX('SW Metrics'!$L$822:$L$920,MATCH($B$4,'SW Metrics'!$A$822:$A$920,0)),"") | M39: =IFERROR(INDEX('SW Metrics'!$M$822:$M$920,MATCH($B$4,'SW Metrics'!$A$822:$A$920,0)),"") | N39: =IFERROR(INDEX('SW Metrics'!$N$822:$N$920,MATCH($B$4,'SW Metrics'!$A$822:$A$920,0)),"")
B40: Peer median | C40: =IFERROR(MEDIAN('SW Metrics'!$C$822:$C$920),"") | D40: =IFERROR(MEDIAN('SW Metrics'!$D$822:$D$920),"") | E40: =IFERROR(MEDIAN('SW Metrics'!$E$822:$E$920),"") | F40: =IFERROR(MEDIAN('SW Metrics'!$F$822:$F$920),"") | G40: =IFERROR(MEDIAN('SW Metrics'!$G$822:$G$920),"") | H40: =IFERROR(MEDIAN('SW Metrics'!$H$822:$H$920),"") | I40: =IFERROR(MEDIAN('SW Metrics'!$I$822:$I$920),"") | J40: =IFERROR(MEDIAN('SW Metrics'!$J$822:$J$920),"") | K40: =IFERROR(MEDIAN('SW Metrics'!$K$822:$K$920),"") | L40: =IFERROR(MEDIAN('SW Metrics'!$L$822:$L$920),"") | M40: =IFERROR(MEDIAN('SW Metrics'!$M$822:$M$920),"") | N40: =IFERROR(MEDIAN('SW Metrics'!$N$822:$N$920),"")
B41: vs median | C41: =IF(OR(C39="",C40=""),"",C39-C40) | D41: =IF(OR(D39="",D40=""),"",D39-D40) | E41: =IF(OR(E39="",E40=""),"",E39-E40) | F41: =IF(OR(F39="",F40=""),"",F39-F40) | G41: =IF(OR(G39="",G40=""),"",G39-G40) | H41: =IF(OR(H39="",H40=""),"",H39-H40) | I41: =IF(OR(I39="",I40=""),"",I39-I40) | J41: =IF(OR(J39="",J40=""),"",J39-J40) | ... N41: =IF(OR(N39="",N40=""),"",N39-N40)
A43: FCF margin LTM % | B43: Company | C43: =IFERROR(INDEX('SW Metrics'!$C$924:$C$1022,MATCH($B$4,'SW Metrics'!$A$924:$A$1022,0)),"") | D43: =IFERROR(INDEX('SW Metrics'!$D$924:$D$1022,MATCH($B$4,'SW Metrics'!$A$924:$A$1022,0)),"") | E43: =IFERROR(INDEX('SW Metrics'!$E$924:$E$1022,MATCH($B$4,'SW Metrics'!$A$924:$A$1022,0)),"") | F43: =IFERROR(INDEX('SW Metrics'!$F$924:$F$1022,MATCH($B$4,'SW Metrics'!$A$924:$A$1022,0)),"") | G43: =IFERROR(INDEX('SW Metrics'!$G$924:$G$1022,MATCH($B$4,'SW Metrics'!$A$924:$A$1022,0)),"") | H43: =IFERROR(INDEX('SW Metrics'!$H$924:$H$1022,MATCH($B$4,'SW Metrics'!$A$924:$A$1022,0)),"") | I43: =IFERROR(INDEX('SW Metrics'!$I$924:$I$1022,MATCH($B$4,'SW Metrics'!$A$924:$A$1022,0)),"") | J43: =IFERROR(INDEX('SW Metrics'!$J$924:$J$1022,MATCH($B$4,'SW Metrics'!$A$924:$A$1022,0)),"") | K43: =IFERROR(INDEX('SW Metrics'!$K$924:$K$1022,MATCH($B$4,'SW Metrics'!$A$924:$A$1022,0)),"") | L43: =IFERROR(INDEX('SW Metrics'!$L$924:$L$1022,MATCH($B$4,'SW Metrics'!$A$924:$A$1022,0)),"") | M43: =IFERROR(INDEX('SW Metrics'!$M$924:$M$1022,MATCH($B$4,'SW Metrics'!$A$924:$A$1022,0)),"") | N43: =IFERROR(INDEX('SW Metrics'!$N$924:$N$1022,MATCH($B$4,'SW Metrics'!$A$924:$A$1022,0)),"")
B44: Peer median | C44: =IFERROR(MEDIAN('SW Metrics'!$C$924:$C$1022),"") | D44: =IFERROR(MEDIAN('SW Metrics'!$D$924:$D$1022),"") | E44: =IFERROR(MEDIAN('SW Metrics'!$E$924:$E$1022),"") | F44: =IFERROR(MEDIAN('SW Metrics'!$F$924:$F$1022),"") | G44: =IFERROR(MEDIAN('SW Metrics'!$G$924:$G$1022),"") | H44: =IFERROR(MEDIAN('SW Metrics'!$H$924:$H$1022),"") | I44: =IFERROR(MEDIAN('SW Metrics'!$I$924:$I$1022),"") | J44: =IFERROR(MEDIAN('SW Metrics'!$J$924:$J$1022),"") | K44: =IFERROR(MEDIAN('SW Metrics'!$K$924:$K$1022),"") | L44: =IFERROR(MEDIAN('SW Metrics'!$L$924:$L$1022),"") | M44: =IFERROR(MEDIAN('SW Metrics'!$M$924:$M$1022),"") | N44: =IFERROR(MEDIAN('SW Metrics'!$N$924:$N$1022),"")
B45: vs median | C45: =IF(OR(C43="",C44=""),"",C43-C44) | D45: =IF(OR(D43="",D44=""),"",D43-D44) | E45: =IF(OR(E43="",E44=""),"",E43-E44) | F45: =IF(OR(F43="",F44=""),"",F43-F44) | G45: =IF(OR(G43="",G44=""),"",G43-G44) | H45: =IF(OR(H43="",H44=""),"",H43-H44) | I45: =IF(OR(I43="",I44=""),"",I43-I44) | J45: =IF(OR(J43="",J44=""),"",J43-J44) | ... N45: =IF(OR(N43="",N44=""),"",N43-N44)
A47: FCF margin Δ YoY (bps) | B47: Company | C47: =IFERROR(INDEX('SW Metrics'!$C$1026:$C$1124,MATCH($B$4,'SW Metrics'!$A$1026:$A$1124,0)),"") | D47: =IFERROR(INDEX('SW Metrics'!$D$1026:$D$1124,MATCH($B$4,'SW Metrics'!$A$1026:$A$1124,0)),"") | E47: =IFERROR(INDEX('SW Metrics'!$E$1026:$E$1124,MATCH($B$4,'SW Metrics'!$A$1026:$A$1124,0)),"") | F47: =IFERROR(INDEX('SW Metrics'!$F$1026:$F$1124,MATCH($B$4,'SW Metrics'!$A$1026:$A$1124,0)),"") | G47: =IFERROR(INDEX('SW Metrics'!$G$1026:$G$1124,MATCH($B$4,'SW Metrics'!$A$1026:$A$1124,0)),"") | H47: =IFERROR(INDEX('SW Metrics'!$H$1026:$H$1124,MATCH($B$4,'SW Metrics'!$A$1026:$A$1124,0)),"") | I47: =IFERROR(INDEX('SW Metrics'!$I$1026:$I$1124,MATCH($B$4,'SW Metrics'!$A$1026:$A$1124,0)),"") | J47: =IFERROR(INDEX('SW Metrics'!$J$1026:$J$1124,MATCH($B$4,'SW Metrics'!$A$1026:$A$1124,0)),"") | K47: =IFERROR(INDEX('SW Metrics'!$K$1026:$K$1124,MATCH($B$4,'SW Metrics'!$A$1026:$A$1124,0)),"") | L47: =IFERROR(INDEX('SW Metrics'!$L$1026:$L$1124,MATCH($B$4,'SW Metrics'!$A$1026:$A$1124,0)),"") | M47: =IFERROR(INDEX('SW Metrics'!$M$1026:$M$1124,MATCH($B$4,'SW Metrics'!$A$1026:$A$1124,0)),"") | N47: =IFERROR(INDEX('SW Metrics'!$N$1026:$N$1124,MATCH($B$4,'SW Metrics'!$A$1026:$A$1124,0)),"")
B48: Peer median | C48: =IFERROR(MEDIAN('SW Metrics'!$C$1026:$C$1124),"") | D48: =IFERROR(MEDIAN('SW Metrics'!$D$1026:$D$1124),"") | E48: =IFERROR(MEDIAN('SW Metrics'!$E$1026:$E$1124),"") | F48: =IFERROR(MEDIAN('SW Metrics'!$F$1026:$F$1124),"") | G48: =IFERROR(MEDIAN('SW Metrics'!$G$1026:$G$1124),"") | H48: =IFERROR(MEDIAN('SW Metrics'!$H$1026:$H$1124),"") | I48: =IFERROR(MEDIAN('SW Metrics'!$I$1026:$I$1124),"") | J48: =IFERROR(MEDIAN('SW Metrics'!$J$1026:$J$1124),"") | K48: =IFERROR(MEDIAN('SW Metrics'!$K$1026:$K$1124),"") | L48: =IFERROR(MEDIAN('SW Metrics'!$L$1026:$L$1124),"") | M48: =IFERROR(MEDIAN('SW Metrics'!$M$1026:$M$1124),"") | N48: =IFERROR(MEDIAN('SW Metrics'!$N$1026:$N$1124),"")
B49: vs median | C49: =IF(OR(C47="",C48=""),"",C47-C48) | D49: =IF(OR(D47="",D48=""),"",D47-D48) | E49: =IF(OR(E47="",E48=""),"",E47-E48) | F49: =IF(OR(F47="",F48=""),"",F47-F48) | G49: =IF(OR(G47="",G48=""),"",G47-G48) | H49: =IF(OR(H47="",H48=""),"",H47-H48) | I49: =IF(OR(I47="",I48=""),"",I47-I48) | J49: =IF(OR(J47="",J48=""),"",J47-J48) | ... N49: =IF(OR(N47="",N48=""),"",N47-N48)
A51: NTM estimate revisions
A52: Metric | B52: Series | C52: Δ1M % | D52: Δ3M % | E52: Δ6M %
A53: NTM Revenue revision | B53: Company | C53: =IFERROR(INDEX('SW Revisions'!$G$6:$G$104,MATCH($B$4,'SW Revisions'!$A$6:$A$104,0)),"") | D53: =IFERROR(INDEX('SW Revisions'!$H$6:$H$104,MATCH($B$4,'SW Revisions'!$A$6:$A$104,0)),"") | E53: =IFERROR(INDEX('SW Revisions'!$I$6:$I$104,MATCH($B$4,'SW Revisions'!$A$6:$A$104,0)),"")
B54: Peer median | C54: =IFERROR(MEDIAN('SW Revisions'!$G$6:$G$104),"") | D54: =IFERROR(MEDIAN('SW Revisions'!$H$6:$H$104),"") | E54: =IFERROR(MEDIAN('SW Revisions'!$I$6:$I$104),"")
B55: vs median | C55: =IF(OR(C53="",C54=""),"",C53-C54) | D55: =IF(OR(D53="",D54=""),"",D53-D54) | E55: =IF(OR(E53="",E54=""),"",E53-E54)
A57: NTM EPS revision | B57: Company | C57: =IFERROR(INDEX('SW Revisions'!$O$6:$O$104,MATCH($B$4,'SW Revisions'!$A$6:$A$104,0)),"") | D57: =IFERROR(INDEX('SW Revisions'!$P$6:$P$104,MATCH($B$4,'SW Revisions'!$A$6:$A$104,0)),"") | E57: =IFERROR(INDEX('SW Revisions'!$Q$6:$Q$104,MATCH($B$4,'SW Revisions'!$A$6:$A$104,0)),"")
B58: Peer median | C58: =IFERROR(MEDIAN('SW Revisions'!$O$6:$O$104),"") | D58: =IFERROR(MEDIAN('SW Revisions'!$P$6:$P$104),"") | E58: =IFERROR(MEDIAN('SW Revisions'!$Q$6:$Q$104),"")
B59: vs median | C59: =IF(OR(C57="",C58=""),"",C57-C58) | D59: =IF(OR(D57="",D58=""),"",D57-D58) | E59: =IF(OR(E57="",E58=""),"",E57-E58)

Sheet SW Metrics
A1: Software — Metric Grids (by fiscal period offset) | H1: ⚠ Cells blank? This is a LIVE Bloomberg workbook — it has no saved data until its first refresh. Open it in desktop Excel on your Bloomberg terminal PC (add-in logged in), then Bloomberg ribbon ▸ Refresh All (or Ctrl+Alt+F9), wait a few minutes, and save. See README.
A2: All inputs from the BQL data sheets. FPO 0 = latest reported quarter per company; +1/+2 = consensus estimates (shaded). Blank cells = insufficient history / no estimate. Hover column headers and block titles for definitions.
A4: Revenue (USD mm)
A5: Ticker | B5: Latest Rpt Qtr | C5: FPO -9 | D5: FPO -8 | E5: FPO -7 | F5: FPO -6 | G5: FPO -5 | H5: FPO -4 | I5: FPO -3 | J5: FPO -2 | K5: FPO -1 | L5: FPO 0 (latest rpt) | M5: FPO +1E | N5: FPO +2E
A6: ='SW Rev'!$A5 | B6: ='SW Rev'!$B5 | C6: =IFERROR(IF(ISNUMBER('SW Rev'!G5),'SW Rev'!G5,""),"") | D6: =IFERROR(IF(ISNUMBER('SW Rev'!H5),'SW Rev'!H5,""),"") | E6: =IFERROR(IF(ISNUMBER('SW Rev'!I5),'SW Rev'!I5,""),"") | F6: =IFERROR(IF(ISNUMBER('SW Rev'!J5),'SW Rev'!J5,""),"") | G6: =IFERROR(IF(ISNUMBER('SW Rev'!K5),'SW Rev'!K5,""),"") | H6: =IFERROR(IF(ISNUMBER('SW Rev'!L5),'SW Rev'!L5,""),"") | I6: =IFERROR(IF(ISNUMBER('SW Rev'!M5),'SW Rev'!M5,""),"") | J6: =IFERROR(IF(ISNUMBER('SW Rev'!N5),'SW Rev'!N5,""),"") | ... N6: =IFERROR(IF(ISNUMBER('SW Rev'!R5),'SW Rev'!R5,""),"")
A7: ='SW Rev'!$A6 | B7: ='SW Rev'!$B6 | C7: =IFERROR(IF(ISNUMBER('SW Rev'!G6),'SW Rev'!G6,""),"") | D7: =IFERROR(IF(ISNUMBER('SW Rev'!H6),'SW Rev'!H6,""),"") | E7: =IFERROR(IF(ISNUMBER('SW Rev'!I6),'SW Rev'!I6,""),"") | F7: =IFERROR(IF(ISNUMBER('SW Rev'!J6),'SW Rev'!J6,""),"") | G7: =IFERROR(IF(ISNUMBER('SW Rev'!K6),'SW Rev'!K6,""),"") | H7: =IFERROR(IF(ISNUMBER('SW Rev'!L6),'SW Rev'!L6,""),"") | I7: =IFERROR(IF(ISNUMBER('SW Rev'!M6),'SW Rev'!M6,""),"") | J7: =IFERROR(IF(ISNUMBER('SW Rev'!N6),'SW Rev'!N6,""),"") | ... N7: =IFERROR(IF(ISNUMBER('SW Rev'!R6),'SW Rev'!R6,""),"")
A8: ='SW Rev'!$A7 | B8: ='SW Rev'!$B7 | C8: =IFERROR(IF(ISNUMBER('SW Rev'!G7),'SW Rev'!G7,""),"") | D8: =IFERROR(IF(ISNUMBER('SW Rev'!H7),'SW Rev'!H7,""),"") | E8: =IFERROR(IF(ISNUMBER('SW Rev'!I7),'SW Rev'!I7,""),"") | F8: =IFERROR(IF(ISNUMBER('SW Rev'!J7),'SW Rev'!J7,""),"") | G8: =IFERROR(IF(ISNUMBER('SW Rev'!K7),'SW Rev'!K7,""),"") | H8: =IFERROR(IF(ISNUMBER('SW Rev'!L7),'SW Rev'!L7,""),"") | I8: =IFERROR(IF(ISNUMBER('SW Rev'!M7),'SW Rev'!M7,""),"") | J8: =IFERROR(IF(ISNUMBER('SW Rev'!N7),'SW Rev'!N7,""),"") | ... N8: =IFERROR(IF(ISNUMBER('SW Rev'!R7),'SW Rev'!R7,""),"")
A9: ='SW Rev'!$A8 | B9: ='SW Rev'!$B8 | C9: =IFERROR(IF(ISNUMBER('SW Rev'!G8),'SW Rev'!G8,""),"") | D9: =IFERROR(IF(ISNUMBER('SW Rev'!H8),'SW Rev'!H8,""),"") | E9: =IFERROR(IF(ISNUMBER('SW Rev'!I8),'SW Rev'!I8,""),"") | F9: =IFERROR(IF(ISNUMBER('SW Rev'!J8),'SW Rev'!J8,""),"") | G9: =IFERROR(IF(ISNUMBER('SW Rev'!K8),'SW Rev'!K8,""),"") | H9: =IFERROR(IF(ISNUMBER('SW Rev'!L8),'SW Rev'!L8,""),"") | I9: =IFERROR(IF(ISNUMBER('SW Rev'!M8),'SW Rev'!M8,""),"") | J9: =IFERROR(IF(ISNUMBER('SW Rev'!N8),'SW Rev'!N8,""),"") | ... N9: =IFERROR(IF(ISNUMBER('SW Rev'!R8),'SW Rev'!R8,""),"")
A10: ='SW Rev'!$A9 | B10: ='SW Rev'!$B9 | C10: =IFERROR(IF(ISNUMBER('SW Rev'!G9),'SW Rev'!G9,""),"") | D10: =IFERROR(IF(ISNUMBER('SW Rev'!H9),'SW Rev'!H9,""),"") | E10: =IFERROR(IF(ISNUMBER('SW Rev'!I9),'SW Rev'!I9,""),"") | F10: =IFERROR(IF(ISNUMBER('SW Rev'!J9),'SW Rev'!J9,""),"") | G10: =IFERROR(IF(ISNUMBER('SW Rev'!K9),'SW Rev'!K9,""),"") | H10: =IFERROR(IF(ISNUMBER('SW Rev'!L9),'SW Rev'!L9,""),"") | I10: =IFERROR(IF(ISNUMBER('SW Rev'!M9),'SW Rev'!M9,""),"") | J10: =IFERROR(IF(ISNUMBER('SW Rev'!N9),'SW Rev'!N9,""),"") | ... N10: =IFERROR(IF(ISNUMBER('SW Rev'!R9),'SW Rev'!R9,""),"")
A11: ='SW Rev'!$A10 | B11: ='SW Rev'!$B10 | C11: =IFERROR(IF(ISNUMBER('SW Rev'!G10),'SW Rev'!G10,""),"") | D11: =IFERROR(IF(ISNUMBER('SW Rev'!H10),'SW Rev'!H10,""),"") | E11: =IFERROR(IF(ISNUMBER('SW Rev'!I10),'SW Rev'!I10,""),"") | F11: =IFERROR(IF(ISNUMBER('SW Rev'!J10),'SW Rev'!J10,""),"") | G11: =IFERROR(IF(ISNUMBER('SW Rev'!K10),'SW Rev'!K10,""),"") | H11: =IFERROR(IF(ISNUMBER('SW Rev'!L10),'SW Rev'!L10,""),"") | I11: =IFERROR(IF(ISNUMBER('SW Rev'!M10),'SW Rev'!M10,""),"") | J11: =IFERROR(IF(ISNUMBER('SW Rev'!N10),'SW Rev'!N10,""),"") | ... N11: =IFERROR(IF(ISNUMBER('SW Rev'!R10),'SW Rev'!R10,""),"")
A12: ='SW Rev'!$A11 | B12: ='SW Rev'!$B11 | C12: =IFERROR(IF(ISNUMBER('SW Rev'!G11),'SW Rev'!G11,""),"") | D12: =IFERROR(IF(ISNUMBER('SW Rev'!H11),'SW Rev'!H11,""),"") | E12: =IFERROR(IF(ISNUMBER('SW Rev'!I11),'SW Rev'!I11,""),"") | F12: =IFERROR(IF(ISNUMBER('SW Rev'!J11),'SW Rev'!J11,""),"") | G12: =IFERROR(IF(ISNUMBER('SW Rev'!K11),'SW Rev'!K11,""),"") | H12: =IFERROR(IF(ISNUMBER('SW Rev'!L11),'SW Rev'!L11,""),"") | I12: =IFERROR(IF(ISNUMBER('SW Rev'!M11),'SW Rev'!M11,""),"") | J12: =IFERROR(IF(ISNUMBER('SW Rev'!N11),'SW Rev'!N11,""),"") | ... N12: =IFERROR(IF(ISNUMBER('SW Rev'!R11),'SW Rev'!R11,""),"")
A13: ='SW Rev'!$A12 | B13: ='SW Rev'!$B12 | C13: =IFERROR(IF(ISNUMBER('SW Rev'!G12),'SW Rev'!G12,""),"") | D13: =IFERROR(IF(ISNUMBER('SW Rev'!H12),'SW Rev'!H12,""),"") | E13: =IFERROR(IF(ISNUMBER('SW Rev'!I12),'SW Rev'!I12,""),"") | F13: =IFERROR(IF(ISNUMBER('SW Rev'!J12),'SW Rev'!J12,""),"") | G13: =IFERROR(IF(ISNUMBER('SW Rev'!K12),'SW Rev'!K12,""),"") | H13: =IFERROR(IF(ISNUMBER('SW Rev'!L12),'SW Rev'!L12,""),"") | I13: =IFERROR(IF(ISNUMBER('SW Rev'!M12),'SW Rev'!M12,""),"") | J13: =IFERROR(IF(ISNUMBER('SW Rev'!N12),'SW Rev'!N12,""),"") | ... N13: =IFERROR(IF(ISNUMBER('SW Rev'!R12),'SW Rev'!R12,""),"")
A14: ='SW Rev'!$A13 | B14: ='SW Rev'!$B13 | C14: =IFERROR(IF(ISNUMBER('SW Rev'!G13),'SW Rev'!G13,""),"") | D14: =IFERROR(IF(ISNUMBER('SW Rev'!H13),'SW Rev'!H13,""),"") | E14: =IFERROR(IF(ISNUMBER('SW Rev'!I13),'SW Rev'!I13,""),"") | F14: =IFERROR(IF(ISNUMBER('SW Rev'!J13),'SW Rev'!J13,""),"") | G14: =IFERROR(IF(ISNUMBER('SW Rev'!K13),'SW Rev'!K13,""),"") | H14: =IFERROR(IF(ISNUMBER('SW Rev'!L13),'SW Rev'!L13,""),"") | I14: =IFERROR(IF(ISNUMBER('SW Rev'!M13),'SW Rev'!M13,""),"") | J14: =IFERROR(IF(ISNUMBER('SW Rev'!N13),'SW Rev'!N13,""),"") | ... N14: =IFERROR(IF(ISNUMBER('SW Rev'!R13),'SW Rev'!R13,""),"")
A15: ='SW Rev'!$A14 | B15: ='SW Rev'!$B14 | C15: =IFERROR(IF(ISNUMBER('SW Rev'!G14),'SW Rev'!G14,""),"") | D15: =IFERROR(IF(ISNUMBER('SW Rev'!H14),'SW Rev'!H14,""),"") | E15: =IFERROR(IF(ISNUMBER('SW Rev'!I14),'SW Rev'!I14,""),"") | F15: =IFERROR(IF(ISNUMBER('SW Rev'!J14),'SW Rev'!J14,""),"") | G15: =IFERROR(IF(ISNUMBER('SW Rev'!K14),'SW Rev'!K14,""),"") | H15: =IFERROR(IF(ISNUMBER('SW Rev'!L14),'SW Rev'!L14,""),"") | I15: =IFERROR(IF(ISNUMBER('SW Rev'!M14),'SW Rev'!M14,""),"") | J15: =IFERROR(IF(ISNUMBER('SW Rev'!N14),'SW Rev'!N14,""),"") | ... N15: =IFERROR(IF(ISNUMBER('SW Rev'!R14),'SW Rev'!R14,""),"")
A16: ='SW Rev'!$A15 | B16: ='SW Rev'!$B15 | C16: =IFERROR(IF(ISNUMBER('SW Rev'!G15),'SW Rev'!G15,""),"") | D16: =IFERROR(IF(ISNUMBER('SW Rev'!H15),'SW Rev'!H15,""),"") | E16: =IFERROR(IF(ISNUMBER('SW Rev'!I15),'SW Rev'!I15,""),"") | F16: =IFERROR(IF(ISNUMBER('SW Rev'!J15),'SW Rev'!J15,""),"") | G16: =IFERROR(IF(ISNUMBER('SW Rev'!K15),'SW Rev'!K15,""),"") | H16: =IFERROR(IF(ISNUMBER('SW Rev'!L15),'SW Rev'!L15,""),"") | I16: =IFERROR(IF(ISNUMBER('SW Rev'!M15),'SW Rev'!M15,""),"") | J16: =IFERROR(IF(ISNUMBER('SW Rev'!N15),'SW Rev'!N15,""),"") | ... N16: =IFERROR(IF(ISNUMBER('SW Rev'!R15),'SW Rev'!R15,""),"")
A17: ='SW Rev'!$A16 | B17: ='SW Rev'!$B16 | C17: =IFERROR(IF(ISNUMBER('SW Rev'!G16),'SW Rev'!G16,""),"") | D17: =IFERROR(IF(ISNUMBER('SW Rev'!H16),'SW Rev'!H16,""),"") | E17: =IFERROR(IF(ISNUMBER('SW Rev'!I16),'SW Rev'!I16,""),"") | F17: =IFERROR(IF(ISNUMBER('SW Rev'!J16),'SW Rev'!J16,""),"") | G17: =IFERROR(IF(ISNUMBER('SW Rev'!K16),'SW Rev'!K16,""),"") | H17: =IFERROR(IF(ISNUMBER('SW Rev'!L16),'SW Rev'!L16,""),"") | I17: =IFERROR(IF(ISNUMBER('SW Rev'!M16),'SW Rev'!M16,""),"") | J17: =IFERROR(IF(ISNUMBER('SW Rev'!N16),'SW Rev'!N16,""),"") | ... N17: =IFERROR(IF(ISNUMBER('SW Rev'!R16),'SW Rev'!R16,""),"")
... A104: ='SW Rev'!$A103 | B104: ='SW Rev'!$B103 | C104: =IFERROR(IF(ISNUMBER('SW Rev'!G103),'SW Rev'!G103,""),"") | D104: =IFERROR(IF(ISNUMBER('SW Rev'!H103),'SW Rev'!H103,""),"") | E104: =IFERROR(IF(ISNUMBER('SW Rev'!I103),'SW Rev'!I103,""),"") | F104: =IFERROR(IF(ISNUMBER('SW Rev'!J103),'SW Rev'!J103,""),"") | G104: =IFERROR(IF(ISNUMBER('SW Rev'!K103),'SW Rev'!K103,""),"") | H104: =IFERROR(IF(ISNUMBER('SW Rev'!L103),'SW Rev'!L103,""),"") | I104: =IFERROR(IF(ISNUMBER('SW Rev'!M103),'SW Rev'!M103,""),"") | J104: =IFERROR(IF(ISNUMBER('SW Rev'!N103),'SW Rev'!N103,""),"") | ... N104: =IFERROR(IF(ISNUMBER('SW Rev'!R103),'SW Rev'!R103,""),"")
A106: Revenue growth YoY %
A107: Ticker | B107: Latest Rpt Qtr | C107: FPO -9 | D107: FPO -8 | E107: FPO -7 | F107: FPO -6 | G107: FPO -5 | H107: FPO -4 | I107: FPO -3 | J107: FPO -2 | K107: FPO -1 | L107: FPO 0 (latest rpt) | M107: FPO +1E | N107: FPO +2E
A108: ='SW Rev'!$A5 | B108: ='SW Rev'!$B5 | C108: =IFERROR(IF(AND(ISNUMBER('SW Rev'!G5),ISNUMBER('SW Rev'!C5),'SW Rev'!C5>0),'SW Rev'!G5/'SW Rev'!C5-1,""),"") | D108: =IFERROR(IF(AND(ISNUMBER('SW Rev'!H5),ISNUMBER('SW Rev'!D5),'SW Rev'!D5>0),'SW Rev'!H5/'SW Rev'!D5-1,""),"") | E108: =IFERROR(IF(AND(ISNUMBER('SW Rev'!I5),ISNUMBER('SW Rev'!E5),'SW Rev'!E5>0),'SW Rev'!I5/'SW Rev'!E5-1,""),"") | F108: =IFERROR(IF(AND(ISNUMBER('SW Rev'!J5),ISNUMBER('SW Rev'!F5),'SW Rev'!F5>0),'SW Rev'!J5/'SW Rev'!F5-1,""),"") | G108: =IFERROR(IF(AND(ISNUMBER('SW Rev'!K5),ISNUMBER('SW Rev'!G5),'SW Rev'!G5>0),'SW Rev'!K5/'SW Rev'!G5-1,""),"") | H108: =IFERROR(IF(AND(ISNUMBER('SW Rev'!L5),ISNUMBER('SW Rev'!H5),'SW Rev'!H5>0),'SW Rev'!L5/'SW Rev'!H5-1,""),"") | I108: =IFERROR(IF(AND(ISNUMBER('SW Rev'!M5),ISNUMBER('SW Rev'!I5),'SW Rev'!I5>0),'SW Rev'!M5/'SW Rev'!I5-1,""),"") | J108: =IFERROR(IF(AND(ISNUMBER('SW Rev'!N5),ISNUMBER('SW Rev'!J5),'SW Rev'!J5>0),'SW Rev'!N5/'SW Rev'!J5-1,""),"") | ... N108: =IFERROR(IF(AND(ISNUMBER('SW Rev'!R5),ISNUMBER('SW Rev'!N5),'SW Rev'!N5>0),'SW Rev'!R5/'SW Rev'!N5-1,""),"")
A109: ='SW Rev'!$A6 | B109: ='SW Rev'!$B6 | C109: =IFERROR(IF(AND(ISNUMBER('SW Rev'!G6),ISNUMBER('SW Rev'!C6),'SW Rev'!C6>0),'SW Rev'!G6/'SW Rev'!C6-1,""),"") | D109: =IFERROR(IF(AND(ISNUMBER('SW Rev'!H6),ISNUMBER('SW Rev'!D6),'SW Rev'!D6>0),'SW Rev'!H6/'SW Rev'!D6-1,""),"") | E109: =IFERROR(IF(AND(ISNUMBER('SW Rev'!I6),ISNUMBER('SW Rev'!E6),'SW Rev'!E6>0),'SW Rev'!I6/'SW Rev'!E6-1,""),"") | F109: =IFERROR(IF(AND(ISNUMBER('SW Rev'!J6),ISNUMBER('SW Rev'!F6),'SW Rev'!F6>0),'SW Rev'!J6/'SW Rev'!F6-1,""),"") | G109: =IFERROR(IF(AND(ISNUMBER('SW Rev'!K6),ISNUMBER('SW Rev'!G6),'SW Rev'!G6>0),'SW Rev'!K6/'SW Rev'!G6-1,""),"") | H109: =IFERROR(IF(AND(ISNUMBER('SW Rev'!L6),ISNUMBER('SW Rev'!H6),'SW Rev'!H6>0),'SW Rev'!L6/'SW Rev'!H6-1,""),"") | I109: =IFERROR(IF(AND(ISNUMBER('SW Rev'!M6),ISNUMBER('SW Rev'!I6),'SW Rev'!I6>0),'SW Rev'!M6/'SW Rev'!I6-1,""),"") | J109: =IFERROR(IF(AND(ISNUMBER('SW Rev'!N6),ISNUMBER('SW Rev'!J6),'SW Rev'!J6>0),'SW Rev'!N6/'SW Rev'!J6-1,""),"") | ... N109: =IFERROR(IF(AND(ISNUMBER('SW Rev'!R6),ISNUMBER('SW Rev'!N6),'SW Rev'!N6>0),'SW Rev'!R6/'SW Rev'!N6-1,""),"")
A110: ='SW Rev'!$A7 | B110: ='SW Rev'!$B7 | C110: =IFERROR(IF(AND(ISNUMBER('SW Rev'!G7),ISNUMBER('SW Rev'!C7),'SW Rev'!C7>0),'SW Rev'!G7/'SW Rev'!C7-1,""),"") | D110: =IFERROR(IF(AND(ISNUMBER('SW Rev'!H7),ISNUMBER('SW Rev'!D7),'SW Rev'!D7>0),'SW Rev'!H7/'SW Rev'!D7-1,""),"") | E110: =IFERROR(IF(AND(ISNUMBER('SW Rev'!I7),ISNUMBER('SW Rev'!E7),'SW Rev'!E7>0),'SW Rev'!I7/'SW Rev'!E7-1,""),"") | F110: =IFERROR(IF(AND(ISNUMBER('SW Rev'!J7),ISNUMBER('SW Rev'!F7),'SW Rev'!F7>0),'SW Rev'!J7/'SW Rev'!F7-1,""),"") | G110: =IFERROR(IF(AND(ISNUMBER('SW Rev'!K7),ISNUMBER('SW Rev'!G7),'SW Rev'!G7>0),'SW Rev'!K7/'SW Rev'!G7-1,""),"") | H110: =IFERROR(IF(AND(ISNUMBER('SW Rev'!L7),ISNUMBER('SW Rev'!H7),'SW Rev'!H7>0),'SW Rev'!L7/'SW Rev'!H7-1,""),"") | I110: =IFERROR(IF(AND(ISNUMBER('SW Rev'!M7),ISNUMBER('SW Rev'!I7),'SW Rev'!I7>0),'SW Rev'!M7/'SW Rev'!I7-1,""),"") | J110: =IFERROR(IF(AND(ISNUMBER('SW Rev'!N7),ISNUMBER('SW Rev'!J7),'SW Rev'!J7>0),'SW Rev'!N7/'SW Rev'!J7-1,""),"") | ... N110: =IFERROR(IF(AND(ISNUMBER('SW Rev'!R7),ISNUMBER('SW Rev'!N7),'SW Rev'!N7>0),'SW Rev'!R7/'SW Rev'!N7-1,""),"")
A111: ='SW Rev'!$A8 | B111: ='SW Rev'!$B8 | C111: =IFERROR(IF(AND(ISNUMBER('SW Rev'!G8),ISNUMBER('SW Rev'!C8),'SW Rev'!C8>0),'SW Rev'!G8/'SW Rev'!C8-1,""),"") | D111: =IFERROR(IF(AND(ISNUMBER('SW Rev'!H8),ISNUMBER('SW Rev'!D8),'SW Rev'!D8>0),'SW Rev'!H8/'SW Rev'!D8-1,""),"") | E111: =IFERROR(IF(AND(ISNUMBER('SW Rev'!I8),ISNUMBER('SW Rev'!E8),'SW Rev'!E8>0),'SW Rev'!I8/'SW Rev'!E8-1,""),"") | F111: =IFERROR(IF(AND(ISNUMBER('SW Rev'!J8),ISNUMBER('SW Rev'!F8),'SW Rev'!F8>0),'SW Rev'!J8/'SW Rev'!F8-1,""),"") | G111: =IFERROR(IF(AND(ISNUMBER('SW Rev'!K8),ISNUMBER('SW Rev'!G8),'SW Rev'!G8>0),'SW Rev'!K8/'SW Rev'!G8-1,""),"") | H111: =IFERROR(IF(AND(ISNUMBER('SW Rev'!L8),ISNUMBER('SW Rev'!H8),'SW Rev'!H8>0),'SW Rev'!L8/'SW Rev'!H8-1,""),"") | I111: =IFERROR(IF(AND(ISNUMBER('SW Rev'!M8),ISNUMBER('SW Rev'!I8),'SW Rev'!I8>0),'SW Rev'!M8/'SW Rev'!I8-1,""),"") | J111: =IFERROR(IF(AND(ISNUMBER('SW Rev'!N8),ISNUMBER('SW Rev'!J8),'SW Rev'!J8>0),'SW Rev'!N8/'SW Rev'!J8-1,""),"") | ... N111: =IFERROR(IF(AND(ISNUMBER('SW Rev'!R8),ISNUMBER('SW Rev'!N8),'SW Rev'!N8>0),'SW Rev'!R8/'SW Rev'!N8-1,""),"")
A112: ='SW Rev'!$A9 | B112: ='SW Rev'!$B9 | C112: =IFERROR(IF(AND(ISNUMBER('SW Rev'!G9),ISNUMBER('SW Rev'!C9),'SW Rev'!C9>0),'SW Rev'!G9/'SW Rev'!C9-1,""),"") | D112: =IFERROR(IF(AND(ISNUMBER('SW Rev'!H9),ISNUMBER('SW Rev'!D9),'SW Rev'!D9>0),'SW Rev'!H9/'SW Rev'!D9-1,""),"") | E112: =IFERROR(IF(AND(ISNUMBER('SW Rev'!I9),ISNUMBER('SW Rev'!E9),'SW Rev'!E9>0),'SW Rev'!I9/'SW Rev'!E9-1,""),"") | F112: =IFERROR(IF(AND(ISNUMBER('SW Rev'!J9),ISNUMBER('SW Rev'!F9),'SW Rev'!F9>0),'SW Rev'!J9/'SW Rev'!F9-1,""),"") | G112: =IFERROR(IF(AND(ISNUMBER('SW Rev'!K9),ISNUMBER('SW Rev'!G9),'SW Rev'!G9>0),'SW Rev'!K9/'SW Rev'!G9-1,""),"") | H112: =IFERROR(IF(AND(ISNUMBER('SW Rev'!L9),ISNUMBER('SW Rev'!H9),'SW Rev'!H9>0),'SW Rev'!L9/'SW Rev'!H9-1,""),"") | I112: =IFERROR(IF(AND(ISNUMBER('SW Rev'!M9),ISNUMBER('SW Rev'!I9),'SW Rev'!I9>0),'SW Rev'!M9/'SW Rev'!I9-1,""),"") | J112: =IFERROR(IF(AND(ISNUMBER('SW Rev'!N9),ISNUMBER('SW Rev'!J9),'SW Rev'!J9>0),'SW Rev'!N9/'SW Rev'!J9-1,""),"") | ... N112: =IFERROR(IF(AND(ISNUMBER('SW Rev'!R9),ISNUMBER('SW Rev'!N9),'SW Rev'!N9>0),'SW Rev'!R9/'SW Rev'!N9-1,""),"")
A113: ='SW Rev'!$A10 | B113: ='SW Rev'!$B10 | C113: =IFERROR(IF(AND(ISNUMBER('SW Rev'!G10),ISNUMBER('SW Rev'!C10),'SW Rev'!C10>0),'SW Rev'!G10/'SW Rev'!C10-1,""),"") | D113: =IFERROR(IF(AND(ISNUMBER('SW Rev'!H10),ISNUMBER('SW Rev'!D10),'SW Rev'!D10>0),'SW Rev'!H10/'SW Rev'!D10-1,""),"") | E113: =IFERROR(IF(AND(ISNUMBER('SW Rev'!I10),ISNUMBER('SW Rev'!E10),'SW Rev'!E10>0),'SW Rev'!I10/'SW Rev'!E10-1,""),"") | F113: =IFERROR(IF(AND(ISNUMBER('SW Rev'!J10),ISNUMBER('SW Rev'!F10),'SW Rev'!F10>0),'SW Rev'!J10/'SW Rev'!F10-1,""),"") | G113: =IFERROR(IF(AND(ISNUMBER('SW Rev'!K10),ISNUMBER('SW Rev'!G10),'SW Rev'!G10>0),'SW Rev'!K10/'SW Rev'!G10-1,""),"") | H113: =IFERROR(IF(AND(ISNUMBER('SW Rev'!L10),ISNUMBER('SW Rev'!H10),'SW Rev'!H10>0),'SW Rev'!L10/'SW Rev'!H10-1,""),"") | I113: =IFERROR(IF(AND(ISNUMBER('SW Rev'!M10),ISNUMBER('SW Rev'!I10),'SW Rev'!I10>0),'SW Rev'!M10/'SW Rev'!I10-1,""),"") | J113: =IFERROR(IF(AND(ISNUMBER('SW Rev'!N10),ISNUMBER('SW Rev'!J10),'SW Rev'!J10>0),'SW Rev'!N10/'SW Rev'!J10-1,""),"") | ... N113: =IFERROR(IF(AND(ISNUMBER('SW Rev'!R10),ISNUMBER('SW Rev'!N10),'SW Rev'!N10>0),'SW Rev'!R10/'SW Rev'!N10-1,""),"")
A114: ='SW Rev'!$A11 | B114: ='SW Rev'!$B11 | C114: =IFERROR(IF(AND(ISNUMBER('SW Rev'!G11),ISNUMBER('SW Rev'!C11),'SW Rev'!C11>0),'SW Rev'!G11/'SW Rev'!C11-1,""),"") | D114: =IFERROR(IF(AND(ISNUMBER('SW Rev'!H11),ISNUMBER('SW Rev'!D11),'SW Rev'!D11>0),'SW Rev'!H11/'SW Rev'!D11-1,""),"") | E114: =IFERROR(IF(AND(ISNUMBER('SW Rev'!I11),ISNUMBER('SW Rev'!E11),'SW Rev'!E11>0),'SW Rev'!I11/'SW Rev'!E11-1,""),"") | F114: =IFERROR(IF(AND(ISNUMBER('SW Rev'!J11),ISNUMBER('SW Rev'!F11),'SW Rev'!F11>0),'SW Rev'!J11/'SW Rev'!F11-1,""),"") | G114: =IFERROR(IF(AND(ISNUMBER('SW Rev'!K11),ISNUMBER('SW Rev'!G11),'SW Rev'!G11>0),'SW Rev'!K11/'SW Rev'!G11-1,""),"") | H114: =IFERROR(IF(AND(ISNUMBER('SW Rev'!L11),ISNUMBER('SW Rev'!H11),'SW Rev'!H11>0),'SW Rev'!L11/'SW Rev'!H11-1,""),"") | I114: =IFERROR(IF(AND(ISNUMBER('SW Rev'!M11),ISNUMBER('SW Rev'!I11),'SW Rev'!I11>0),'SW Rev'!M11/'SW Rev'!I11-1,""),"") | J114: =IFERROR(IF(AND(ISNUMBER('SW Rev'!N11),ISNUMBER('SW Rev'!J11),'SW Rev'!J11>0),'SW Rev'!N11/'SW Rev'!J11-1,""),"") | ... N114: =IFERROR(IF(AND(ISNUMBER('SW Rev'!R11),ISNUMBER('SW Rev'!N11),'SW Rev'!N11>0),'SW Rev'!R11/'SW Rev'!N11-1,""),"")
A115: ='SW Rev'!$A12 | B115: ='SW Rev'!$B12 | C115: =IFERROR(IF(AND(ISNUMBER('SW Rev'!G12),ISNUMBER('SW Rev'!C12),'SW Rev'!C12>0),'SW Rev'!G12/'SW Rev'!C12-1,""),"") | D115: =IFERROR(IF(AND(ISNUMBER('SW Rev'!H12),ISNUMBER('SW Rev'!D12),'SW Rev'!D12>0),'SW Rev'!H12/'SW Rev'!D12-1,""),"") | E115: =IFERROR(IF(AND(ISNUMBER('SW Rev'!I12),ISNUMBER('SW Rev'!E12),'SW Rev'!E12>0),'SW Rev'!I12/'SW Rev'!E12-1,""),"") | F115: =IFERROR(IF(AND(ISNUMBER('SW Rev'!J12),ISNUMBER('SW Rev'!F12),'SW Rev'!F12>0),'SW Rev'!J12/'SW Rev'!F12-1,""),"") | G115: =IFERROR(IF(AND(ISNUMBER('SW Rev'!K12),ISNUMBER('SW Rev'!G12),'SW Rev'!G12>0),'SW Rev'!K12/'SW Rev'!G12-1,""),"") | H115: =IFERROR(IF(AND(ISNUMBER('SW Rev'!L12),ISNUMBER('SW Rev'!H12),'SW Rev'!H12>0),'SW Rev'!L12/'SW Rev'!H12-1,""),"") | I115: =IFERROR(IF(AND(ISNUMBER('SW Rev'!M12),ISNUMBER('SW Rev'!I12),'SW Rev'!I12>0),'SW Rev'!M12/'SW Rev'!I12-1,""),"") | J115: =IFERROR(IF(AND(ISNUMBER('SW Rev'!N12),ISNUMBER('SW Rev'!J12),'SW Rev'!J12>0),'SW Rev'!N12/'SW Rev'!J12-1,""),"") | ... N115: =IFERROR(IF(AND(ISNUMBER('SW Rev'!R12),ISNUMBER('SW Rev'!N12),'SW Rev'!N12>0),'SW Rev'!R12/'SW Rev'!N12-1,""),"")
A116: ='SW Rev'!$A13 | B116: ='SW Rev'!$B13 | C116: =IFERROR(IF(AND(ISNUMBER('SW Rev'!G13),ISNUMBER('SW Rev'!C13),'SW Rev'!C13>0),'SW Rev'!G13/'SW Rev'!C13-1,""),"") | D116: =IFERROR(IF(AND(ISNUMBER('SW Rev'!H13),ISNUMBER('SW Rev'!D13),'SW Rev'!D13>0),'SW Rev'!H13/'SW Rev'!D13-1,""),"") | E116: =IFERROR(IF(AND(ISNUMBER('SW Rev'!I13),ISNUMBER('SW Rev'!E13),'SW Rev'!E13>0),'SW Rev'!I13/'SW Rev'!E13-1,""),"") | F116: =IFERROR(IF(AND(ISNUMBER('SW Rev'!J13),ISNUMBER('SW Rev'!F13),'SW Rev'!F13>0),'SW Rev'!J13/'SW Rev'!F13-1,""),"") | G116: =IFERROR(IF(AND(ISNUMBER('SW Rev'!K13),ISNUMBER('SW Rev'!G13),'SW Rev'!G13>0),'SW Rev'!K13/'SW Rev'!G13-1,""),"") | H116: =IFERROR(IF(AND(ISNUMBER('SW Rev'!L13),ISNUMBER('SW Rev'!H13),'SW Rev'!H13>0),'SW Rev'!L13/'SW Rev'!H13-1,""),"") | I116: =IFERROR(IF(AND(ISNUMBER('SW Rev'!M13),ISNUMBER('SW Rev'!I13),'SW Rev'!I13>0),'SW Rev'!M13/'SW Rev'!I13-1,""),"") | J116: =IFERROR(IF(AND(ISNUMBER('SW Rev'!N13),ISNUMBER('SW Rev'!J13),'SW Rev'!J13>0),'SW Rev'!N13/'SW Rev'!J13-1,""),"") | ... N116: =IFERROR(IF(AND(ISNUMBER('SW Rev'!R13),ISNUMBER('SW Rev'!N13),'SW Rev'!N13>0),'SW Rev'!R13/'SW Rev'!N13-1,""),"")
A117: ='SW Rev'!$A14 | B117: ='SW Rev'!$B14 | C117: =IFERROR(IF(AND(ISNUMBER('SW Rev'!G14),ISNUMBER('SW Rev'!C14),'SW Rev'!C14>0),'SW Rev'!G14/'SW Rev'!C14-1,""),"") | D117: =IFERROR(IF(AND(ISNUMBER('SW Rev'!H14),ISNUMBER('SW Rev'!D14),'SW Rev'!D14>0),'SW Rev'!H14/'SW Rev'!D14-1,""),"") | E117: =IFERROR(IF(AND(ISNUMBER('SW Rev'!I14),ISNUMBER('SW Rev'!E14),'SW Rev'!E14>0),'SW Rev'!I14/'SW Rev'!E14-1,""),"") | F117: =IFERROR(IF(AND(ISNUMBER('SW Rev'!J14),ISNUMBER('SW Rev'!F14),'SW Rev'!F14>0),'SW Rev'!J14/'SW Rev'!F14-1,""),"") | G117: =IFERROR(IF(AND(ISNUMBER('SW Rev'!K14),ISNUMBER('SW Rev'!G14),'SW Rev'!G14>0),'SW Rev'!K14/'SW Rev'!G14-1,""),"") | H117: =IFERROR(IF(AND(ISNUMBER('SW Rev'!L14),ISNUMBER('SW Rev'!H14),'SW Rev'!H14>0),'SW Rev'!L14/'SW Rev'!H14-1,""),"") | I117: =IFERROR(IF(AND(ISNUMBER('SW Rev'!M14),ISNUMBER('SW Rev'!I14),'SW Rev'!I14>0),'SW Rev'!M14/'SW Rev'!I14-1,""),"") | J117: =IFERROR(IF(AND(ISNUMBER('SW Rev'!N14),ISNUMBER('SW Rev'!J14),'SW Rev'!J14>0),'SW Rev'!N14/'SW Rev'!J14-1,""),"") | ... N117: =IFERROR(IF(AND(ISNUMBER('SW Rev'!R14),ISNUMBER('SW Rev'!N14),'SW Rev'!N14>0),'SW Rev'!R14/'SW Rev'!N14-1,""),"")
A118: ='SW Rev'!$A15 | B118: ='SW Rev'!$B15 | C118: =IFERROR(IF(AND(ISNUMBER('SW Rev'!G15),ISNUMBER('SW Rev'!C15),'SW Rev'!C15>0),'SW Rev'!G15/'SW Rev'!C15-1,""),"") | D118: =IFERROR(IF(AND(ISNUMBER('SW Rev'!H15),ISNUMBER('SW Rev'!D15),'SW Rev'!D15>0),'SW Rev'!H15/'SW Rev'!D15-1,""),"") | E118: =IFERROR(IF(AND(ISNUMBER('SW Rev'!I15),ISNUMBER('SW Rev'!E15),'SW Rev'!E15>0),'SW Rev'!I15/'SW Rev'!E15-1,""),"") | F118: =IFERROR(IF(AND(ISNUMBER('SW Rev'!J15),ISNUMBER('SW Rev'!F15),'SW Rev'!F15>0),'SW Rev'!J15/'SW Rev'!F15-1,""),"") | G118: =IFERROR(IF(AND(ISNUMBER('SW Rev'!K15),ISNUMBER('SW Rev'!G15),'SW Rev'!G15>0),'SW Rev'!K15/'SW Rev'!G15-1,""),"") | H118: =IFERROR(IF(AND(ISNUMBER('SW Rev'!L15),ISNUMBER('SW Rev'!H15),'SW Rev'!H15>0),'SW Rev'!L15/'SW Rev'!H15-1,""),"") | I118: =IFERROR(IF(AND(ISNUMBER('SW Rev'!M15),ISNUMBER('SW Rev'!I15),'SW Rev'!I15>0),'SW Rev'!M15/'SW Rev'!I15-1,""),"") | J118: =IFERROR(IF(AND(ISNUMBER('SW Rev'!N15),ISNUMBER('SW Rev'!J15),'SW Rev'!J15>0),'SW Rev'!N15/'SW Rev'!J15-1,""),"") | ... N118: =IFERROR(IF(AND(ISNUMBER('SW Rev'!R15),ISNUMBER('SW Rev'!N15),'SW Rev'!N15>0),'SW Rev'!R15/'SW Rev'!N15-1,""),"")
A119: ='SW Rev'!$A16 | B119: ='SW Rev'!$B16 | C119: =IFERROR(IF(AND(ISNUMBER('SW Rev'!G16),ISNUMBER('SW Rev'!C16),'SW Rev'!C16>0),'SW Rev'!G16/'SW Rev'!C16-1,""),"") | D119: =IFERROR(IF(AND(ISNUMBER('SW Rev'!H16),ISNUMBER('SW Rev'!D16),'SW Rev'!D16>0),'SW Rev'!H16/'SW Rev'!D16-1,""),"") | E119: =IFERROR(IF(AND(ISNUMBER('SW Rev'!I16),ISNUMBER('SW Rev'!E16),'SW Rev'!E16>0),'SW Rev'!I16/'SW Rev'!E16-1,""),"") | F119: =IFERROR(IF(AND(ISNUMBER('SW Rev'!J16),ISNUMBER('SW Rev'!F16),'SW Rev'!F16>0),'SW Rev'!J16/'SW Rev'!F16-1,""),"") | G119: =IFERROR(IF(AND(ISNUMBER('SW Rev'!K16),ISNUMBER('SW Rev'!G16),'SW Rev'!G16>0),'SW Rev'!K16/'SW Rev'!G16-1,""),"") | H119: =IFERROR(IF(AND(ISNUMBER('SW Rev'!L16),ISNUMBER('SW Rev'!H16),'SW Rev'!H16>0),'SW Rev'!L16/'SW Rev'!H16-1,""),"") | I119: =IFERROR(IF(AND(ISNUMBER('SW Rev'!M16),ISNUMBER('SW Rev'!I16),'SW Rev'!I16>0),'SW Rev'!M16/'SW Rev'!I16-1,""),"") | J119: =IFERROR(IF(AND(ISNUMBER('SW Rev'!N16),ISNUMBER('SW Rev'!J16),'SW Rev'!J16>0),'SW Rev'!N16/'SW Rev'!J16-1,""),"") | ... N119: =IFERROR(IF(AND(ISNUMBER('SW Rev'!R16),ISNUMBER('SW Rev'!N16),'SW Rev'!N16>0),'SW Rev'!R16/'SW Rev'!N16-1,""),"")
... A206: ='SW Rev'!$A103 | B206: ='SW Rev'!$B103 | C206: =IFERROR(IF(AND(ISNUMBER('SW Rev'!G103),ISNUMBER('SW Rev'!C103),'SW Rev'!C103>0),'SW Rev'!G103/'SW Rev'!C103-1,""),"") | D206: =IFERROR(IF(AND(ISNUMBER('SW Rev'!H103),ISNUMBER('SW Rev'!D103),'SW Rev'!D103>0),'SW Rev'!H103/'SW Rev'!D103-1,""),"") | E206: =IFERROR(IF(AND(ISNUMBER('SW Rev'!I103),ISNUMBER('SW Rev'!E103),'SW Rev'!E103>0),'SW Rev'!I103/'SW Rev'!E103-1,""),"") | F206: =IFERROR(IF(AND(ISNUMBER('SW Rev'!J103),ISNUMBER('SW Rev'!F103),'SW Rev'!F103>0),'SW Rev'!J103/'SW Rev'!F103-1,""),"") | G206: =IFERROR(IF(AND(ISNUMBER('SW Rev'!K103),ISNUMBER('SW Rev'!G103),'SW Rev'!G103>0),'SW Rev'!K103/'SW Rev'!G103-1,""),"") | H206: =IFERROR(IF(AND(ISNUMBER('SW Rev'!L103),ISNUMBER('SW Rev'!H103),'SW Rev'!H103>0),'SW Rev'!L103/'SW Rev'!H103-1,""),"") | I206: =IFERROR(IF(AND(ISNUMBER('SW Rev'!M103),ISNUMBER('SW Rev'!I103),'SW Rev'!I103>0),'SW Rev'!M103/'SW Rev'!I103-1,""),"") | J206: =IFERROR(IF(AND(ISNUMBER('SW Rev'!N103),ISNUMBER('SW Rev'!J103),'SW Rev'!J103>0),'SW Rev'!N103/'SW Rev'!J103-1,""),"") | ... N206: =IFERROR(IF(AND(ISNUMBER('SW Rev'!R103),ISNUMBER('SW Rev'!N103),'SW Rev'!N103>0),'SW Rev'!R103/'SW Rev'!N103-1,""),"")
A208: Revenue growth QoQ %
A209: Ticker | B209: Latest Rpt Qtr | C209: FPO -9 | D209: FPO -8 | E209: FPO -7 | F209: FPO -6 | G209: FPO -5 | H209: FPO -4 | I209: FPO -3 | J209: FPO -2 | K209: FPO -1 | L209: FPO 0 (latest rpt) | M209: FPO +1E | N209: FPO +2E
A210: ='SW Rev'!$A5 | B210: ='SW Rev'!$B5 | C210: =IFERROR(IF(AND(ISNUMBER('SW Rev'!G5),ISNUMBER('SW Rev'!F5),'SW Rev'!F5>0),'SW Rev'!G5/'SW Rev'!F5-1,""),"") | D210: =IFERROR(IF(AND(ISNUMBER('SW Rev'!H5),ISNUMBER('SW Rev'!G5),'SW Rev'!G5>0),'SW Rev'!H5/'SW Rev'!G5-1,""),"") | E210: =IFERROR(IF(AND(ISNUMBER('SW Rev'!I5),ISNUMBER('SW Rev'!H5),'SW Rev'!H5>0),'SW Rev'!I5/'SW Rev'!H5-1,""),"") | F210: =IFERROR(IF(AND(ISNUMBER('SW Rev'!J5),ISNUMBER('SW Rev'!I5),'SW Rev'!I5>0),'SW Rev'!J5/'SW Rev'!I5-1,""),"") | G210: =IFERROR(IF(AND(ISNUMBER('SW Rev'!K5),ISNUMBER('SW Rev'!J5),'SW Rev'!J5>0),'SW Rev'!K5/'SW Rev'!J5-1,""),"") | H210: =IFERROR(IF(AND(ISNUMBER('SW Rev'!L5),ISNUMBER('SW Rev'!K5),'SW Rev'!K5>0),'SW Rev'!L5/'SW Rev'!K5-1,""),"") | I210: =IFERROR(IF(AND(ISNUMBER('SW Rev'!M5),ISNUMBER('SW Rev'!L5),'SW Rev'!L5>0),'SW Rev'!M5/'SW Rev'!L5-1,""),"") | J210: =IFERROR(IF(AND(ISNUMBER('SW Rev'!N5),ISNUMBER('SW Rev'!M5),'SW Rev'!M5>0),'SW Rev'!N5/'SW Rev'!M5-1,""),"") | ... N210: =IFERROR(IF(AND(ISNUMBER('SW Rev'!R5),ISNUMBER('SW Rev'!Q5),'SW Rev'!Q5>0),'SW Rev'!R5/'SW Rev'!Q5-1,""),"")
A211: ='SW Rev'!$A6 | B211: ='SW Rev'!$B6 | C211: =IFERROR(IF(AND(ISNUMBER('SW Rev'!G6),ISNUMBER('SW Rev'!F6),'SW Rev'!F6>0),'SW Rev'!G6/'SW Rev'!F6-1,""),"") | D211: =IFERROR(IF(AND(ISNUMBER('SW Rev'!H6),ISNUMBER('SW Rev'!G6),'SW Rev'!G6>0),'SW Rev'!H6/'SW Rev'!G6-1,""),"") | E211: =IFERROR(IF(AND(ISNUMBER('SW Rev'!I6),ISNUMBER('SW Rev'!H6),'SW Rev'!H6>0),'SW Rev'!I6/'SW Rev'!H6-1,""),"") | F211: =IFERROR(IF(AND(ISNUMBER('SW Rev'!J6),ISNUMBER('SW Rev'!I6),'SW Rev'!I6>0),'SW Rev'!J6/'SW Rev'!I6-1,""),"") | G211: =IFERROR(IF(AND(ISNUMBER('SW Rev'!K6),ISNUMBER('SW Rev'!J6),'SW Rev'!J6>0),'SW Rev'!K6/'SW Rev'!J6-1,""),"") | H211: =IFERROR(IF(AND(ISNUMBER('SW Rev'!L6),ISNUMBER('SW Rev'!K6),'SW Rev'!K6>0),'SW Rev'!L6/'SW Rev'!K6-1,""),"") | I211: =IFERROR(IF(AND(ISNUMBER('SW Rev'!M6),ISNUMBER('SW Rev'!L6),'SW Rev'!L6>0),'SW Rev'!M6/'SW Rev'!L6-1,""),"") | J211: =IFERROR(IF(AND(ISNUMBER('SW Rev'!N6),ISNUMBER('SW Rev'!M6),'SW Rev'!M6>0),'SW Rev'!N6/'SW Rev'!M6-1,""),"") | ... N211: =IFERROR(IF(AND(ISNUMBER('SW Rev'!R6),ISNUMBER('SW Rev'!Q6),'SW Rev'!Q6>0),'SW Rev'!R6/'SW Rev'!Q6-1,""),"")
A212: ='SW Rev'!$A7 | B212: ='SW Rev'!$B7 | C212: =IFERROR(IF(AND(ISNUMBER('SW Rev'!G7),ISNUMBER('SW Rev'!F7),'SW Rev'!F7>0),'SW Rev'!G7/'SW Rev'!F7-1,""),"") | D212: =IFERROR(IF(AND(ISNUMBER('SW Rev'!H7),ISNUMBER('SW Rev'!G7),'SW Rev'!G7>0),'SW Rev'!H7/'SW Rev'!G7-1,""),"") | E212: =IFERROR(IF(AND(ISNUMBER('SW Rev'!I7),ISNUMBER('SW Rev'!H7),'SW Rev'!H7>0),'SW Rev'!I7/'SW Rev'!H7-1,""),"") | F212: =IFERROR(IF(AND(ISNUMBER('SW Rev'!J7),ISNUMBER('SW Rev'!I7),'SW Rev'!I7>0),'SW Rev'!J7/'SW Rev'!I7-1,""),"") | G212: =IFERROR(IF(AND(ISNUMBER('SW Rev'!K7),ISNUMBER('SW Rev'!J7),'SW Rev'!J7>0),'SW Rev'!K7/'SW Rev'!J7-1,""),"") | H212: =IFERROR(IF(AND(ISNUMBER('SW Rev'!L7),ISNUMBER('SW Rev'!K7),'SW Rev'!K7>0),'SW Rev'!L7/'SW Rev'!K7-1,""),"") | I212: =IFERROR(IF(AND(ISNUMBER('SW Rev'!M7),ISNUMBER('SW Rev'!L7),'SW Rev'!L7>0),'SW Rev'!M7/'SW Rev'!L7-1,""),"") | J212: =IFERROR(IF(AND(ISNUMBER('SW Rev'!N7),ISNUMBER('SW Rev'!M7),'SW Rev'!M7>0),'SW Rev'!N7/'SW Rev'!M7-1,""),"") | ... N212: =IFERROR(IF(AND(ISNUMBER('SW Rev'!R7),ISNUMBER('SW Rev'!Q7),'SW Rev'!Q7>0),'SW Rev'!R7/'SW Rev'!Q7-1,""),"")
A213: ='SW Rev'!$A8 | B213: ='SW Rev'!$B8 | C213: =IFERROR(IF(AND(ISNUMBER('SW Rev'!G8),ISNUMBER('SW Rev'!F8),'SW Rev'!F8>0),'SW Rev'!G8/'SW Rev'!F8-1,""),"") | D213: =IFERROR(IF(AND(ISNUMBER('SW Rev'!H8),ISNUMBER('SW Rev'!G8),'SW Rev'!G8>0),'SW Rev'!H8/'SW Rev'!G8-1,""),"") | E213: =IFERROR(IF(AND(ISNUMBER('SW Rev'!I8),ISNUMBER('SW Rev'!H8),'SW Rev'!H8>0),'SW Rev'!I8/'SW Rev'!H8-1,""),"") | F213: =IFERROR(IF(AND(ISNUMBER('SW Rev'!J8),ISNUMBER('SW Rev'!I8),'SW Rev'!I8>0),'SW Rev'!J8/'SW Rev'!I8-1,""),"") | G213: =IFERROR(IF(AND(ISNUMBER('SW Rev'!K8),ISNUMBER('SW Rev'!J8),'SW Rev'!J8>0),'SW Rev'!K8/'SW Rev'!J8-1,""),"") | H213: =IFERROR(IF(AND(ISNUMBER('SW Rev'!L8),ISNUMBER('SW Rev'!K8),'SW Rev'!K8>0),'SW Rev'!L8/'SW Rev'!K8-1,""),"") | I213: =IFERROR(IF(AND(ISNUMBER('SW Rev'!M8),ISNUMBER('SW Rev'!L8),'SW Rev'!L8>0),'SW Rev'!M8/'SW Rev'!L8-1,""),"") | J213: =IFERROR(IF(AND(ISNUMBER('SW Rev'!N8),ISNUMBER('SW Rev'!M8),'SW Rev'!M8>0),'SW Rev'!N8/'SW Rev'!M8-1,""),"") | ... N213: =IFERROR(IF(AND(ISNUMBER('SW Rev'!R8),ISNUMBER('SW Rev'!Q8),'SW Rev'!Q8>0),'SW Rev'!R8/'SW Rev'!Q8-1,""),"")
A214: ='SW Rev'!$A9 | B214: ='SW Rev'!$B9 | C214: =IFERROR(IF(AND(ISNUMBER('SW Rev'!G9),ISNUMBER('SW Rev'!F9),'SW Rev'!F9>0),'SW Rev'!G9/'SW Rev'!F9-1,""),"") | D214: =IFERROR(IF(AND(ISNUMBER('SW Rev'!H9),ISNUMBER('SW Rev'!G9),'SW Rev'!G9>0),'SW Rev'!H9/'SW Rev'!G9-1,""),"") | E214: =IFERROR(IF(AND(ISNUMBER('SW Rev'!I9),ISNUMBER('SW Rev'!H9),'SW Rev'!H9>0),'SW Rev'!I9/'SW Rev'!H9-1,""),"") | F214: =IFERROR(IF(AND(ISNUMBER('SW Rev'!J9),ISNUMBER('SW Rev'!I9),'SW Rev'!I9>0),'SW Rev'!J9/'SW Rev'!I9-1,""),"") | G214: =IFERROR(IF(AND(ISNUMBER('SW Rev'!K9),ISNUMBER('SW Rev'!J9),'SW Rev'!J9>0),'SW Rev'!K9/'SW Rev'!J9-1,""),"") | H214: =IFERROR(IF(AND(ISNUMBER('SW Rev'!L9),ISNUMBER('SW Rev'!K9),'SW Rev'!K9>0),'SW Rev'!L9/'SW Rev'!K9-1,""),"") | I214: =IFERROR(IF(AND(ISNUMBER('SW Rev'!M9),ISNUMBER('SW Rev'!L9),'SW Rev'!L9>0),'SW Rev'!M9/'SW Rev'!L9-1,""),"") | J214: =IFERROR(IF(AND(ISNUMBER('SW Rev'!N9),ISNUMBER('SW Rev'!M9),'SW Rev'!M9>0),'SW Rev'!N9/'SW Rev'!M9-1,""),"") | ... N214: =IFERROR(IF(AND(ISNUMBER('SW Rev'!R9),ISNUMBER('SW Rev'!Q9),'SW Rev'!Q9>0),'SW Rev'!R9/'SW Rev'!Q9-1,""),"")
A215: ='SW Rev'!$A10 | B215: ='SW Rev'!$B10 | C215: =IFERROR(IF(AND(ISNUMBER('SW Rev'!G10),ISNUMBER('SW Rev'!F10),'SW Rev'!F10>0),'SW Rev'!G10/'SW Rev'!F10-1,""),"") | D215: =IFERROR(IF(AND(ISNUMBER('SW Rev'!H10),ISNUMBER('SW Rev'!G10),'SW Rev'!G10>0),'SW Rev'!H10/'SW Rev'!G10-1,""),"") | E215: =IFERROR(IF(AND(ISNUMBER('SW Rev'!I10),ISNUMBER('SW Rev'!H10),'SW Rev'!H10>0),'SW Rev'!I10/'SW Rev'!H10-1,""),"") | F215: =IFERROR(IF(AND(ISNUMBER('SW Rev'!J10),ISNUMBER('SW Rev'!I10),'SW Rev'!I10>0),'SW Rev'!J10/'SW Rev'!I10-1,""),"") | G215: =IFERROR(IF(AND(ISNUMBER('SW Rev'!K10),ISNUMBER('SW Rev'!J10),'SW Rev'!J10>0),'SW Rev'!K10/'SW Rev'!J10-1,""),"") | H215: =IFERROR(IF(AND(ISNUMBER('SW Rev'!L10),ISNUMBER('SW Rev'!K10),'SW Rev'!K10>0),'SW Rev'!L10/'SW Rev'!K10-1,""),"") | I215: =IFERROR(IF(AND(ISNUMBER('SW Rev'!M10),ISNUMBER('SW Rev'!L10),'SW Rev'!L10>0),'SW Rev'!M10/'SW Rev'!L10-1,""),"") | J215: =IFERROR(IF(AND(ISNUMBER('SW Rev'!N10),ISNUMBER('SW Rev'!M10),'SW Rev'!M10>0),'SW Rev'!N10/'SW Rev'!M10-1,""),"") | ... N215: =IFERROR(IF(AND(ISNUMBER('SW Rev'!R10),ISNUMBER('SW Rev'!Q10),'SW Rev'!Q10>0),'SW Rev'!R10/'SW Rev'!Q10-1,""),"")
A216: ='SW Rev'!$A11 | B216: ='SW Rev'!$B11 | C216: =IFERROR(IF(AND(ISNUMBER('SW Rev'!G11),ISNUMBER('SW Rev'!F11),'SW Rev'!F11>0),'SW Rev'!G11/'SW Rev'!F11-1,""),"") | D216: =IFERROR(IF(AND(ISNUMBER('SW Rev'!H11),ISNUMBER('SW Rev'!G11),'SW Rev'!G11>0),'SW Rev'!H11/'SW Rev'!G11-1,""),"") | E216: =IFERROR(IF(AND(ISNUMBER('SW Rev'!I11),ISNUMBER('SW Rev'!H11),'SW Rev'!H11>0),'SW Rev'!I11/'SW Rev'!H11-1,""),"") | F216: =IFERROR(IF(AND(ISNUMBER('SW Rev'!J11),ISNUMBER('SW Rev'!I11),'SW Rev'!I11>0),'SW Rev'!J11/'SW Rev'!I11-1,""),"") | G216: =IFERROR(IF(AND(ISNUMBER('SW Rev'!K11),ISNUMBER('SW Rev'!J11),'SW Rev'!J11>0),'SW Rev'!K11/'SW Rev'!J11-1,""),"") | H216: =IFERROR(IF(AND(ISNUMBER('SW Rev'!L11),ISNUMBER('SW Rev'!K11),'SW Rev'!K11>0),'SW Rev'!L11/'SW Rev'!K11-1,""),"") | I216: =IFERROR(IF(AND(ISNUMBER('SW Rev'!M11),ISNUMBER('SW Rev'!L11),'SW Rev'!L11>0),'SW Rev'!M11/'SW Rev'!L11-1,""),"") | J216: =IFERROR(IF(AND(ISNUMBER('SW Rev'!N11),ISNUMBER('SW Rev'!M11),'SW Rev'!M11>0),'SW Rev'!N11/'SW Rev'!M11-1,""),"") | ... N216: =IFERROR(IF(AND(ISNUMBER('SW Rev'!R11),ISNUMBER('SW Rev'!Q11),'SW Rev'!Q11>0),'SW Rev'!R11/'SW Rev'!Q11-1,""),"")
A217: ='SW Rev'!$A12 | B217: ='SW Rev'!$B12 | C217: =IFERROR(IF(AND(ISNUMBER('SW Rev'!G12),ISNUMBER('SW Rev'!F12),'SW Rev'!F12>0),'SW Rev'!G12/'SW Rev'!F12-1,""),"") | D217: =IFERROR(IF(AND(ISNUMBER('SW Rev'!H12),ISNUMBER('SW Rev'!G12),'SW Rev'!G12>0),'SW Rev'!H12/'SW Rev'!G12-1,""),"") | E217: =IFERROR(IF(AND(ISNUMBER('SW Rev'!I12),ISNUMBER('SW Rev'!H12),'SW Rev'!H12>0),'SW Rev'!I12/'SW Rev'!H12-1,""),"") | F217: =IFERROR(IF(AND(ISNUMBER('SW Rev'!J12),ISNUMBER('SW Rev'!I12),'SW Rev'!I12>0),'SW Rev'!J12/'SW Rev'!I12-1,""),"") | G217: =IFERROR(IF(AND(ISNUMBER('SW Rev'!K12),ISNUMBER('SW Rev'!J12),'SW Rev'!J12>0),'SW Rev'!K12/'SW Rev'!J12-1,""),"") | H217: =IFERROR(IF(AND(ISNUMBER('SW Rev'!L12),ISNUMBER('SW Rev'!K12),'SW Rev'!K12>0),'SW Rev'!L12/'SW Rev'!K12-1,""),"") | I217: =IFERROR(IF(AND(ISNUMBER('SW Rev'!M12),ISNUMBER('SW Rev'!L12),'SW Rev'!L12>0),'SW Rev'!M12/'SW Rev'!L12-1,""),"") | J217: =IFERROR(IF(AND(ISNUMBER('SW Rev'!N12),ISNUMBER('SW Rev'!M12),'SW Rev'!M12>0),'SW Rev'!N12/'SW Rev'!M12-1,""),"") | ... N217: =IFERROR(IF(AND(ISNUMBER('SW Rev'!R12),ISNUMBER('SW Rev'!Q12),'SW Rev'!Q12>0),'SW Rev'!R12/'SW Rev'!Q12-1,""),"")
A218: ='SW Rev'!$A13 | B218: ='SW Rev'!$B13 | C218: =IFERROR(IF(AND(ISNUMBER('SW Rev'!G13),ISNUMBER('SW Rev'!F13),'SW Rev'!F13>0),'SW Rev'!G13/'SW Rev'!F13-1,""),"") | D218: =IFERROR(IF(AND(ISNUMBER('SW Rev'!H13),ISNUMBER('SW Rev'!G13),'SW Rev'!G13>0),'SW Rev'!H13/'SW Rev'!G13-1,""),"") | E218: =IFERROR(IF(AND(ISNUMBER('SW Rev'!I13),ISNUMBER('SW Rev'!H13),'SW Rev'!H13>0),'SW Rev'!I13/'SW Rev'!H13-1,""),"") | F218: =IFERROR(IF(AND(ISNUMBER('SW Rev'!J13),ISNUMBER('SW Rev'!I13),'SW Rev'!I13>0),'SW Rev'!J13/'SW Rev'!I13-1,""),"") | G218: =IFERROR(IF(AND(ISNUMBER('SW Rev'!K13),ISNUMBER('SW Rev'!J13),'SW Rev'!J13>0),'SW Rev'!K13/'SW Rev'!J13-1,""),"") | H218: =IFERROR(IF(AND(ISNUMBER('SW Rev'!L13),ISNUMBER('SW Rev'!K13),'SW Rev'!K13>0),'SW Rev'!L13/'SW Rev'!K13-1,""),"") | I218: =IFERROR(IF(AND(ISNUMBER('SW Rev'!M13),ISNUMBER('SW Rev'!L13),'SW Rev'!L13>0),'SW Rev'!M13/'SW Rev'!L13-1,""),"") | J218: =IFERROR(IF(AND(ISNUMBER('SW Rev'!N13),ISNUMBER('SW Rev'!M13),'SW Rev'!M13>0),'SW Rev'!N13/'SW Rev'!M13-1,""),"") | ... N218: =IFERROR(IF(AND(ISNUMBER('SW Rev'!R13),ISNUMBER('SW Rev'!Q13),'SW Rev'!Q13>0),'SW Rev'!R13/'SW Rev'!Q13-1,""),"")
A219: ='SW Rev'!$A14 | B219: ='SW Rev'!$B14 | C219: =IFERROR(IF(AND(ISNUMBER('SW Rev'!G14),ISNUMBER('SW Rev'!F14),'SW Rev'!F14>0),'SW Rev'!G14/'SW Rev'!F14-1,""),"") | D219: =IFERROR(IF(AND(ISNUMBER('SW Rev'!H14),ISNUMBER('SW Rev'!G14),'SW Rev'!G14>0),'SW Rev'!H14/'SW Rev'!G14-1,""),"") | E219: =IFERROR(IF(AND(ISNUMBER('SW Rev'!I14),ISNUMBER('SW Rev'!H14),'SW Rev'!H14>0),'SW Rev'!I14/'SW Rev'!H14-1,""),"") | F219: =IFERROR(IF(AND(ISNUMBER('SW Rev'!J14),ISNUMBER('SW Rev'!I14),'SW Rev'!I14>0),'SW Rev'!J14/'SW Rev'!I14-1,""),"") | G219: =IFERROR(IF(AND(ISNUMBER('SW Rev'!K14),ISNUMBER('SW Rev'!J14),'SW Rev'!J14>0),'SW Rev'!K14/'SW Rev'!J14-1,""),"") | H219: =IFERROR(IF(AND(ISNUMBER('SW Rev'!L14),ISNUMBER('SW Rev'!K14),'SW Rev'!K14>0),'SW Rev'!L14/'SW Rev'!K14-1,""),"") | I219: =IFERROR(IF(AND(ISNUMBER('SW Rev'!M14),ISNUMBER('SW Rev'!L14),'SW Rev'!L14>0),'SW Rev'!M14/'SW Rev'!L14-1,""),"") | J219: =IFERROR(IF(AND(ISNUMBER('SW Rev'!N14),ISNUMBER('SW Rev'!M14),'SW Rev'!M14>0),'SW Rev'!N14/'SW Rev'!M14-1,""),"") | ... N219: =IFERROR(IF(AND(ISNUMBER('SW Rev'!R14),ISNUMBER('SW Rev'!Q14),'SW Rev'!Q14>0),'SW Rev'!R14/'SW Rev'!Q14-1,""),"")
A220: ='SW Rev'!$A15 | B220: ='SW Rev'!$B15 | C220: =IFERROR(IF(AND(ISNUMBER('SW Rev'!G15),ISNUMBER('SW Rev'!F15),'SW Rev'!F15>0),'SW Rev'!G15/'SW Rev'!F15-1,""),"") | D220: =IFERROR(IF(AND(ISNUMBER('SW Rev'!H15),ISNUMBER('SW Rev'!G15),'SW Rev'!G15>0),'SW Rev'!H15/'SW Rev'!G15-1,""),"") | E220: =IFERROR(IF(AND(ISNUMBER('SW Rev'!I15),ISNUMBER('SW Rev'!H15),'SW Rev'!H15>0),'SW Rev'!I15/'SW Rev'!H15-1,""),"") | F220: =IFERROR(IF(AND(ISNUMBER('SW Rev'!J15),ISNUMBER('SW Rev'!I15),'SW Rev'!I15>0),'SW Rev'!J15/'SW Rev'!I15-1,""),"") | G220: =IFERROR(IF(AND(ISNUMBER('SW Rev'!K15),ISNUMBER('SW Rev'!J15),'SW Rev'!J15>0),'SW Rev'!K15/'SW Rev'!J15-1,""),"") | H220: =IFERROR(IF(AND(ISNUMBER('SW Rev'!L15),ISNUMBER('SW Rev'!K15),'SW Rev'!K15>0),'SW Rev'!L15/'SW Rev'!K15-1,""),"") | I220: =IFERROR(IF(AND(ISNUMBER('SW Rev'!M15),ISNUMBER('SW Rev'!L15),'SW Rev'!L15>0),'SW Rev'!M15/'SW Rev'!L15-1,""),"") | J220: =IFERROR(IF(AND(ISNUMBER('SW Rev'!N15),ISNUMBER('SW Rev'!M15),'SW Rev'!M15>0),'SW Rev'!N15/'SW Rev'!M15-1,""),"") | ... N220: =IFERROR(IF(AND(ISNUMBER('SW Rev'!R15),ISNUMBER('SW Rev'!Q15),'SW Rev'!Q15>0),'SW Rev'!R15/'SW Rev'!Q15-1,""),"")
A221: ='SW Rev'!$A16 | B221: ='SW Rev'!$B16 | C221: =IFERROR(IF(AND(ISNUMBER('SW Rev'!G16),ISNUMBER('SW Rev'!F16),'SW Rev'!F16>0),'SW Rev'!G16/'SW Rev'!F16-1,""),"") | D221: =IFERROR(IF(AND(ISNUMBER('SW Rev'!H16),ISNUMBER('SW Rev'!G16),'SW Rev'!G16>0),'SW Rev'!H16/'SW Rev'!G16-1,""),"") | E221: =IFERROR(IF(AND(ISNUMBER('SW Rev'!I16),ISNUMBER('SW Rev'!H16),'SW Rev'!H16>0),'SW Rev'!I16/'SW Rev'!H16-1,""),"") | F221: =IFERROR(IF(AND(ISNUMBER('SW Rev'!J16),ISNUMBER('SW Rev'!I16),'SW Rev'!I16>0),'SW Rev'!J16/'SW Rev'!I16-1,""),"") | G221: =IFERROR(IF(AND(ISNUMBER('SW Rev'!K16),ISNUMBER('SW Rev'!J16),'SW Rev'!J16>0),'SW Rev'!K16/'SW Rev'!J16-1,""),"") | H221: =IFERROR(IF(AND(ISNUMBER('SW Rev'!L16),ISNUMBER('SW Rev'!K16),'SW Rev'!K16>0),'SW Rev'!L16/'SW Rev'!K16-1,""),"") | I221: =IFERROR(IF(AND(ISNUMBER('SW Rev'!M16),ISNUMBER('SW Rev'!L16),'SW Rev'!L16>0),'SW Rev'!M16/'SW Rev'!L16-1,""),"") | J221: =IFERROR(IF(AND(ISNUMBER('SW Rev'!N16),ISNUMBER('SW Rev'!M16),'SW Rev'!M16>0),'SW Rev'!N16/'SW Rev'!M16-1,""),"") | ... N221: =IFERROR(IF(AND(ISNUMBER('SW Rev'!R16),ISNUMBER('SW Rev'!Q16),'SW Rev'!Q16>0),'SW Rev'!R16/'SW Rev'!Q16-1,""),"")
... A308: ='SW Rev'!$A103 | B308: ='SW Rev'!$B103 | C308: =IFERROR(IF(AND(ISNUMBER('SW Rev'!G103),ISNUMBER('SW Rev'!F103),'SW Rev'!F103>0),'SW Rev'!G103/'SW Rev'!F103-1,""),"") | D308: =IFERROR(IF(AND(ISNUMBER('SW Rev'!H103),ISNUMBER('SW Rev'!G103),'SW Rev'!G103>0),'SW Rev'!H103/'SW Rev'!G103-1,""),"") | E308: =IFERROR(IF(AND(ISNUMBER('SW Rev'!I103),ISNUMBER('SW Rev'!H103),'SW Rev'!H103>0),'SW Rev'!I103/'SW Rev'!H103-1,""),"") | F308: =IFERROR(IF(AND(ISNUMBER('SW Rev'!J103),ISNUMBER('SW Rev'!I103),'SW Rev'!I103>0),'SW Rev'!J103/'SW Rev'!I103-1,""),"") | G308: =IFERROR(IF(AND(ISNUMBER('SW Rev'!K103),ISNUMBER('SW Rev'!J103),'SW Rev'!J103>0),'SW Rev'!K103/'SW Rev'!J103-1,""),"") | H308: =IFERROR(IF(AND(ISNUMBER('SW Rev'!L103),ISNUMBER('SW Rev'!K103),'SW Rev'!K103>0),'SW Rev'!L103/'SW Rev'!K103-1,""),"") | I308: =IFERROR(IF(AND(ISNUMBER('SW Rev'!M103),ISNUMBER('SW Rev'!L103),'SW Rev'!L103>0),'SW Rev'!M103/'SW Rev'!L103-1,""),"") | J308: =IFERROR(IF(AND(ISNUMBER('SW Rev'!N103),ISNUMBER('SW Rev'!M103),'SW Rev'!M103>0),'SW Rev'!N103/'SW Rev'!M103-1,""),"") | ... N308: =IFERROR(IF(AND(ISNUMBER('SW Rev'!R103),ISNUMBER('SW Rev'!Q103),'SW Rev'!Q103>0),'SW Rev'!R103/'SW Rev'!Q103-1,""),"")
A310: Revenue $ added YoY (USD mm)
A311: Ticker | B311: Latest Rpt Qtr | C311: FPO -9 | D311: FPO -8 | E311: FPO -7 | F311: FPO -6 | G311: FPO -5 | H311: FPO -4 | I311: FPO -3 | J311: FPO -2 | K311: FPO -1 | L311: FPO 0 (latest rpt) | M311: FPO +1E | N311: FPO +2E
A312: ='SW Rev'!$A5 | B312: ='SW Rev'!$B5 | C312: =IFERROR(IF(AND(ISNUMBER('SW Rev'!G5),ISNUMBER('SW Rev'!C5)),'SW Rev'!G5-'SW Rev'!C5,""),"") | D312: =IFERROR(IF(AND(ISNUMBER('SW Rev'!H5),ISNUMBER('SW Rev'!D5)),'SW Rev'!H5-'SW Rev'!D5,""),"") | E312: =IFERROR(IF(AND(ISNUMBER('SW Rev'!I5),ISNUMBER('SW Rev'!E5)),'SW Rev'!I5-'SW Rev'!E5,""),"") | F312: =IFERROR(IF(AND(ISNUMBER('SW Rev'!J5),ISNUMBER('SW Rev'!F5)),'SW Rev'!J5-'SW Rev'!F5,""),"") | G312: =IFERROR(IF(AND(ISNUMBER('SW Rev'!K5),ISNUMBER('SW Rev'!G5)),'SW Rev'!K5-'SW Rev'!G5,""),"") | H312: =IFERROR(IF(AND(ISNUMBER('SW Rev'!L5),ISNUMBER('SW Rev'!H5)),'SW Rev'!L5-'SW Rev'!H5,""),"") | I312: =IFERROR(IF(AND(ISNUMBER('SW Rev'!M5),ISNUMBER('SW Rev'!I5)),'SW Rev'!M5-'SW Rev'!I5,""),"") | J312: =IFERROR(IF(AND(ISNUMBER('SW Rev'!N5),ISNUMBER('SW Rev'!J5)),'SW Rev'!N5-'SW Rev'!J5,""),"") | ... N312: =IFERROR(IF(AND(ISNUMBER('SW Rev'!R5),ISNUMBER('SW Rev'!N5)),'SW Rev'!R5-'SW Rev'!N5,""),"")
A313: ='SW Rev'!$A6 | B313: ='SW Rev'!$B6 | C313: =IFERROR(IF(AND(ISNUMBER('SW Rev'!G6),ISNUMBER('SW Rev'!C6)),'SW Rev'!G6-'SW Rev'!C6,""),"") | D313: =IFERROR(IF(AND(ISNUMBER('SW Rev'!H6),ISNUMBER('SW Rev'!D6)),'SW Rev'!H6-'SW Rev'!D6,""),"") | E313: =IFERROR(IF(AND(ISNUMBER('SW Rev'!I6),ISNUMBER('SW Rev'!E6)),'SW Rev'!I6-'SW Rev'!E6,""),"") | F313: =IFERROR(IF(AND(ISNUMBER('SW Rev'!J6),ISNUMBER('SW Rev'!F6)),'SW Rev'!J6-'SW Rev'!F6,""),"") | G313: =IFERROR(IF(AND(ISNUMBER('SW Rev'!K6),ISNUMBER('SW Rev'!G6)),'SW Rev'!K6-'SW Rev'!G6,""),"") | H313: =IFERROR(IF(AND(ISNUMBER('SW Rev'!L6),ISNUMBER('SW Rev'!H6)),'SW Rev'!L6-'SW Rev'!H6,""),"") | I313: =IFERROR(IF(AND(ISNUMBER('SW Rev'!M6),ISNUMBER('SW Rev'!I6)),'SW Rev'!M6-'SW Rev'!I6,""),"") | J313: =IFERROR(IF(AND(ISNUMBER('SW Rev'!N6),ISNUMBER('SW Rev'!J6)),'SW Rev'!N6-'SW Rev'!J6,""),"") | ... N313: =IFERROR(IF(AND(ISNUMBER('SW Rev'!R6),ISNUMBER('SW Rev'!N6)),'SW Rev'!R6-'SW Rev'!N6,""),"")
A314: ='SW Rev'!$A7 | B314: ='SW Rev'!$B7 | C314: =IFERROR(IF(AND(ISNUMBER('SW Rev'!G7),ISNUMBER('SW Rev'!C7)),'SW Rev'!G7-'SW Rev'!C7,""),"") | D314: =IFERROR(IF(AND(ISNUMBER('SW Rev'!H7),ISNUMBER('SW Rev'!D7)),'SW Rev'!H7-'SW Rev'!D7,""),"") | E314: =IFERROR(IF(AND(ISNUMBER('SW Rev'!I7),ISNUMBER('SW Rev'!E7)),'SW Rev'!I7-'SW Rev'!E7,""),"") | F314: =IFERROR(IF(AND(ISNUMBER('SW Rev'!J7),ISNUMBER('SW Rev'!F7)),'SW Rev'!J7-'SW Rev'!F7,""),"") | G314: =IFERROR(IF(AND(ISNUMBER('SW Rev'!K7),ISNUMBER('SW Rev'!G7)),'SW Rev'!K7-'SW Rev'!G7,""),"") | H314: =IFERROR(IF(AND(ISNUMBER('SW Rev'!L7),ISNUMBER('SW Rev'!H7)),'SW Rev'!L7-'SW Rev'!H7,""),"") | I314: =IFERROR(IF(AND(ISNUMBER('SW Rev'!M7),ISNUMBER('SW Rev'!I7)),'SW Rev'!M7-'SW Rev'!I7,""),"") | J314: =IFERROR(IF(AND(ISNUMBER('SW Rev'!N7),ISNUMBER('SW Rev'!J7)),'SW Rev'!N7-'SW Rev'!J7,""),"") | ... N314: =IFERROR(IF(AND(ISNUMBER('SW Rev'!R7),ISNUMBER('SW Rev'!N7)),'SW Rev'!R7-'SW Rev'!N7,""),"")
A315: ='SW Rev'!$A8 | B315: ='SW Rev'!$B8 | C315: =IFERROR(IF(AND(ISNUMBER('SW Rev'!G8),ISNUMBER('SW Rev'!C8)),'SW Rev'!G8-'SW Rev'!C8,""),"") | D315: =IFERROR(IF(AND(ISNUMBER('SW Rev'!H8),ISNUMBER('SW Rev'!D8)),'SW Rev'!H8-'SW Rev'!D8,""),"") | E315: =IFERROR(IF(AND(ISNUMBER('SW Rev'!I8),ISNUMBER('SW Rev'!E8)),'SW Rev'!I8-'SW Rev'!E8,""),"") | F315: =IFERROR(IF(AND(ISNUMBER('SW Rev'!J8),ISNUMBER('SW Rev'!F8)),'SW Rev'!J8-'SW Rev'!F8,""),"") | G315: =IFERROR(IF(AND(ISNUMBER('SW Rev'!K8),ISNUMBER('SW Rev'!G8)),'SW Rev'!K8-'SW Rev'!G8,""),"") | H315: =IFERROR(IF(AND(ISNUMBER('SW Rev'!L8),ISNUMBER('SW Rev'!H8)),'SW Rev'!L8-'SW Rev'!H8,""),"") | I315: =IFERROR(IF(AND(ISNUMBER('SW Rev'!M8),ISNUMBER('SW Rev'!I8)),'SW Rev'!M8-'SW Rev'!I8,""),"") | J315: =IFERROR(IF(AND(ISNUMBER('SW Rev'!N8),ISNUMBER('SW Rev'!J8)),'SW Rev'!N8-'SW Rev'!J8,""),"") | ... N315: =IFERROR(IF(AND(ISNUMBER('SW Rev'!R8),ISNUMBER('SW Rev'!N8)),'SW Rev'!R8-'SW Rev'!N8,""),"")
A316: ='SW Rev'!$A9 | B316: ='SW Rev'!$B9 | C316: =IFERROR(IF(AND(ISNUMBER('SW Rev'!G9),ISNUMBER('SW Rev'!C9)),'SW Rev'!G9-'SW Rev'!C9,""),"") | D316: =IFERROR(IF(AND(ISNUMBER('SW Rev'!H9),ISNUMBER('SW Rev'!D9)),'SW Rev'!H9-'SW Rev'!D9,""),"") | E316: =IFERROR(IF(AND(ISNUMBER('SW Rev'!I9),ISNUMBER('SW Rev'!E9)),'SW Rev'!I9-'SW Rev'!E9,""),"") | F316: =IFERROR(IF(AND(ISNUMBER('SW Rev'!J9),ISNUMBER('SW Rev'!F9)),'SW Rev'!J9-'SW Rev'!F9,""),"") | G316: =IFERROR(IF(AND(ISNUMBER('SW Rev'!K9),ISNUMBER('SW Rev'!G9)),'SW Rev'!K9-'SW Rev'!G9,""),"") | H316: =IFERROR(IF(AND(ISNUMBER('SW Rev'!L9),ISNUMBER('SW Rev'!H9)),'SW Rev'!L9-'SW Rev'!H9,""),"") | I316: =IFERROR(IF(AND(ISNUMBER('SW Rev'!M9),ISNUMBER('SW Rev'!I9)),'SW Rev'!M9-'SW Rev'!I9,""),"") | J316: =IFERROR(IF(AND(ISNUMBER('SW Rev'!N9),ISNUMBER('SW Rev'!J9)),'SW Rev'!N9-'SW Rev'!J9,""),"") | ... N316: =IFERROR(IF(AND(ISNUMBER('SW Rev'!R9),ISNUMBER('SW Rev'!N9)),'SW Rev'!R9-'SW Rev'!N9,""),"")
A317: ='SW Rev'!$A10 | B317: ='SW Rev'!$B10 | C317: =IFERROR(IF(AND(ISNUMBER('SW Rev'!G10),ISNUMBER('SW Rev'!C10)),'SW Rev'!G10-'SW Rev'!C10,""),"") | D317: =IFERROR(IF(AND(ISNUMBER('SW Rev'!H10),ISNUMBER('SW Rev'!D10)),'SW Rev'!H10-'SW Rev'!D10,""),"") | E317: =IFERROR(IF(AND(ISNUMBER('SW Rev'!I10),ISNUMBER('SW Rev'!E10)),'SW Rev'!I10-'SW Rev'!E10,""),"") | F317: =IFERROR(IF(AND(ISNUMBER('SW Rev'!J10),ISNUMBER('SW Rev'!F10)),'SW Rev'!J10-'SW Rev'!F10,""),"") | G317: =IFERROR(IF(AND(ISNUMBER('SW Rev'!K10),ISNUMBER('SW Rev'!G10)),'SW Rev'!K10-'SW Rev'!G10,""),"") | H317: =IFERROR(IF(AND(ISNUMBER('SW Rev'!L10),ISNUMBER('SW Rev'!H10)),'SW Rev'!L10-'SW Rev'!H10,""),"") | I317: =IFERROR(IF(AND(ISNUMBER('SW Rev'!M10),ISNUMBER('SW Rev'!I10)),'SW Rev'!M10-'SW Rev'!I10,""),"") | J317: =IFERROR(IF(AND(ISNUMBER('SW Rev'!N10),ISNUMBER('SW Rev'!J10)),'SW Rev'!N10-'SW Rev'!J10,""),"") | ... N317: =IFERROR(IF(AND(ISNUMBER('SW Rev'!R10),ISNUMBER('SW Rev'!N10)),'SW Rev'!R10-'SW Rev'!N10,""),"")
A318: ='SW Rev'!$A11 | B318: ='SW Rev'!$B11 | C318: =IFERROR(IF(AND(ISNUMBER('SW Rev'!G11),ISNUMBER('SW Rev'!C11)),'SW Rev'!G11-'SW Rev'!C11,""),"") | D318: =IFERROR(IF(AND(ISNUMBER('SW Rev'!H11),ISNUMBER('SW Rev'!D11)),'SW Rev'!H11-'SW Rev'!D11,""),"") | E318: =IFERROR(IF(AND(ISNUMBER('SW Rev'!I11),ISNUMBER('SW Rev'!E11)),'SW Rev'!I11-'SW Rev'!E11,""),"") | F318: =IFERROR(IF(AND(ISNUMBER('SW Rev'!J11),ISNUMBER('SW Rev'!F11)),'SW Rev'!J11-'SW Rev'!F11,""),"") | G318: =IFERROR(IF(AND(ISNUMBER('SW Rev'!K11),ISNUMBER('SW Rev'!G11)),'SW Rev'!K11-'SW Rev'!G11,""),"") | H318: =IFERROR(IF(AND(ISNUMBER('SW Rev'!L11),ISNUMBER('SW Rev'!H11)),'SW Rev'!L11-'SW Rev'!H11,""),"") | I318: =IFERROR(IF(AND(ISNUMBER('SW Rev'!M11),ISNUMBER('SW Rev'!I11)),'SW Rev'!M11-'SW Rev'!I11,""),"") | J318: =IFERROR(IF(AND(ISNUMBER('SW Rev'!N11),ISNUMBER('SW Rev'!J11)),'SW Rev'!N11-'SW Rev'!J11,""),"") | ... N318: =IFERROR(IF(AND(ISNUMBER('SW Rev'!R11),ISNUMBER('SW Rev'!N11)),'SW Rev'!R11-'SW Rev'!N11,""),"")
A319: ='SW Rev'!$A12 | B319: ='SW Rev'!$B12 | C319: =IFERROR(IF(AND(ISNUMBER('SW Rev'!G12),ISNUMBER('SW Rev'!C12)),'SW Rev'!G12-'SW Rev'!C12,""),"") | D319: =IFERROR(IF(AND(ISNUMBER('SW Rev'!H12),ISNUMBER('SW Rev'!D12)),'SW Rev'!H12-'SW Rev'!D12,""),"") | E319: =IFERROR(IF(AND(ISNUMBER('SW Rev'!I12),ISNUMBER('SW Rev'!E12)),'SW Rev'!I12-'SW Rev'!E12,""),"") | F319: =IFERROR(IF(AND(ISNUMBER('SW Rev'!J12),ISNUMBER('SW Rev'!F12)),'SW Rev'!J12-'SW Rev'!F12,""),"") | G319: =IFERROR(IF(AND(ISNUMBER('SW Rev'!K12),ISNUMBER('SW Rev'!G12)),'SW Rev'!K12-'SW Rev'!G12,""),"") | H319: =IFERROR(IF(AND(ISNUMBER('SW Rev'!L12),ISNUMBER('SW Rev'!H12)),'SW Rev'!L12-'SW Rev'!H12,""),"") | I319: =IFERROR(IF(AND(ISNUMBER('SW Rev'!M12),ISNUMBER('SW Rev'!I12)),'SW Rev'!M12-'SW Rev'!I12,""),"") | J319: =IFERROR(IF(AND(ISNUMBER('SW Rev'!N12),ISNUMBER('SW Rev'!J12)),'SW Rev'!N12-'SW Rev'!J12,""),"") | ... N319: =IFERROR(IF(AND(ISNUMBER('SW Rev'!R12),ISNUMBER('SW Rev'!N12)),'SW Rev'!R12-'SW Rev'!N12,""),"")
A320: ='SW Rev'!$A13 | B320: ='SW Rev'!$B13 | C320: =IFERROR(IF(AND(ISNUMBER('SW Rev'!G13),ISNUMBER('SW Rev'!C13)),'SW Rev'!G13-'SW Rev'!C13,""),"") | D320: =IFERROR(IF(AND(ISNUMBER('SW Rev'!H13),ISNUMBER('SW Rev'!D13)),'SW Rev'!H13-'SW Rev'!D13,""),"") | E320: =IFERROR(IF(AND(ISNUMBER('SW Rev'!I13),ISNUMBER('SW Rev'!E13)),'SW Rev'!I13-'SW Rev'!E13,""),"") | F320: =IFERROR(IF(AND(ISNUMBER('SW Rev'!J13),ISNUMBER('SW Rev'!F13)),'SW Rev'!J13-'SW Rev'!F13,""),"") | G320: =IFERROR(IF(AND(ISNUMBER('SW Rev'!K13),ISNUMBER('SW Rev'!G13)),'SW Rev'!K13-'SW Rev'!G13,""),"") | H320: =IFERROR(IF(AND(ISNUMBER('SW Rev'!L13),ISNUMBER('SW Rev'!H13)),'SW Rev'!L13-'SW Rev'!H13,""),"") | I320: =IFERROR(IF(AND(ISNUMBER('SW Rev'!M13),ISNUMBER('SW Rev'!I13)),'SW Rev'!M13-'SW Rev'!I13,""),"") | J320: =IFERROR(IF(AND(ISNUMBER('SW Rev'!N13),ISNUMBER('SW Rev'!J13)),'SW Rev'!N13-'SW Rev'!J13,""),"") | ... N320: =IFERROR(IF(AND(ISNUMBER('SW Rev'!R13),ISNUMBER('SW Rev'!N13)),'SW Rev'!R13-'SW Rev'!N13,""),"")
A321: ='SW Rev'!$A14 | B321: ='SW Rev'!$B14 | C321: =IFERROR(IF(AND(ISNUMBER('SW Rev'!G14),ISNUMBER('SW Rev'!C14)),'SW Rev'!G14-'SW Rev'!C14,""),"") | D321: =IFERROR(IF(AND(ISNUMBER('SW Rev'!H14),ISNUMBER('SW Rev'!D14)),'SW Rev'!H14-'SW Rev'!D14,""),"") | E321: =IFERROR(IF(AND(ISNUMBER('SW Rev'!I14),ISNUMBER('SW Rev'!E14)),'SW Rev'!I14-'SW Rev'!E14,""),"") | F321: =IFERROR(IF(AND(ISNUMBER('SW Rev'!J14),ISNUMBER('SW Rev'!F14)),'SW Rev'!J14-'SW Rev'!F14,""),"") | G321: =IFERROR(IF(AND(ISNUMBER('SW Rev'!K14),ISNUMBER('SW Rev'!G14)),'SW Rev'!K14-'SW Rev'!G14,""),"") | H321: =IFERROR(IF(AND(ISNUMBER('SW Rev'!L14),ISNUMBER('SW Rev'!H14)),'SW Rev'!L14-'SW Rev'!H14,""),"") | I321: =IFERROR(IF(AND(ISNUMBER('SW Rev'!M14),ISNUMBER('SW Rev'!I14)),'SW Rev'!M14-'SW Rev'!I14,""),"") | J321: =IFERROR(IF(AND(ISNUMBER('SW Rev'!N14),ISNUMBER('SW Rev'!J14)),'SW Rev'!N14-'SW Rev'!J14,""),"") | ... N321: =IFERROR(IF(AND(ISNUMBER('SW Rev'!R14),ISNUMBER('SW Rev'!N14)),'SW Rev'!R14-'SW Rev'!N14,""),"")
A322: ='SW Rev'!$A15 | B322: ='SW Rev'!$B15 | C322: =IFERROR(IF(AND(ISNUMBER('SW Rev'!G15),ISNUMBER('SW Rev'!C15)),'SW Rev'!G15-'SW Rev'!C15,""),"") | D322: =IFERROR(IF(AND(ISNUMBER('SW Rev'!H15),ISNUMBER('SW Rev'!D15)),'SW Rev'!H15-'SW Rev'!D15,""),"") | E322: =IFERROR(IF(AND(ISNUMBER('SW Rev'!I15),ISNUMBER('SW Rev'!E15)),'SW Rev'!I15-'SW Rev'!E15,""),"") | F322: =IFERROR(IF(AND(ISNUMBER('SW Rev'!J15),ISNUMBER('SW Rev'!F15)),'SW Rev'!J15-'SW Rev'!F15,""),"") | G322: =IFERROR(IF(AND(ISNUMBER('SW Rev'!K15),ISNUMBER('SW Rev'!G15)),'SW Rev'!K15-'SW Rev'!G15,""),"") | H322: =IFERROR(IF(AND(ISNUMBER('SW Rev'!L15),ISNUMBER('SW Rev'!H15)),'SW Rev'!L15-'SW Rev'!H15,""),"") | I322: =IFERROR(IF(AND(ISNUMBER('SW Rev'!M15),ISNUMBER('SW Rev'!I15)),'SW Rev'!M15-'SW Rev'!I15,""),"") | J322: =IFERROR(IF(AND(ISNUMBER('SW Rev'!N15),ISNUMBER('SW Rev'!J15)),'SW Rev'!N15-'SW Rev'!J15,""),"") | ... N322: =IFERROR(IF(AND(ISNUMBER('SW Rev'!R15),ISNUMBER('SW Rev'!N15)),'SW Rev'!R15-'SW Rev'!N15,""),"")
A323: ='SW Rev'!$A16 | B323: ='SW Rev'!$B16 | C323: =IFERROR(IF(AND(ISNUMBER('SW Rev'!G16),ISNUMBER('SW Rev'!C16)),'SW Rev'!G16-'SW Rev'!C16,""),"") | D323: =IFERROR(IF(AND(ISNUMBER('SW Rev'!H16),ISNUMBER('SW Rev'!D16)),'SW Rev'!H16-'SW Rev'!D16,""),"") | E323: =IFERROR(IF(AND(ISNUMBER('SW Rev'!I16),ISNUMBER('SW Rev'!E16)),'SW Rev'!I16-'SW Rev'!E16,""),"") | F323: =IFERROR(IF(AND(ISNUMBER('SW Rev'!J16),ISNUMBER('SW Rev'!F16)),'SW Rev'!J16-'SW Rev'!F16,""),"") | G323: =IFERROR(IF(AND(ISNUMBER('SW Rev'!K16),ISNUMBER('SW Rev'!G16)),'SW Rev'!K16-'SW Rev'!G16,""),"") | H323: =IFERROR(IF(AND(ISNUMBER('SW Rev'!L16),ISNUMBER('SW Rev'!H16)),'SW Rev'!L16-'SW Rev'!H16,""),"") | I323: =IFERROR(IF(AND(ISNUMBER('SW Rev'!M16),ISNUMBER('SW Rev'!I16)),'SW Rev'!M16-'SW Rev'!I16,""),"") | J323: =IFERROR(IF(AND(ISNUMBER('SW Rev'!N16),ISNUMBER('SW Rev'!J16)),'SW Rev'!N16-'SW Rev'!J16,""),"") | ... N323: =IFERROR(IF(AND(ISNUMBER('SW Rev'!R16),ISNUMBER('SW Rev'!N16)),'SW Rev'!R16-'SW Rev'!N16,""),"")
... A410: ='SW Rev'!$A103 | B410: ='SW Rev'!$B103 | C410: =IFERROR(IF(AND(ISNUMBER('SW Rev'!G103),ISNUMBER('SW Rev'!C103)),'SW Rev'!G103-'SW Rev'!C103,""),"") | D410: =IFERROR(IF(AND(ISNUMBER('SW Rev'!H103),ISNUMBER('SW Rev'!D103)),'SW Rev'!H103-'SW Rev'!D103,""),"") | E410: =IFERROR(IF(AND(ISNUMBER('SW Rev'!I103),ISNUMBER('SW Rev'!E103)),'SW Rev'!I103-'SW Rev'!E103,""),"") | F410: =IFERROR(IF(AND(ISNUMBER('SW Rev'!J103),ISNUMBER('SW Rev'!F103)),'SW Rev'!J103-'SW Rev'!F103,""),"") | G410: =IFERROR(IF(AND(ISNUMBER('SW Rev'!K103),ISNUMBER('SW Rev'!G103)),'SW Rev'!K103-'SW Rev'!G103,""),"") | H410: =IFERROR(IF(AND(ISNUMBER('SW Rev'!L103),ISNUMBER('SW Rev'!H103)),'SW Rev'!L103-'SW Rev'!H103,""),"") | I410: =IFERROR(IF(AND(ISNUMBER('SW Rev'!M103),ISNUMBER('SW Rev'!I103)),'SW Rev'!M103-'SW Rev'!I103,""),"") | J410: =IFERROR(IF(AND(ISNUMBER('SW Rev'!N103),ISNUMBER('SW Rev'!J103)),'SW Rev'!N103-'SW Rev'!J103,""),"") | ... N410: =IFERROR(IF(AND(ISNUMBER('SW Rev'!R103),ISNUMBER('SW Rev'!N103)),'SW Rev'!R103-'SW Rev'!N103,""),"")
A412: Revenue $ added QoQ (USD mm)
A413: Ticker | B413: Latest Rpt Qtr | C413: FPO -9 | D413: FPO -8 | E413: FPO -7 | F413: FPO -6 | G413: FPO -5 | H413: FPO -4 | I413: FPO -3 | J413: FPO -2 | K413: FPO -1 | L413: FPO 0 (latest rpt) | M413: FPO +1E | N413: FPO +2E
A414: ='SW Rev'!$A5 | B414: ='SW Rev'!$B5 | C414: =IFERROR(IF(AND(ISNUMBER('SW Rev'!G5),ISNUMBER('SW Rev'!F5)),'SW Rev'!G5-'SW Rev'!F5,""),"") | D414: =IFERROR(IF(AND(ISNUMBER('SW Rev'!H5),ISNUMBER('SW Rev'!G5)),'SW Rev'!H5-'SW Rev'!G5,""),"") | E414: =IFERROR(IF(AND(ISNUMBER('SW Rev'!I5),ISNUMBER('SW Rev'!H5)),'SW Rev'!I5-'SW Rev'!H5,""),"") | F414: =IFERROR(IF(AND(ISNUMBER('SW Rev'!J5),ISNUMBER('SW Rev'!I5)),'SW Rev'!J5-'SW Rev'!I5,""),"") | G414: =IFERROR(IF(AND(ISNUMBER('SW Rev'!K5),ISNUMBER('SW Rev'!J5)),'SW Rev'!K5-'SW Rev'!J5,""),"") | H414: =IFERROR(IF(AND(ISNUMBER('SW Rev'!L5),ISNUMBER('SW Rev'!K5)),'SW Rev'!L5-'SW Rev'!K5,""),"") | I414: =IFERROR(IF(AND(ISNUMBER('SW Rev'!M5),ISNUMBER('SW Rev'!L5)),'SW Rev'!M5-'SW Rev'!L5,""),"") | J414: =IFERROR(IF(AND(ISNUMBER('SW Rev'!N5),ISNUMBER('SW Rev'!M5)),'SW Rev'!N5-'SW Rev'!M5,""),"") | ... N414: =IFERROR(IF(AND(ISNUMBER('SW Rev'!R5),ISNUMBER('SW Rev'!Q5)),'SW Rev'!R5-'SW Rev'!Q5,""),"")
A415: ='SW Rev'!$A6 | B415: ='SW Rev'!$B6 | C415: =IFERROR(IF(AND(ISNUMBER('SW Rev'!G6),ISNUMBER('SW Rev'!F6)),'SW Rev'!G6-'SW Rev'!F6,""),"") | D415: =IFERROR(IF(AND(ISNUMBER('SW Rev'!H6),ISNUMBER('SW Rev'!G6)),'SW Rev'!H6-'SW Rev'!G6,""),"") | E415: =IFERROR(IF(AND(ISNUMBER('SW Rev'!I6),ISNUMBER('SW Rev'!H6)),'SW Rev'!I6-'SW Rev'!H6,""),"") | F415: =IFERROR(IF(AND(ISNUMBER('SW Rev'!J6),ISNUMBER('SW Rev'!I6)),'SW Rev'!J6-'SW Rev'!I6,""),"") | G415: =IFERROR(IF(AND(ISNUMBER('SW Rev'!K6),ISNUMBER('SW Rev'!J6)),'SW Rev'!K6-'SW Rev'!J6,""),"") | H415: =IFERROR(IF(AND(ISNUMBER('SW Rev'!L6),ISNUMBER('SW Rev'!K6)),'SW Rev'!L6-'SW Rev'!K6,""),"") | I415: =IFERROR(IF(AND(ISNUMBER('SW Rev'!M6),ISNUMBER('SW Rev'!L6)),'SW Rev'!M6-'SW Rev'!L6,""),"") | J415: =IFERROR(IF(AND(ISNUMBER('SW Rev'!N6),ISNUMBER('SW Rev'!M6)),'SW Rev'!N6-'SW Rev'!M6,""),"") | ... N415: =IFERROR(IF(AND(ISNUMBER('SW Rev'!R6),ISNUMBER('SW Rev'!Q6)),'SW Rev'!R6-'SW Rev'!Q6,""),"")
A416: ='SW Rev'!$A7 | B416: ='SW Rev'!$B7 | C416: =IFERROR(IF(AND(ISNUMBER('SW Rev'!G7),ISNUMBER('SW Rev'!F7)),'SW Rev'!G7-'SW Rev'!F7,""),"") | D416: =IFERROR(IF(AND(ISNUMBER('SW Rev'!H7),ISNUMBER('SW Rev'!G7)),'SW Rev'!H7-'SW Rev'!G7,""),"") | E416: =IFERROR(IF(AND(ISNUMBER('SW Rev'!I7),ISNUMBER('SW Rev'!H7)),'SW Rev'!I7-'SW Rev'!H7,""),"") | F416: =IFERROR(IF(AND(ISNUMBER('SW Rev'!J7),ISNUMBER('SW Rev'!I7)),'SW Rev'!J7-'SW Rev'!I7,""),"") | G416: =IFERROR(IF(AND(ISNUMBER('SW Rev'!K7),ISNUMBER('SW Rev'!J7)),'SW Rev'!K7-'SW Rev'!J7,""),"") | H416: =IFERROR(IF(AND(ISNUMBER('SW Rev'!L7),ISNUMBER('SW Rev'!K7)),'SW Rev'!L7-'SW Rev'!K7,""),"") | I416: =IFERROR(IF(AND(ISNUMBER('SW Rev'!M7),ISNUMBER('SW Rev'!L7)),'SW Rev'!M7-'SW Rev'!L7,""),"") | J416: =IFERROR(IF(AND(ISNUMBER('SW Rev'!N7),ISNUMBER('SW Rev'!M7)),'SW Rev'!N7-'SW Rev'!M7,""),"") | ... N416: =IFERROR(IF(AND(ISNUMBER('SW Rev'!R7),ISNUMBER('SW Rev'!Q7)),'SW Rev'!R7-'SW Rev'!Q7,""),"")
A417: ='SW Rev'!$A8 | B417: ='SW Rev'!$B8 | C417: =IFERROR(IF(AND(ISNUMBER('SW Rev'!G8),ISNUMBER('SW Rev'!F8)),'SW Rev'!G8-'SW Rev'!F8,""),"") | D417: =IFERROR(IF(AND(ISNUMBER('SW Rev'!H8),ISNUMBER('SW Rev'!G8)),'SW Rev'!H8-'SW Rev'!G8,""),"") | E417: =IFERROR(IF(AND(ISNUMBER('SW Rev'!I8),ISNUMBER('SW Rev'!H8)),'SW Rev'!I8-'SW Rev'!H8,""),"") | F417: =IFERROR(IF(AND(ISNUMBER('SW Rev'!J8),ISNUMBER('SW Rev'!I8)),'SW Rev'!J8-'SW Rev'!I8,""),"") | G417: =IFERROR(IF(AND(ISNUMBER('SW Rev'!K8),ISNUMBER('SW Rev'!J8)),'SW Rev'!K8-'SW Rev'!J8,""),"") | H417: =IFERROR(IF(AND(ISNUMBER('SW Rev'!L8),ISNUMBER('SW Rev'!K8)),'SW Rev'!L8-'SW Rev'!K8,""),"") | I417: =IFERROR(IF(AND(ISNUMBER('SW Rev'!M8),ISNUMBER('SW Rev'!L8)),'SW Rev'!M8-'SW Rev'!L8,""),"") | J417: =IFERROR(IF(AND(ISNUMBER('SW Rev'!N8),ISNUMBER('SW Rev'!M8)),'SW Rev'!N8-'SW Rev'!M8,""),"") | ... N417: =IFERROR(IF(AND(ISNUMBER('SW Rev'!R8),ISNUMBER('SW Rev'!Q8)),'SW Rev'!R8-'SW Rev'!Q8,""),"")
A418: ='SW Rev'!$A9 | B418: ='SW Rev'!$B9 | C418: =IFERROR(IF(AND(ISNUMBER('SW Rev'!G9),ISNUMBER('SW Rev'!F9)),'SW Rev'!G9-'SW Rev'!F9,""),"") | D418: =IFERROR(IF(AND(ISNUMBER('SW Rev'!H9),ISNUMBER('SW Rev'!G9)),'SW Rev'!H9-'SW Rev'!G9,""),"") | E418: =IFERROR(IF(AND(ISNUMBER('SW Rev'!I9),ISNUMBER('SW Rev'!H9)),'SW Rev'!I9-'SW Rev'!H9,""),"") | F418: =IFERROR(IF(AND(ISNUMBER('SW Rev'!J9),ISNUMBER('SW Rev'!I9)),'SW Rev'!J9-'SW Rev'!I9,""),"") | G418: =IFERROR(IF(AND(ISNUMBER('SW Rev'!K9),ISNUMBER('SW Rev'!J9)),'SW Rev'!K9-'SW Rev'!J9,""),"") | H418: =IFERROR(IF(AND(ISNUMBER('SW Rev'!L9),ISNUMBER('SW Rev'!K9)),'SW Rev'!L9-'SW Rev'!K9,""),"") | I418: =IFERROR(IF(AND(ISNUMBER('SW Rev'!M9),ISNUMBER('SW Rev'!L9)),'SW Rev'!M9-'SW Rev'!L9,""),"") | J418: =IFERROR(IF(AND(ISNUMBER('SW Rev'!N9),ISNUMBER('SW Rev'!M9)),'SW Rev'!N9-'SW Rev'!M9,""),"") | ... N418: =IFERROR(IF(AND(ISNUMBER('SW Rev'!R9),ISNUMBER('SW Rev'!Q9)),'SW Rev'!R9-'SW Rev'!Q9,""),"")
A419: ='SW Rev'!$A10 | B419: ='SW Rev'!$B10 | C419: =IFERROR(IF(AND(ISNUMBER('SW Rev'!G10),ISNUMBER('SW Rev'!F10)),'SW Rev'!G10-'SW Rev'!F10,""),"") | D419: =IFERROR(IF(AND(ISNUMBER('SW Rev'!H10),ISNUMBER('SW Rev'!G10)),'SW Rev'!H10-'SW Rev'!G10,""),"") | E419: =IFERROR(IF(AND(ISNUMBER('SW Rev'!I10),ISNUMBER('SW Rev'!H10)),'SW Rev'!I10-'SW Rev'!H10,""),"") | F419: =IFERROR(IF(AND(ISNUMBER('SW Rev'!J10),ISNUMBER('SW Rev'!I10)),'SW Rev'!J10-'SW Rev'!I10,""),"") | G419: =IFERROR(IF(AND(ISNUMBER('SW Rev'!K10),ISNUMBER('SW Rev'!J10)),'SW Rev'!K10-'SW Rev'!J10,""),"") | H419: =IFERROR(IF(AND(ISNUMBER('SW Rev'!L10),ISNUMBER('SW Rev'!K10)),'SW Rev'!L10-'SW Rev'!K10,""),"") | I419: =IFERROR(IF(AND(ISNUMBER('SW Rev'!M10),ISNUMBER('SW Rev'!L10)),'SW Rev'!M10-'SW Rev'!L10,""),"") | J419: =IFERROR(IF(AND(ISNUMBER('SW Rev'!N10),ISNUMBER('SW Rev'!M10)),'SW Rev'!N10-'SW Rev'!M10,""),"") | ... N419: =IFERROR(IF(AND(ISNUMBER('SW Rev'!R10),ISNUMBER('SW Rev'!Q10)),'SW Rev'!R10-'SW Rev'!Q10,""),"")
A420: ='SW Rev'!$A11 | B420: ='SW Rev'!$B11 | C420: =IFERROR(IF(AND(ISNUMBER('SW Rev'!G11),ISNUMBER('SW Rev'!F11)),'SW Rev'!G11-'SW Rev'!F11,""),"") | D420: =IFERROR(IF(AND(ISNUMBER('SW Rev'!H11),ISNUMBER('SW Rev'!G11)),'SW Rev'!H11-'SW Rev'!G11,""),"") | E420: =IFERROR(IF(AND(ISNUMBER('SW Rev'!I11),ISNUMBER('SW Rev'!H11)),'SW Rev'!I11-'SW Rev'!H11,""),"") | F420: =IFERROR(IF(AND(ISNUMBER('SW Rev'!J11),ISNUMBER('SW Rev'!I11)),'SW Rev'!J11-'SW Rev'!I11,""),"") | G420: =IFERROR(IF(AND(ISNUMBER('SW Rev'!K11),ISNUMBER('SW Rev'!J11)),'SW Rev'!K11-'SW Rev'!J11,""),"") | H420: =IFERROR(IF(AND(ISNUMBER('SW Rev'!L11),ISNUMBER('SW Rev'!K11)),'SW Rev'!L11-'SW Rev'!K11,""),"") | I420: =IFERROR(IF(AND(ISNUMBER('SW Rev'!M11),ISNUMBER('SW Rev'!L11)),'SW Rev'!M11-'SW Rev'!L11,""),"") | J420: =IFERROR(IF(AND(ISNUMBER('SW Rev'!N11),ISNUMBER('SW Rev'!M11)),'SW Rev'!N11-'SW Rev'!M11,""),"") | ... N420: =IFERROR(IF(AND(ISNUMBER('SW Rev'!R11),ISNUMBER('SW Rev'!Q11)),'SW Rev'!R11-'SW Rev'!Q11,""),"")
A421: ='SW Rev'!$A12 | B421: ='SW Rev'!$B12 | C421: =IFERROR(IF(AND(ISNUMBER('SW Rev'!G12),ISNUMBER('SW Rev'!F12)),'SW Rev'!G12-'SW Rev'!F12,""),"") | D421: =IFERROR(IF(AND(ISNUMBER('SW Rev'!H12),ISNUMBER('SW Rev'!G12)),'SW Rev'!H12-'SW Rev'!G12,""),"") | E421: =IFERROR(IF(AND(ISNUMBER('SW Rev'!I12),ISNUMBER('SW Rev'!H12)),'SW Rev'!I12-'SW Rev'!H12,""),"") | F421: =IFERROR(IF(AND(ISNUMBER('SW Rev'!J12),ISNUMBER('SW Rev'!I12)),'SW Rev'!J12-'SW Rev'!I12,""),"") | G421: =IFERROR(IF(AND(ISNUMBER('SW Rev'!K12),ISNUMBER('SW Rev'!J12)),'SW Rev'!K12-'SW Rev'!J12,""),"") | H421: =IFERROR(IF(AND(ISNUMBER('SW Rev'!L12),ISNUMBER('SW Rev'!K12)),'SW Rev'!L12-'SW Rev'!K12,""),"") | I421: =IFERROR(IF(AND(ISNUMBER('SW Rev'!M12),ISNUMBER('SW Rev'!L12)),'SW Rev'!M12-'SW Rev'!L12,""),"") | J421: =IFERROR(IF(AND(ISNUMBER('SW Rev'!N12),ISNUMBER('SW Rev'!M12)),'SW Rev'!N12-'SW Rev'!M12,""),"") | ... N421: =IFERROR(IF(AND(ISNUMBER('SW Rev'!R12),ISNUMBER('SW Rev'!Q12)),'SW Rev'!R12-'SW Rev'!Q12,""),"")
A422: ='SW Rev'!$A13 | B422: ='SW Rev'!$B13 | C422: =IFERROR(IF(AND(ISNUMBER('SW Rev'!G13),ISNUMBER('SW Rev'!F13)),'SW Rev'!G13-'SW Rev'!F13,""),"") | D422: =IFERROR(IF(AND(ISNUMBER('SW Rev'!H13),ISNUMBER('SW Rev'!G13)),'SW Rev'!H13-'SW Rev'!G13,""),"") | E422: =IFERROR(IF(AND(ISNUMBER('SW Rev'!I13),ISNUMBER('SW Rev'!H13)),'SW Rev'!I13-'SW Rev'!H13,""),"") | F422: =IFERROR(IF(AND(ISNUMBER('SW Rev'!J13),ISNUMBER('SW Rev'!I13)),'SW Rev'!J13-'SW Rev'!I13,""),"") | G422: =IFERROR(IF(AND(ISNUMBER('SW Rev'!K13),ISNUMBER('SW Rev'!J13)),'SW Rev'!K13-'SW Rev'!J13,""),"") | H422: =IFERROR(IF(AND(ISNUMBER('SW Rev'!L13),ISNUMBER('SW Rev'!K13)),'SW Rev'!L13-'SW Rev'!K13,""),"") | I422: =IFERROR(IF(AND(ISNUMBER('SW Rev'!M13),ISNUMBER('SW Rev'!L13)),'SW Rev'!M13-'SW Rev'!L13,""),"") | J422: =IFERROR(IF(AND(ISNUMBER('SW Rev'!N13),ISNUMBER('SW Rev'!M13)),'SW Rev'!N13-'SW Rev'!M13,""),"") | ... N422: =IFERROR(IF(AND(ISNUMBER('SW Rev'!R13),ISNUMBER('SW Rev'!Q13)),'SW Rev'!R13-'SW Rev'!Q13,""),"")
A423: ='SW Rev'!$A14 | B423: ='SW Rev'!$B14 | C423: =IFERROR(IF(AND(ISNUMBER('SW Rev'!G14),ISNUMBER('SW Rev'!F14)),'SW Rev'!G14-'SW Rev'!F14,""),"") | D423: =IFERROR(IF(AND(ISNUMBER('SW Rev'!H14),ISNUMBER('SW Rev'!G14)),'SW Rev'!H14-'SW Rev'!G14,""),"") | E423: =IFERROR(IF(AND(ISNUMBER('SW Rev'!I14),ISNUMBER('SW Rev'!H14)),'SW Rev'!I14-'SW Rev'!H14,""),"") | F423: =IFERROR(IF(AND(ISNUMBER('SW Rev'!J14),ISNUMBER('SW Rev'!I14)),'SW Rev'!J14-'SW Rev'!I14,""),"") | G423: =IFERROR(IF(AND(ISNUMBER('SW Rev'!K14),ISNUMBER('SW Rev'!J14)),'SW Rev'!K14-'SW Rev'!J14,""),"") | H423: =IFERROR(IF(AND(ISNUMBER('SW Rev'!L14),ISNUMBER('SW Rev'!K14)),'SW Rev'!L14-'SW Rev'!K14,""),"") | I423: =IFERROR(IF(AND(ISNUMBER('SW Rev'!M14),ISNUMBER('SW Rev'!L14)),'SW Rev'!M14-'SW Rev'!L14,""),"") | J423: =IFERROR(IF(AND(ISNUMBER('SW Rev'!N14),ISNUMBER('SW Rev'!M14)),'SW Rev'!N14-'SW Rev'!M14,""),"") | ... N423: =IFERROR(IF(AND(ISNUMBER('SW Rev'!R14),ISNUMBER('SW Rev'!Q14)),'SW Rev'!R14-'SW Rev'!Q14,""),"")
A424: ='SW Rev'!$A15 | B424: ='SW Rev'!$B15 | C424: =IFERROR(IF(AND(ISNUMBER('SW Rev'!G15),ISNUMBER('SW Rev'!F15)),'SW Rev'!G15-'SW Rev'!F15,""),"") | D424: =IFERROR(IF(AND(ISNUMBER('SW Rev'!H15),ISNUMBER('SW Rev'!G15)),'SW Rev'!H15-'SW Rev'!G15,""),"") | E424: =IFERROR(IF(AND(ISNUMBER('SW Rev'!I15),ISNUMBER('SW Rev'!H15)),'SW Rev'!I15-'SW Rev'!H15,""),"") | F424: =IFERROR(IF(AND(ISNUMBER('SW Rev'!J15),ISNUMBER('SW Rev'!I15)),'SW Rev'!J15-'SW Rev'!I15,""),"") | G424: =IFERROR(IF(AND(ISNUMBER('SW Rev'!K15),ISNUMBER('SW Rev'!J15)),'SW Rev'!K15-'SW Rev'!J15,""),"") | H424: =IFERROR(IF(AND(ISNUMBER('SW Rev'!L15),ISNUMBER('SW Rev'!K15)),'SW Rev'!L15-'SW Rev'!K15,""),"") | I424: =IFERROR(IF(AND(ISNUMBER('SW Rev'!M15),ISNUMBER('SW Rev'!L15)),'SW Rev'!M15-'SW Rev'!L15,""),"") | J424: =IFERROR(IF(AND(ISNUMBER('SW Rev'!N15),ISNUMBER('SW Rev'!M15)),'SW Rev'!N15-'SW Rev'!M15,""),"") | ... N424: =IFERROR(IF(AND(ISNUMBER('SW Rev'!R15),ISNUMBER('SW Rev'!Q15)),'SW Rev'!R15-'SW Rev'!Q15,""),"")
A425: ='SW Rev'!$A16 | B425: ='SW Rev'!$B16 | C425: =IFERROR(IF(AND(ISNUMBER('SW Rev'!G16),ISNUMBER('SW Rev'!F16)),'SW Rev'!G16-'SW Rev'!F16,""),"") | D425: =IFERROR(IF(AND(ISNUMBER('SW Rev'!H16),ISNUMBER('SW Rev'!G16)),'SW Rev'!H16-'SW Rev'!G16,""),"") | E425: =IFERROR(IF(AND(ISNUMBER('SW Rev'!I16),ISNUMBER('SW Rev'!H16)),'SW Rev'!I16-'SW Rev'!H16,""),"") | F425: =IFERROR(IF(AND(ISNUMBER('SW Rev'!J16),ISNUMBER('SW Rev'!I16)),'SW Rev'!J16-'SW Rev'!I16,""),"") | G425: =IFERROR(IF(AND(ISNUMBER('SW Rev'!K16),ISNUMBER('SW Rev'!J16)),'SW Rev'!K16-'SW Rev'!J16,""),"") | H425: =IFERROR(IF(AND(ISNUMBER('SW Rev'!L16),ISNUMBER('SW Rev'!K16)),'SW Rev'!L16-'SW Rev'!K16,""),"") | I425: =IFERROR(IF(AND(ISNUMBER('SW Rev'!M16),ISNUMBER('SW Rev'!L16)),'SW Rev'!M16-'SW Rev'!L16,""),"") | J425: =IFERROR(IF(AND(ISNUMBER('SW Rev'!N16),ISNUMBER('SW Rev'!M16)),'SW Rev'!N16-'SW Rev'!M16,""),"") | ... N425: =IFERROR(IF(AND(ISNUMBER('SW Rev'!R16),ISNUMBER('SW Rev'!Q16)),'SW Rev'!R16-'SW Rev'!Q16,""),"")
... A512: ='SW Rev'!$A103 | B512: ='SW Rev'!$B103 | C512: =IFERROR(IF(AND(ISNUMBER('SW Rev'!G103),ISNUMBER('SW Rev'!F103)),'SW Rev'!G103-'SW Rev'!F103,""),"") | D512: =IFERROR(IF(AND(ISNUMBER('SW Rev'!H103),ISNUMBER('SW Rev'!G103)),'SW Rev'!H103-'SW Rev'!G103,""),"") | E512: =IFERROR(IF(AND(ISNUMBER('SW Rev'!I103),ISNUMBER('SW Rev'!H103)),'SW Rev'!I103-'SW Rev'!H103,""),"") | F512: =IFERROR(IF(AND(ISNUMBER('SW Rev'!J103),ISNUMBER('SW Rev'!I103)),'SW Rev'!J103-'SW Rev'!I103,""),"") | G512: =IFERROR(IF(AND(ISNUMBER('SW Rev'!K103),ISNUMBER('SW Rev'!J103)),'SW Rev'!K103-'SW Rev'!J103,""),"") | H512: =IFERROR(IF(AND(ISNUMBER('SW Rev'!L103),ISNUMBER('SW Rev'!K103)),'SW Rev'!L103-'SW Rev'!K103,""),"") | I512: =IFERROR(IF(AND(ISNUMBER('SW Rev'!M103),ISNUMBER('SW Rev'!L103)),'SW Rev'!M103-'SW Rev'!L103,""),"") | J512: =IFERROR(IF(AND(ISNUMBER('SW Rev'!N103),ISNUMBER('SW Rev'!M103)),'SW Rev'!N103-'SW Rev'!M103,""),"") | ... N512: =IFERROR(IF(AND(ISNUMBER('SW Rev'!R103),ISNUMBER('SW Rev'!Q103)),'SW Rev'!R103-'SW Rev'!Q103,""),"")
A514: Adj. operating margin %
A515: Ticker | B515: Latest Rpt Qtr | C515: FPO -9 | D515: FPO -8 | E515: FPO -7 | F515: FPO -6 | G515: FPO -5 | H515: FPO -4 | I515: FPO -3 | J515: FPO -2 | K515: FPO -1 | L515: FPO 0 (latest rpt) | M515: FPO +1E | N515: FPO +2E
A516: ='SW Rev'!$A5 | B516: ='SW Rev'!$B5 | C516: =IFERROR(IF(AND(ISNUMBER('SW OpInc'!G5),ISNUMBER('SW Rev'!G5),'SW Rev'!G5>0),'SW OpInc'!G5/'SW Rev'!G5,""),"") | D516: =IFERROR(IF(AND(ISNUMBER('SW OpInc'!H5),ISNUMBER('SW Rev'!H5),'SW Rev'!H5>0),'SW OpInc'!H5/'SW Rev'!H5,""),"") | E516: =IFERROR(IF(AND(ISNUMBER('SW OpInc'!I5),ISNUMBER('SW Rev'!I5),'SW Rev'!I5>0),'SW OpInc'!I5/'SW Rev'!I5,""),"") | F516: =IFERROR(IF(AND(ISNUMBER('SW OpInc'!J5),ISNUMBER('SW Rev'!J5),'SW Rev'!J5>0),'SW OpInc'!J5/'SW Rev'!J5,""),"") | G516: =IFERROR(IF(AND(ISNUMBER('SW OpInc'!K5),ISNUMBER('SW Rev'!K5),'SW Rev'!K5>0),'SW OpInc'!K5/'SW Rev'!K5,""),"") | H516: =IFERROR(IF(AND(ISNUMBER('SW OpInc'!L5),ISNUMBER('SW Rev'!L5),'SW Rev'!L5>0),'SW OpInc'!L5/'SW Rev'!L5,""),"") | I516: =IFERROR(IF(AND(ISNUMBER('SW OpInc'!M5),ISNUMBER('SW Rev'!M5),'SW Rev'!M5>0),'SW OpInc'!M5/'SW Rev'!M5,""),"") | J516: =IFERROR(IF(AND(ISNUMBER('SW OpInc'!N5),ISNUMBER('SW Rev'!N5),'SW Rev'!N5>0),'SW OpInc'!N5/'SW Rev'!N5,""),"") | ... N516: =IFERROR(IF(AND(ISNUMBER('SW OpInc'!R5),ISNUMBER('SW Rev'!R5),'SW Rev'!R5>0),'SW OpInc'!R5/'SW Rev'!R5,""),"")
A517: ='SW Rev'!$A6 | B517: ='SW Rev'!$B6 | C517: =IFERROR(IF(AND(ISNUMBER('SW OpInc'!G6),ISNUMBER('SW Rev'!G6),'SW Rev'!G6>0),'SW OpInc'!G6/'SW Rev'!G6,""),"") | D517: =IFERROR(IF(AND(ISNUMBER('SW OpInc'!H6),ISNUMBER('SW Rev'!H6),'SW Rev'!H6>0),'SW OpInc'!H6/'SW Rev'!H6,""),"") | E517: =IFERROR(IF(AND(ISNUMBER('SW OpInc'!I6),ISNUMBER('SW Rev'!I6),'SW Rev'!I6>0),'SW OpInc'!I6/'SW Rev'!I6,""),"") | F517: =IFERROR(IF(AND(ISNUMBER('SW OpInc'!J6),ISNUMBER('SW Rev'!J6),'SW Rev'!J6>0),'SW OpInc'!J6/'SW Rev'!J6,""),"") | G517: =IFERROR(IF(AND(ISNUMBER('SW OpInc'!K6),ISNUMBER('SW Rev'!K6),'SW Rev'!K6>0),'SW OpInc'!K6/'SW Rev'!K6,""),"") | H517: =IFERROR(IF(AND(ISNUMBER('SW OpInc'!L6),ISNUMBER('SW Rev'!L6),'SW Rev'!L6>0),'SW OpInc'!L6/'SW Rev'!L6,""),"") | I517: =IFERROR(IF(AND(ISNUMBER('SW OpInc'!M6),ISNUMBER('SW Rev'!M6),'SW Rev'!M6>0),'SW OpInc'!M6/'SW Rev'!M6,""),"") | J517: =IFERROR(IF(AND(ISNUMBER('SW OpInc'!N6),ISNUMBER('SW Rev'!N6),'SW Rev'!N6>0),'SW OpInc'!N6/'SW Rev'!N6,""),"") | ... N517: =IFERROR(IF(AND(ISNUMBER('SW OpInc'!R6),ISNUMBER('SW Rev'!R6),'SW Rev'!R6>0),'SW OpInc'!R6/'SW Rev'!R6,""),"")
A518: ='SW Rev'!$A7 | B518: ='SW Rev'!$B7 | C518: =IFERROR(IF(AND(ISNUMBER('SW OpInc'!G7),ISNUMBER('SW Rev'!G7),'SW Rev'!G7>0),'SW OpInc'!G7/'SW Rev'!G7,""),"") | D518: =IFERROR(IF(AND(ISNUMBER('SW OpInc'!H7),ISNUMBER('SW Rev'!H7),'SW Rev'!H7>0),'SW OpInc'!H7/'SW Rev'!H7,""),"") | E518: =IFERROR(IF(AND(ISNUMBER('SW OpInc'!I7),ISNUMBER('SW Rev'!I7),'SW Rev'!I7>0),'SW OpInc'!I7/'SW Rev'!I7,""),"") | F518: =IFERROR(IF(AND(ISNUMBER('SW OpInc'!J7),ISNUMBER('SW Rev'!J7),'SW Rev'!J7>0),'SW OpInc'!J7/'SW Rev'!J7,""),"") | G518: =IFERROR(IF(AND(ISNUMBER('SW OpInc'!K7),ISNUMBER('SW Rev'!K7),'SW Rev'!K7>0),'SW OpInc'!K7/'SW Rev'!K7,""),"") | H518: =IFERROR(IF(AND(ISNUMBER('SW OpInc'!L7),ISNUMBER('SW Rev'!L7),'SW Rev'!L7>0),'SW OpInc'!L7/'SW Rev'!L7,""),"") | I518: =IFERROR(IF(AND(ISNUMBER('SW OpInc'!M7),ISNUMBER('SW Rev'!M7),'SW Rev'!M7>0),'SW OpInc'!M7/'SW Rev'!M7,""),"") | J518: =IFERROR(IF(AND(ISNUMBER('SW OpInc'!N7),ISNUMBER('SW Rev'!N7),'SW Rev'!N7>0),'SW OpInc'!N7/'SW Rev'!N7,""),"") | ... N518: =IFERROR(IF(AND(ISNUMBER('SW OpInc'!R7),ISNUMBER('SW Rev'!R7),'SW Rev'!R7>0),'SW OpInc'!R7/'SW Rev'!R7,""),"")
A519: ='SW Rev'!$A8 | B519: ='SW Rev'!$B8 | C519: =IFERROR(IF(AND(ISNUMBER('SW OpInc'!G8),ISNUMBER('SW Rev'!G8),'SW Rev'!G8>0),'SW OpInc'!G8/'SW Rev'!G8,""),"") | D519: =IFERROR(IF(AND(ISNUMBER('SW OpInc'!H8),ISNUMBER('SW Rev'!H8),'SW Rev'!H8>0),'SW OpInc'!H8/'SW Rev'!H8,""),"") | E519: =IFERROR(IF(AND(ISNUMBER('SW OpInc'!I8),ISNUMBER('SW Rev'!I8),'SW Rev'!I8>0),'SW OpInc'!I8/'SW Rev'!I8,""),"") | F519: =IFERROR(IF(AND(ISNUMBER('SW OpInc'!J8),ISNUMBER('SW Rev'!J8),'SW Rev'!J8>0),'SW OpInc'!J8/'SW Rev'!J8,""),"") | G519: =IFERROR(IF(AND(ISNUMBER('SW OpInc'!K8),ISNUMBER('SW Rev'!K8),'SW Rev'!K8>0),'SW OpInc'!K8/'SW Rev'!K8,""),"") | H519: =IFERROR(IF(AND(ISNUMBER('SW OpInc'!L8),ISNUMBER('SW Rev'!L8),'SW Rev'!L8>0),'SW OpInc'!L8/'SW Rev'!L8,""),"") | I519: =IFERROR(IF(AND(ISNUMBER('SW OpInc'!M8),ISNUMBER('SW Rev'!M8),'SW Rev'!M8>0),'SW OpInc'!M8/'SW Rev'!M8,""),"") | J519: =IFERROR(IF(AND(ISNUMBER('SW OpInc'!N8),ISNUMBER('SW Rev'!N8),'SW Rev'!N8>0),'SW OpInc'!N8/'SW Rev'!N8,""),"") | ... N519: =IFERROR(IF(AND(ISNUMBER('SW OpInc'!R8),ISNUMBER('SW Rev'!R8),'SW Rev'!R8>0),'SW OpInc'!R8/'SW Rev'!R8,""),"")
A520: ='SW Rev'!$A9 | B520: ='SW Rev'!$B9 | C520: =IFERROR(IF(AND(ISNUMBER('SW OpInc'!G9),ISNUMBER('SW Rev'!G9),'SW Rev'!G9>0),'SW OpInc'!G9/'SW Rev'!G9,""),"") | D520: =IFERROR(IF(AND(ISNUMBER('SW OpInc'!H9),ISNUMBER('SW Rev'!H9),'SW Rev'!H9>0),'SW OpInc'!H9/'SW Rev'!H9,""),"") | E520: =IFERROR(IF(AND(ISNUMBER('SW OpInc'!I9),ISNUMBER('SW Rev'!I9),'SW Rev'!I9>0),'SW OpInc'!I9/'SW Rev'!I9,""),"") | F520: =IFERROR(IF(AND(ISNUMBER('SW OpInc'!J9),ISNUMBER('SW Rev'!J9),'SW Rev'!J9>0),'SW OpInc'!J9/'SW Rev'!J9,""),"") | G520: =IFERROR(IF(AND(ISNUMBER('SW OpInc'!K9),ISNUMBER('SW Rev'!K9),'SW Rev'!K9>0),'SW OpInc'!K9/'SW Rev'!K9,""),"") | H520: =IFERROR(IF(AND(ISNUMBER('SW OpInc'!L9),ISNUMBER('SW Rev'!L9),'SW Rev'!L9>0),'SW OpInc'!L9/'SW Rev'!L9,""),"") | I520: =IFERROR(IF(AND(ISNUMBER('SW OpInc'!M9),ISNUMBER('SW Rev'!M9),'SW Rev'!M9>0),'SW OpInc'!M9/'SW Rev'!M9,""),"") | J520: =IFERROR(IF(AND(ISNUMBER('SW OpInc'!N9),ISNUMBER('SW Rev'!N9),'SW Rev'!N9>0),'SW OpInc'!N9/'SW Rev'!N9,""),"") | ... N520: =IFERROR(IF(AND(ISNUMBER('SW OpInc'!R9),ISNUMBER('SW Rev'!R9),'SW Rev'!R9>0),'SW OpInc'!R9/'SW Rev'!R9,""),"")
A521: ='SW Rev'!$A10 | B521: ='SW Rev'!$B10 | C521: =IFERROR(IF(AND(ISNUMBER('SW OpInc'!G10),ISNUMBER('SW Rev'!G10),'SW Rev'!G10>0),'SW OpInc'!G10/'SW Rev'!G10,""),"") | D521: =IFERROR(IF(AND(ISNUMBER('SW OpInc'!H10),ISNUMBER('SW Rev'!H10),'SW Rev'!H10>0),'SW OpInc'!H10/'SW Rev'!H10,""),"") | E521: =IFERROR(IF(AND(ISNUMBER('SW OpInc'!I10),ISNUMBER('SW Rev'!I10),'SW Rev'!I10>0),'SW OpInc'!I10/'SW Rev'!I10,""),"") | F521: =IFERROR(IF(AND(ISNUMBER('SW OpInc'!J10),ISNUMBER('SW Rev'!J10),'SW Rev'!J10>0),'SW OpInc'!J10/'SW Rev'!J10,""),"") | G521: =IFERROR(IF(AND(ISNUMBER('SW OpInc'!K10),ISNUMBER('SW Rev'!K10),'SW Rev'!K10>0),'SW OpInc'!K10/'SW Rev'!K10,""),"") | H521: =IFERROR(IF(AND(ISNUMBER('SW OpInc'!L10),ISNUMBER('SW Rev'!L10),'SW Rev'!L10>0),'SW OpInc'!L10/'SW Rev'!L10,""),"") | I521: =IFERROR(IF(AND(ISNUMBER('SW OpInc'!M10),ISNUMBER('SW Rev'!M10),'SW Rev'!M10>0),'SW OpInc'!M10/'SW Rev'!M10,""),"") | J521: =IFERROR(IF(AND(ISNUMBER('SW OpInc'!N10),ISNUMBER('SW Rev'!N10),'SW Rev'!N10>0),'SW OpInc'!N10/'SW Rev'!N10,""),"") | ... N521: =IFERROR(IF(AND(ISNUMBER('SW OpInc'!R10),ISNUMBER('SW Rev'!R10),'SW Rev'!R10>0),'SW OpInc'!R10/'SW Rev'!R10,""),"")
A522: ='SW Rev'!$A11 | B522: ='SW Rev'!$B11 | C522: =IFERROR(IF(AND(ISNUMBER('SW OpInc'!G11),ISNUMBER('SW Rev'!G11),'SW Rev'!G11>0),'SW OpInc'!G11/'SW Rev'!G11,""),"") | D522: =IFERROR(IF(AND(ISNUMBER('SW OpInc'!H11),ISNUMBER('SW Rev'!H11),'SW Rev'!H11>0),'SW OpInc'!H11/'SW Rev'!H11,""),"") | E522: =IFERROR(IF(AND(ISNUMBER('SW OpInc'!I11),ISNUMBER('SW Rev'!I11),'SW Rev'!I11>0),'SW OpInc'!I11/'SW Rev'!I11,""),"") | F522: =IFERROR(IF(AND(ISNUMBER('SW OpInc'!J11),ISNUMBER('SW Rev'!J11),'SW Rev'!J11>0),'SW OpInc'!J11/'SW Rev'!J11,""),"") | G522: =IFERROR(IF(AND(ISNUMBER('SW OpInc'!K11),ISNUMBER('SW Rev'!K11),'SW Rev'!K11>0),'SW OpInc'!K11/'SW Rev'!K11,""),"") | H522: =IFERROR(IF(AND(ISNUMBER('SW OpInc'!L11),ISNUMBER('SW Rev'!L11),'SW Rev'!L11>0),'SW OpInc'!L11/'SW Rev'!L11,""),"") | I522: =IFERROR(IF(AND(ISNUMBER('SW OpInc'!M11),ISNUMBER('SW Rev'!M11),'SW Rev'!M11>0),'SW OpInc'!M11/'SW Rev'!M11,""),"") | J522: =IFERROR(IF(AND(ISNUMBER('SW OpInc'!N11),ISNUMBER('SW Rev'!N11),'SW Rev'!N11>0),'SW OpInc'!N11/'SW Rev'!N11,""),"") | ... N522: =IFERROR(IF(AND(ISNUMBER('SW OpInc'!R11),ISNUMBER('SW Rev'!R11),'SW Rev'!R11>0),'SW OpInc'!R11/'SW Rev'!R11,""),"")
A523: ='SW Rev'!$A12 | B523: ='SW Rev'!$B12 | C523: =IFERROR(IF(AND(ISNUMBER('SW OpInc'!G12),ISNUMBER('SW Rev'!G12),'SW Rev'!G12>0),'SW OpInc'!G12/'SW Rev'!G12,""),"") | D523: =IFERROR(IF(AND(ISNUMBER('SW OpInc'!H12),ISNUMBER('SW Rev'!H12),'SW Rev'!H12>0),'SW OpInc'!H12/'SW Rev'!H12,""),"") | E523: =IFERROR(IF(AND(ISNUMBER('SW OpInc'!I12),ISNUMBER('SW Rev'!I12),'SW Rev'!I12>0),'SW OpInc'!I12/'SW Rev'!I12,""),"") | F523: =IFERROR(IF(AND(ISNUMBER('SW OpInc'!J12),ISNUMBER('SW Rev'!J12),'SW Rev'!J12>0),'SW OpInc'!J12/'SW Rev'!J12,""),"") | G523: =IFERROR(IF(AND(ISNUMBER('SW OpInc'!K12),ISNUMBER('SW Rev'!K12),'SW Rev'!K12>0),'SW OpInc'!K12/'SW Rev'!K12,""),"") | H523: =IFERROR(IF(AND(ISNUMBER('SW OpInc'!L12),ISNUMBER('SW Rev'!L12),'SW Rev'!L12>0),'SW OpInc'!L12/'SW Rev'!L12,""),"") | I523: =IFERROR(IF(AND(ISNUMBER('SW OpInc'!M12),ISNUMBER('SW Rev'!M12),'SW Rev'!M12>0),'SW OpInc'!M12/'SW Rev'!M12,""),"") | J523: =IFERROR(IF(AND(ISNUMBER('SW OpInc'!N12),ISNUMBER('SW Rev'!N12),'SW Rev'!N12>0),'SW OpInc'!N12/'SW Rev'!N12,""),"") | ... N523: =IFERROR(IF(AND(ISNUMBER('SW OpInc'!R12),ISNUMBER('SW Rev'!R12),'SW Rev'!R12>0),'SW OpInc'!R12/'SW Rev'!R12,""),"")
A524: ='SW Rev'!$A13 | B524: ='SW Rev'!$B13 | C524: =IFERROR(IF(AND(ISNUMBER('SW OpInc'!G13),ISNUMBER('SW Rev'!G13),'SW Rev'!G13>0),'SW OpInc'!G13/'SW Rev'!G13,""),"") | D524: =IFERROR(IF(AND(ISNUMBER('SW OpInc'!H13),ISNUMBER('SW Rev'!H13),'SW Rev'!H13>0),'SW OpInc'!H13/'SW Rev'!H13,""),"") | E524: =IFERROR(IF(AND(ISNUMBER('SW OpInc'!I13),ISNUMBER('SW Rev'!I13),'SW Rev'!I13>0),'SW OpInc'!I13/'SW Rev'!I13,""),"") | F524: =IFERROR(IF(AND(ISNUMBER('SW OpInc'!J13),ISNUMBER('SW Rev'!J13),'SW Rev'!J13>0),'SW OpInc'!J13/'SW Rev'!J13,""),"") | G524: =IFERROR(IF(AND(ISNUMBER('SW OpInc'!K13),ISNUMBER('SW Rev'!K13),'SW Rev'!K13>0),'SW OpInc'!K13/'SW Rev'!K13,""),"") | H524: =IFERROR(IF(AND(ISNUMBER('SW OpInc'!L13),ISNUMBER('SW Rev'!L13),'SW Rev'!L13>0),'SW OpInc'!L13/'SW Rev'!L13,""),"") | I524: =IFERROR(IF(AND(ISNUMBER('SW OpInc'!M13),ISNUMBER('SW Rev'!M13),'SW Rev'!M13>0),'SW OpInc'!M13/'SW Rev'!M13,""),"") | J524: =IFERROR(IF(AND(ISNUMBER('SW OpInc'!N13),ISNUMBER('SW Rev'!N13),'SW Rev'!N13>0),'SW OpInc'!N13/'SW Rev'!N13,""),"") | ... N524: =IFERROR(IF(AND(ISNUMBER('SW OpInc'!R13),ISNUMBER('SW Rev'!R13),'SW Rev'!R13>0),'SW OpInc'!R13/'SW Rev'!R13,""),"")
A525: ='SW Rev'!$A14 | B525: ='SW Rev'!$B14 | C525: =IFERROR(IF(AND(ISNUMBER('SW OpInc'!G14),ISNUMBER('SW Rev'!G14),'SW Rev'!G14>0),'SW OpInc'!G14/'SW Rev'!G14,""),"") | D525: =IFERROR(IF(AND(ISNUMBER('SW OpInc'!H14),ISNUMBER('SW Rev'!H14),'SW Rev'!H14>0),'SW OpInc'!H14/'SW Rev'!H14,""),"") | E525: =IFERROR(IF(AND(ISNUMBER('SW OpInc'!I14),ISNUMBER('SW Rev'!I14),'SW Rev'!I14>0),'SW OpInc'!I14/'SW Rev'!I14,""),"") | F525: =IFERROR(IF(AND(ISNUMBER('SW OpInc'!J14),ISNUMBER('SW Rev'!J14),'SW Rev'!J14>0),'SW OpInc'!J14/'SW Rev'!J14,""),"") | G525: =IFERROR(IF(AND(ISNUMBER('SW OpInc'!K14),ISNUMBER('SW Rev'!K14),'SW Rev'!K14>0),'SW OpInc'!K14/'SW Rev'!K14,""),"") | H525: =IFERROR(IF(AND(ISNUMBER('SW OpInc'!L14),ISNUMBER('SW Rev'!L14),'SW Rev'!L14>0),'SW OpInc'!L14/'SW Rev'!L14,""),"") | I525: =IFERROR(IF(AND(ISNUMBER('SW OpInc'!M14),ISNUMBER('SW Rev'!M14),'SW Rev'!M14>0),'SW OpInc'!M14/'SW Rev'!M14,""),"") | J525: =IFERROR(IF(AND(ISNUMBER('SW OpInc'!N14),ISNUMBER('SW Rev'!N14),'SW Rev'!N14>0),'SW OpInc'!N14/'SW Rev'!N14,""),"") | ... N525: =IFERROR(IF(AND(ISNUMBER('SW OpInc'!R14),ISNUMBER('SW Rev'!R14),'SW Rev'!R14>0),'SW OpInc'!R14/'SW Rev'!R14,""),"")
A526: ='SW Rev'!$A15 | B526: ='SW Rev'!$B15 | C526: =IFERROR(IF(AND(ISNUMBER('SW OpInc'!G15),ISNUMBER('SW Rev'!G15),'SW Rev'!G15>0),'SW OpInc'!G15/'SW Rev'!G15,""),"") | D526: =IFERROR(IF(AND(ISNUMBER('SW OpInc'!H15),ISNUMBER('SW Rev'!H15),'SW Rev'!H15>0),'SW OpInc'!H15/'SW Rev'!H15,""),"") | E526: =IFERROR(IF(AND(ISNUMBER('SW OpInc'!I15),ISNUMBER('SW Rev'!I15),'SW Rev'!I15>0),'SW OpInc'!I15/'SW Rev'!I15,""),"") | F526: =IFERROR(IF(AND(ISNUMBER('SW OpInc'!J15),ISNUMBER('SW Rev'!J15),'SW Rev'!J15>0),'SW OpInc'!J15/'SW Rev'!J15,""),"") | G526: =IFERROR(IF(AND(ISNUMBER('SW OpInc'!K15),ISNUMBER('SW Rev'!K15),'SW Rev'!K15>0),'SW OpInc'!K15/'SW Rev'!K15,""),"") | H526: =IFERROR(IF(AND(ISNUMBER('SW OpInc'!L15),ISNUMBER('SW Rev'!L15),'SW Rev'!L15>0),'SW OpInc'!L15/'SW Rev'!L15,""),"") | I526: =IFERROR(IF(AND(ISNUMBER('SW OpInc'!M15),ISNUMBER('SW Rev'!M15),'SW Rev'!M15>0),'SW OpInc'!M15/'SW Rev'!M15,""),"") | J526: =IFERROR(IF(AND(ISNUMBER('SW OpInc'!N15),ISNUMBER('SW Rev'!N15),'SW Rev'!N15>0),'SW OpInc'!N15/'SW Rev'!N15,""),"") | ... N526: =IFERROR(IF(AND(ISNUMBER('SW OpInc'!R15),ISNUMBER('SW Rev'!R15),'SW Rev'!R15>0),'SW OpInc'!R15/'SW Rev'!R15,""),"")
A527: ='SW Rev'!$A16 | B527: ='SW Rev'!$B16 | C527: =IFERROR(IF(AND(ISNUMBER('SW OpInc'!G16),ISNUMBER('SW Rev'!G16),'SW Rev'!G16>0),'SW OpInc'!G16/'SW Rev'!G16,""),"") | D527: =IFERROR(IF(AND(ISNUMBER('SW OpInc'!H16),ISNUMBER('SW Rev'!H16),'SW Rev'!H16>0),'SW OpInc'!H16/'SW Rev'!H16,""),"") | E527: =IFERROR(IF(AND(ISNUMBER('SW OpInc'!I16),ISNUMBER('SW Rev'!I16),'SW Rev'!I16>0),'SW OpInc'!I16/'SW Rev'!I16,""),"") | F527: =IFERROR(IF(AND(ISNUMBER('SW OpInc'!J16),ISNUMBER('SW Rev'!J16),'SW Rev'!J16>0),'SW OpInc'!J16/'SW Rev'!J16,""),"") | G527: =IFERROR(IF(AND(ISNUMBER('SW OpInc'!K16),ISNUMBER('SW Rev'!K16),'SW Rev'!K16>0),'SW OpInc'!K16/'SW Rev'!K16,""),"") | H527: =IFERROR(IF(AND(ISNUMBER('SW OpInc'!L16),ISNUMBER('SW Rev'!L16),'SW Rev'!L16>0),'SW OpInc'!L16/'SW Rev'!L16,""),"") | I527: =IFERROR(IF(AND(ISNUMBER('SW OpInc'!M16),ISNUMBER('SW Rev'!M16),'SW Rev'!M16>0),'SW OpInc'!M16/'SW Rev'!M16,""),"") | J527: =IFERROR(IF(AND(ISNUMBER('SW OpInc'!N16),ISNUMBER('SW Rev'!N16),'SW Rev'!N16>0),'SW OpInc'!N16/'SW Rev'!N16,""),"") | ... N527: =IFERROR(IF(AND(ISNUMBER('SW OpInc'!R16),ISNUMBER('SW Rev'!R16),'SW Rev'!R16>0),'SW OpInc'!R16/'SW Rev'!R16,""),"")
... A614: ='SW Rev'!$A103 | B614: ='SW Rev'!$B103 | C614: =IFERROR(IF(AND(ISNUMBER('SW OpInc'!G103),ISNUMBER('SW Rev'!G103),'SW Rev'!G103>0),'SW OpInc'!G103/'SW Rev'!G103,""),"") | D614: =IFERROR(IF(AND(ISNUMBER('SW OpInc'!H103),ISNUMBER('SW Rev'!H103),'SW Rev'!H103>0),'SW OpInc'!H103/'SW Rev'!H103,""),"") | E614: =IFERROR(IF(AND(ISNUMBER('SW OpInc'!I103),ISNUMBER('SW Rev'!I103),'SW Rev'!I103>0),'SW OpInc'!I103/'SW Rev'!I103,""),"") | F614: =IFERROR(IF(AND(ISNUMBER('SW OpInc'!J103),ISNUMBER('SW Rev'!J103),'SW Rev'!J103>0),'SW OpInc'!J103/'SW Rev'!J103,""),"") | G614: =IFERROR(IF(AND(ISNUMBER('SW OpInc'!K103),ISNUMBER('SW Rev'!K103),'SW Rev'!K103>0),'SW OpInc'!K103/'SW Rev'!K103,""),"") | H614: =IFERROR(IF(AND(ISNUMBER('SW OpInc'!L103),ISNUMBER('SW Rev'!L103),'SW Rev'!L103>0),'SW OpInc'!L103/'SW Rev'!L103,""),"") | I614: =IFERROR(IF(AND(ISNUMBER('SW OpInc'!M103),ISNUMBER('SW Rev'!M103),'SW Rev'!M103>0),'SW OpInc'!M103/'SW Rev'!M103,""),"") | J614: =IFERROR(IF(AND(ISNUMBER('SW OpInc'!N103),ISNUMBER('SW Rev'!N103),'SW Rev'!N103>0),'SW OpInc'!N103/'SW Rev'!N103,""),"") | ... N614: =IFERROR(IF(AND(ISNUMBER('SW OpInc'!R103),ISNUMBER('SW Rev'!R103),'SW Rev'!R103>0),'SW OpInc'!R103/'SW Rev'!R103,""),"")
A616: Op margin expansion YoY (bps)
A617: Ticker | B617: Latest Rpt Qtr | C617: FPO -9 | D617: FPO -8 | E617: FPO -7 | F617: FPO -6 | G617: FPO -5 | H617: FPO -4 | I617: FPO -3 | J617: FPO -2 | K617: FPO -1 | L617: FPO 0 (latest rpt) | M617: FPO +1E | N617: FPO +2E
A618: ='SW Rev'!$A5 | B618: ='SW Rev'!$B5 | C618: =IFERROR(IF(AND(ISNUMBER('SW OpInc'!G5),ISNUMBER('SW Rev'!G5),ISNUMBER('SW OpInc'!C5),ISNUMBER('SW Rev'!C5),'SW Rev'!G5>0,'SW Rev'!C5>0),('SW OpInc'!G5/'SW Rev'!G5-'SW OpInc'!C5/'SW Rev'!C5)*10000,""),"") | D618: =IFERROR(IF(AND(ISNUMBER('SW OpInc'!H5),ISNUMBER('SW Rev'!H5),ISNUMBER('SW OpInc'!D5),ISNUMBER('SW Rev'!D5),'SW Rev'!H5>0,'SW Rev'!D5>0),('SW OpInc'!H5/'SW Rev'!H5-'SW OpInc'!D5/'SW Rev'!D5)*10000,""),"") | E618: =IFERROR(IF(AND(ISNUMBER('SW OpInc'!I5),ISNUMBER('SW Rev'!I5),ISNUMBER('SW OpInc'!E5),ISNUMBER('SW Rev'!E5),'SW Rev'!I5>0,'SW Rev'!E5>0),('SW OpInc'!I5/'SW Rev'!I5-'SW OpInc'!E5/'SW Rev'!E5)*10000,""),"") | F618: =IFERROR(IF(AND(ISNUMBER('SW OpInc'!J5),ISNUMBER('SW Rev'!J5),ISNUMBER('SW OpInc'!F5),ISNUMBER('SW Rev'!F5),'SW Rev'!J5>0,'SW Rev'!F5>0),('SW OpInc'!J5/'SW Rev'!J5-'SW OpInc'!F5/'SW Rev'!F5)*10000,""),"") | G618: =IFERROR(IF(AND(ISNUMBER('SW OpInc'!K5),ISNUMBER('SW Rev'!K5),ISNUMBER('SW OpInc'!G5),ISNUMBER('SW Rev'!G5),'SW Rev'!K5>0,'SW Rev'!G5>0),('SW OpInc'!K5/'SW Rev'!K5-'SW OpInc'!G5/'SW Rev'!G5)*10000,""),"") | H618: =IFERROR(IF(AND(ISNUMBER('SW OpInc'!L5),ISNUMBER('SW Rev'!L5),ISNUMBER('SW OpInc'!H5),ISNUMBER('SW Rev'!H5),'SW Rev'!L5>0,'SW Rev'!H5>0),('SW OpInc'!L5/'SW Rev'!L5-'SW OpInc'!H5/'SW Rev'!H5)*10000,""),"") | I618: =IFERROR(IF(AND(ISNUMBER('SW OpInc'!M5),ISNUMBER('SW Rev'!M5),ISNUMBER('SW OpInc'!I5),ISNUMBER('SW Rev'!I5),'SW Rev'!M5>0,'SW Rev'!I5>0),('SW OpInc'!M5/'SW Rev'!M5-'SW OpInc'!I5/'SW Rev'!I5)*10000,""),"") | J618: =IFERROR(IF(AND(ISNUMBER('SW OpInc'!N5),ISNUMBER('SW Rev'!N5),ISNUMBER('SW OpInc'!J5),ISNUMBER('SW Rev'!J5),'SW Rev'!N5>0,'SW Rev'!J5>0),('SW OpInc'!N5/'SW Rev'!N5-'SW OpInc'!J5/'SW Rev'!J5)*10000,""),"") | ... N618: =IFERROR(IF(AND(ISNUMBER('SW OpInc'!R5),ISNUMBER('SW Rev'!R5),ISNUMBER('SW OpInc'!N5),ISNUMBER('SW Rev'!N5),'SW Rev'!R5>0,'SW Rev'!N5>0),('SW OpInc'!R5/'SW Rev'!R5-'SW OpInc'!N5/'SW Rev'!N5)*10000,""),"")
A619: ='SW Rev'!$A6 | B619: ='SW Rev'!$B6 | C619: =IFERROR(IF(AND(ISNUMBER('SW OpInc'!G6),ISNUMBER('SW Rev'!G6),ISNUMBER('SW OpInc'!C6),ISNUMBER('SW Rev'!C6),'SW Rev'!G6>0,'SW Rev'!C6>0),('SW OpInc'!G6/'SW Rev'!G6-'SW OpInc'!C6/'SW Rev'!C6)*10000,""),"") | D619: =IFERROR(IF(AND(ISNUMBER('SW OpInc'!H6),ISNUMBER('SW Rev'!H6),ISNUMBER('SW OpInc'!D6),ISNUMBER('SW Rev'!D6),'SW Rev'!H6>0,'SW Rev'!D6>0),('SW OpInc'!H6/'SW Rev'!H6-'SW OpInc'!D6/'SW Rev'!D6)*10000,""),"") | E619: =IFERROR(IF(AND(ISNUMBER('SW OpInc'!I6),ISNUMBER('SW Rev'!I6),ISNUMBER('SW OpInc'!E6),ISNUMBER('SW Rev'!E6),'SW Rev'!I6>0,'SW Rev'!E6>0),('SW OpInc'!I6/'SW Rev'!I6-'SW OpInc'!E6/'SW Rev'!E6)*10000,""),"") | F619: =IFERROR(IF(AND(ISNUMBER('SW OpInc'!J6),ISNUMBER('SW Rev'!J6),ISNUMBER('SW OpInc'!F6),ISNUMBER('SW Rev'!F6),'SW Rev'!J6>0,'SW Rev'!F6>0),('SW OpInc'!J6/'SW Rev'!J6-'SW OpInc'!F6/'SW Rev'!F6)*10000,""),"") | G619: =IFERROR(IF(AND(ISNUMBER('SW OpInc'!K6),ISNUMBER('SW Rev'!K6),ISNUMBER('SW OpInc'!G6),ISNUMBER('SW Rev'!G6),'SW Rev'!K6>0,'SW Rev'!G6>0),('SW OpInc'!K6/'SW Rev'!K6-'SW OpInc'!G6/'SW Rev'!G6)*10000,""),"") | H619: =IFERROR(IF(AND(ISNUMBER('SW OpInc'!L6),ISNUMBER('SW Rev'!L6),ISNUMBER('SW OpInc'!H6),ISNUMBER('SW Rev'!H6),'SW Rev'!L6>0,'SW Rev'!H6>0),('SW OpInc'!L6/'SW Rev'!L6-'SW OpInc'!H6/'SW Rev'!H6)*10000,""),"") | I619: =IFERROR(IF(AND(ISNUMBER('SW OpInc'!M6),ISNUMBER('SW Rev'!M6),ISNUMBER('SW OpInc'!I6),ISNUMBER('SW Rev'!I6),'SW Rev'!M6>0,'SW Rev'!I6>0),('SW OpInc'!M6/'SW Rev'!M6-'SW OpInc'!I6/'SW Rev'!I6)*10000,""),"") | J619: =IFERROR(IF(AND(ISNUMBER('SW OpInc'!N6),ISNUMBER('SW Rev'!N6),ISNUMBER('SW OpInc'!J6),ISNUMBER('SW Rev'!J6),'SW Rev'!N6>0,'SW Rev'!J6>0),('SW OpInc'!N6/'SW Rev'!N6-'SW OpInc'!J6/'SW Rev'!J6)*10000,""),"") | ... N619: =IFERROR(IF(AND(ISNUMBER('SW OpInc'!R6),ISNUMBER('SW Rev'!R6),ISNUMBER('SW OpInc'!N6),ISNUMBER('SW Rev'!N6),'SW Rev'!R6>0,'SW Rev'!N6>0),('SW OpInc'!R6/'SW Rev'!R6-'SW OpInc'!N6/'SW Rev'!N6)*10000,""),"")
A620: ='SW Rev'!$A7 | B620: ='SW Rev'!$B7 | C620: =IFERROR(IF(AND(ISNUMBER('SW OpInc'!G7),ISNUMBER('SW Rev'!G7),ISNUMBER('SW OpInc'!C7),ISNUMBER('SW Rev'!C7),'SW Rev'!G7>0,'SW Rev'!C7>0),('SW OpInc'!G7/'SW Rev'!G7-'SW OpInc'!C7/'SW Rev'!C7)*10000,""),"") | D620: =IFERROR(IF(AND(ISNUMBER('SW OpInc'!H7),ISNUMBER('SW Rev'!H7),ISNUMBER('SW OpInc'!D7),ISNUMBER('SW Rev'!D7),'SW Rev'!H7>0,'SW Rev'!D7>0),('SW OpInc'!H7/'SW Rev'!H7-'SW OpInc'!D7/'SW Rev'!D7)*10000,""),"") | E620: =IFERROR(IF(AND(ISNUMBER('SW OpInc'!I7),ISNUMBER('SW Rev'!I7),ISNUMBER('SW OpInc'!E7),ISNUMBER('SW Rev'!E7),'SW Rev'!I7>0,'SW Rev'!E7>0),('SW OpInc'!I7/'SW Rev'!I7-'SW OpInc'!E7/'SW Rev'!E7)*10000,""),"") | F620: =IFERROR(IF(AND(ISNUMBER('SW OpInc'!J7),ISNUMBER('SW Rev'!J7),ISNUMBER('SW OpInc'!F7),ISNUMBER('SW Rev'!F7),'SW Rev'!J7>0,'SW Rev'!F7>0),('SW OpInc'!J7/'SW Rev'!J7-'SW OpInc'!F7/'SW Rev'!F7)*10000,""),"") | G620: =IFERROR(IF(AND(ISNUMBER('SW OpInc'!K7),ISNUMBER('SW Rev'!K7),ISNUMBER('SW OpInc'!G7),ISNUMBER('SW Rev'!G7),'SW Rev'!K7>0,'SW Rev'!G7>0),('SW OpInc'!K7/'SW Rev'!K7-'SW OpInc'!G7/'SW Rev'!G7)*10000,""),"") | H620: =IFERROR(IF(AND(ISNUMBER('SW OpInc'!L7),ISNUMBER('SW Rev'!L7),ISNUMBER('SW OpInc'!H7),ISNUMBER('SW Rev'!H7),'SW Rev'!L7>0,'SW Rev'!H7>0),('SW OpInc'!L7/'SW Rev'!L7-'SW OpInc'!H7/'SW Rev'!H7)*10000,""),"") | I620: =IFERROR(IF(AND(ISNUMBER('SW OpInc'!M7),ISNUMBER('SW Rev'!M7),ISNUMBER('SW OpInc'!I7),ISNUMBER('SW Rev'!I7),'SW Rev'!M7>0,'SW Rev'!I7>0),('SW OpInc'!M7/'SW Rev'!M7-'SW OpInc'!I7/'SW Rev'!I7)*10000,""),"") | J620: =IFERROR(IF(AND(ISNUMBER('SW OpInc'!N7),ISNUMBER('SW Rev'!N7),ISNUMBER('SW OpInc'!J7),ISNUMBER('SW Rev'!J7),'SW Rev'!N7>0,'SW Rev'!J7>0),('SW OpInc'!N7/'SW Rev'!N7-'SW OpInc'!J7/'SW Rev'!J7)*10000,""),"") | ... N620: =IFERROR(IF(AND(ISNUMBER('SW OpInc'!R7),ISNUMBER('SW Rev'!R7),ISNUMBER('SW OpInc'!N7),ISNUMBER('SW Rev'!N7),'SW Rev'!R7>0,'SW Rev'!N7>0),('SW OpInc'!R7/'SW Rev'!R7-'SW OpInc'!N7/'SW Rev'!N7)*10000,""),"")
A621: ='SW Rev'!$A8 | B621: ='SW Rev'!$B8 | C621: =IFERROR(IF(AND(ISNUMBER('SW OpInc'!G8),ISNUMBER('SW Rev'!G8),ISNUMBER('SW OpInc'!C8),ISNUMBER('SW Rev'!C8),'SW Rev'!G8>0,'SW Rev'!C8>0),('SW OpInc'!G8/'SW Rev'!G8-'SW OpInc'!C8/'SW Rev'!C8)*10000,""),"") | D621: =IFERROR(IF(AND(ISNUMBER('SW OpInc'!H8),ISNUMBER('SW Rev'!H8),ISNUMBER('SW OpInc'!D8),ISNUMBER('SW Rev'!D8),'SW Rev'!H8>0,'SW Rev'!D8>0),('SW OpInc'!H8/'SW Rev'!H8-'SW OpInc'!D8/'SW Rev'!D8)*10000,""),"") | E621: =IFERROR(IF(AND(ISNUMBER('SW OpInc'!I8),ISNUMBER('SW Rev'!I8),ISNUMBER('SW OpInc'!E8),ISNUMBER('SW Rev'!E8),'SW Rev'!I8>0,'SW Rev'!E8>0),('SW OpInc'!I8/'SW Rev'!I8-'SW OpInc'!E8/'SW Rev'!E8)*10000,""),"") | F621: =IFERROR(IF(AND(ISNUMBER('SW OpInc'!J8),ISNUMBER('SW Rev'!J8),ISNUMBER('SW OpInc'!F8),ISNUMBER('SW Rev'!F8),'SW Rev'!J8>0,'SW Rev'!F8>0),('SW OpInc'!J8/'SW Rev'!J8-'SW OpInc'!F8/'SW Rev'!F8)*10000,""),"") | G621: =IFERROR(IF(AND(ISNUMBER('SW OpInc'!K8),ISNUMBER('SW Rev'!K8),ISNUMBER('SW OpInc'!G8),ISNUMBER('SW Rev'!G8),'SW Rev'!K8>0,'SW Rev'!G8>0),('SW OpInc'!K8/'SW Rev'!K8-'SW OpInc'!G8/'SW Rev'!G8)*10000,""),"") | H621: =IFERROR(IF(AND(ISNUMBER('SW OpInc'!L8),ISNUMBER('SW Rev'!L8),ISNUMBER('SW OpInc'!H8),ISNUMBER('SW Rev'!H8),'SW Rev'!L8>0,'SW Rev'!H8>0),('SW OpInc'!L8/'SW Rev'!L8-'SW OpInc'!H8/'SW Rev'!H8)*10000,""),"") | I621: =IFERROR(IF(AND(ISNUMBER('SW OpInc'!M8),ISNUMBER('SW Rev'!M8),ISNUMBER('SW OpInc'!I8),ISNUMBER('SW Rev'!I8),'SW Rev'!M8>0,'SW Rev'!I8>0),('SW OpInc'!M8/'SW Rev'!M8-'SW OpInc'!I8/'SW Rev'!I8)*10000,""),"") | J621: =IFERROR(IF(AND(ISNUMBER('SW OpInc'!N8),ISNUMBER('SW Rev'!N8),ISNUMBER('SW OpInc'!J8),ISNUMBER('SW Rev'!J8),'SW Rev'!N8>0,'SW Rev'!J8>0),('SW OpInc'!N8/'SW Rev'!N8-'SW OpInc'!J8/'SW Rev'!J8)*10000,""),"") | ... N621: =IFERROR(IF(AND(ISNUMBER('SW OpInc'!R8),ISNUMBER('SW Rev'!R8),ISNUMBER('SW OpInc'!N8),ISNUMBER('SW Rev'!N8),'SW Rev'!R8>0,'SW Rev'!N8>0),('SW OpInc'!R8/'SW Rev'!R8-'SW OpInc'!N8/'SW Rev'!N8)*10000,""),"")
A622: ='SW Rev'!$A9 | B622: ='SW Rev'!$B9 | C622: =IFERROR(IF(AND(ISNUMBER('SW OpInc'!G9),ISNUMBER('SW Rev'!G9),ISNUMBER('SW OpInc'!C9),ISNUMBER('SW Rev'!C9),'SW Rev'!G9>0,'SW Rev'!C9>0),('SW OpInc'!G9/'SW Rev'!G9-'SW OpInc'!C9/'SW Rev'!C9)*10000,""),"") | D622: =IFERROR(IF(AND(ISNUMBER('SW OpInc'!H9),ISNUMBER('SW Rev'!H9),ISNUMBER('SW OpInc'!D9),ISNUMBER('SW Rev'!D9),'SW Rev'!H9>0,'SW Rev'!D9>0),('SW OpInc'!H9/'SW Rev'!H9-'SW OpInc'!D9/'SW Rev'!D9)*10000,""),"") | E622: =IFERROR(IF(AND(ISNUMBER('SW OpInc'!I9),ISNUMBER('SW Rev'!I9),ISNUMBER('SW OpInc'!E9),ISNUMBER('SW Rev'!E9),'SW Rev'!I9>0,'SW Rev'!E9>0),('SW OpInc'!I9/'SW Rev'!I9-'SW OpInc'!E9/'SW Rev'!E9)*10000,""),"") | F622: =IFERROR(IF(AND(ISNUMBER('SW OpInc'!J9),ISNUMBER('SW Rev'!J9),ISNUMBER('SW OpInc'!F9),ISNUMBER('SW Rev'!F9),'SW Rev'!J9>0,'SW Rev'!F9>0),('SW OpInc'!J9/'SW Rev'!J9-'SW OpInc'!F9/'SW Rev'!F9)*10000,""),"") | G622: =IFERROR(IF(AND(ISNUMBER('SW OpInc'!K9),ISNUMBER('SW Rev'!K9),ISNUMBER('SW OpInc'!G9),ISNUMBER('SW Rev'!G9),'SW Rev'!K9>0,'SW Rev'!G9>0),('SW OpInc'!K9/'SW Rev'!K9-'SW OpInc'!G9/'SW Rev'!G9)*10000,""),"") | H622: =IFERROR(IF(AND(ISNUMBER('SW OpInc'!L9),ISNUMBER('SW Rev'!L9),ISNUMBER('SW OpInc'!H9),ISNUMBER('SW Rev'!H9),'SW Rev'!L9>0,'SW Rev'!H9>0),('SW OpInc'!L9/'SW Rev'!L9-'SW OpInc'!H9/'SW Rev'!H9)*10000,""),"") | I622: =IFERROR(IF(AND(ISNUMBER('SW OpInc'!M9),ISNUMBER('SW Rev'!M9),ISNUMBER('SW OpInc'!I9),ISNUMBER('SW Rev'!I9),'SW Rev'!M9>0,'SW Rev'!I9>0),('SW OpInc'!M9/'SW Rev'!M9-'SW OpInc'!I9/'SW Rev'!I9)*10000,""),"") | J622: =IFERROR(IF(AND(ISNUMBER('SW OpInc'!N9),ISNUMBER('SW Rev'!N9),ISNUMBER('SW OpInc'!J9),ISNUMBER('SW Rev'!J9),'SW Rev'!N9>0,'SW Rev'!J9>0),('SW OpInc'!N9/'SW Rev'!N9-'SW OpInc'!J9/'SW Rev'!J9)*10000,""),"") | ... N622: =IFERROR(IF(AND(ISNUMBER('SW OpInc'!R9),ISNUMBER('SW Rev'!R9),ISNUMBER('SW OpInc'!N9),ISNUMBER('SW Rev'!N9),'SW Rev'!R9>0,'SW Rev'!N9>0),('SW OpInc'!R9/'SW Rev'!R9-'SW OpInc'!N9/'SW Rev'!N9)*10000,""),"")
A623: ='SW Rev'!$A10 | B623: ='SW Rev'!$B10 | C623: =IFERROR(IF(AND(ISNUMBER('SW OpInc'!G10),ISNUMBER('SW Rev'!G10),ISNUMBER('SW OpInc'!C10),ISNUMBER('SW Rev'!C10),'SW Rev'!G10>0,'SW Rev'!C10>0),('SW OpInc'!G10/'SW Rev'!G10-'SW OpInc'!C10/'SW Rev'!C10)*10000,""),"") | D623: =IFERROR(IF(AND(ISNUMBER('SW OpInc'!H10),ISNUMBER('SW Rev'!H10),ISNUMBER('SW OpInc'!D10),ISNUMBER('SW Rev'!D10),'SW Rev'!H10>0,'SW Rev'!D10>0),('SW OpInc'!H10/'SW Rev'!H10-'SW OpInc'!D10/'SW Rev'!D10)*10000,""),"") | E623: =IFERROR(IF(AND(ISNUMBER('SW OpInc'!I10),ISNUMBER('SW Rev'!I10),ISNUMBER('SW OpInc'!E10),ISNUMBER('SW Rev'!E10),'SW Rev'!I10>0,'SW Rev'!E10>0),('SW OpInc'!I10/'SW Rev'!I10-'SW OpInc'!E10/'SW Rev'!E10)*10000,""),"") | F623: =IFERROR(IF(AND(ISNUMBER('SW OpInc'!J10),ISNUMBER('SW Rev'!J10),ISNUMBER('SW OpInc'!F10),ISNUMBER('SW Rev'!F10),'SW Rev'!J10>0,'SW Rev'!F10>0),('SW OpInc'!J10/'SW Rev'!J10-'SW OpInc'!F10/'SW Rev'!F10)*10000,""),"") | G623: =IFERROR(IF(AND(ISNUMBER('SW OpInc'!K10),ISNUMBER('SW Rev'!K10),ISNUMBER('SW OpInc'!G10),ISNUMBER('SW Rev'!G10),'SW Rev'!K10>0,'SW Rev'!G10>0),('SW OpInc'!K10/'SW Rev'!K10-'SW OpInc'!G10/'SW Rev'!G10)*10000,""),"") | H623: =IFERROR(IF(AND(ISNUMBER('SW OpInc'!L10),ISNUMBER('SW Rev'!L10),ISNUMBER('SW OpInc'!H10),ISNUMBER('SW Rev'!H10),'SW Rev'!L10>0,'SW Rev'!H10>0),('SW OpInc'!L10/'SW Rev'!L10-'SW OpInc'!H10/'SW Rev'!H10)*10000,""),"") | I623: =IFERROR(IF(AND(ISNUMBER('SW OpInc'!M10),ISNUMBER('SW Rev'!M10),ISNUMBER('SW OpInc'!I10),ISNUMBER('SW Rev'!I10),'SW Rev'!M10>0,'SW Rev'!I10>0),('SW OpInc'!M10/'SW Rev'!M10-'SW OpInc'!I10/'SW Rev'!I10)*10000,""),"") | J623: =IFERROR(IF(AND(ISNUMBER('SW OpInc'!N10),ISNUMBER('SW Rev'!N10),ISNUMBER('SW OpInc'!J10),ISNUMBER('SW Rev'!J10),'SW Rev'!N10>0,'SW Rev'!J10>0),('SW OpInc'!N10/'SW Rev'!N10-'SW OpInc'!J10/'SW Rev'!J10)*10000,""),"") | ... N623: =IFERROR(IF(AND(ISNUMBER('SW OpInc'!R10),ISNUMBER('SW Rev'!R10),ISNUMBER('SW OpInc'!N10),ISNUMBER('SW Rev'!N10),'SW Rev'!R10>0,'SW Rev'!N10>0),('SW OpInc'!R10/'SW Rev'!R10-'SW OpInc'!N10/'SW Rev'!N10)*10000,""),"")
...

Sheet SW Revisions
A1: Software — NTM Consensus Estimate Revisions | H1: ⚠ Cells blank? This is a LIVE Bloomberg workbook — it has no saved data until its first refresh. Open it in desktop Excel on your Bloomberg terminal PC (add-in logged in), then Bloomberg ribbon ▸ Refresh All (or Ctrl+Alt+F9), wait a few minutes, and save. See README.
A2: NTM (blended-forward 12M, BEst 1BF) consensus revenue and EPS: current vs 1M / 3M / 6M ago. Revisions are % changes, so mixed reporting currencies do not distort them.
A3: Source: Bloomberg BDP — BEST_SALES / BEST_EPS with BEST_FPERIOD_OVERRIDE=1BF; historical as-of via BEST_DATA_DATE_OVERRIDE (dates in row 4, driven by TODAY()).
B4: As-of dates: | C4: =TODAY() | D4: =EDATE($C$4,-1) | E4: =EDATE($C$4,-3) | F4: =EDATE($C$4,-6)
A5: Ticker | C5: NTM Rev (loc mm) | D5: NTM Rev 1M ago | E5: NTM Rev 3M ago | F5: NTM Rev 6M ago | G5: Rev rev Δ1M % | H5: Rev rev Δ3M % | I5: Rev rev Δ6M % | K5: NTM EPS | L5: NTM EPS 1M ago | M5: NTM EPS 3M ago | N5: NTM EPS 6M ago | O5: EPS rev Δ1M % | P5: EPS rev Δ3M % | Q5: EPS rev Δ6M %
A6: =Tickers!$A$5 | C6: =_xll.BDP($A6,"BEST_SALES","BEST_FPERIOD_OVERRIDE","1BF") | D6: =_xll.BDP($A6,"BEST_SALES","BEST_FPERIOD_OVERRIDE","1BF","BEST_DATA_DATE_OVERRIDE",TEXT(YEAR($D$4),"0000")&TEXT(MONTH($D$4),"00")&TEXT(DAY($D$4),"00")) | E6: =_xll.BDP($A6,"BEST_SALES","BEST_FPERIOD_OVERRIDE","1BF","BEST_DATA_DATE_OVERRIDE",TEXT(YEAR($E$4),"0000")&TEXT(MONTH($E$4),"00")&TEXT(DAY($E$4),"00")) | F6: =_xll.BDP($A6,"BEST_SALES","BEST_FPERIOD_OVERRIDE","1BF","BEST_DATA_DATE_OVERRIDE",TEXT(YEAR($F$4),"0000")&TEXT(MONTH($F$4),"00")&TEXT(DAY($F$4),"00")) | G6: =IFERROR(IF(AND(ISNUMBER($C6),ISNUMBER(D6),D6<>0),$C6/D6-1,""),"") | H6: =IFERROR(IF(AND(ISNUMBER($C6),ISNUMBER(E6),E6<>0),$C6/E6-1,""),"") | I6: =IFERROR(IF(AND(ISNUMBER($C6),ISNUMBER(F6),F6<>0),$C6/F6-1,""),"") | K6: =_xll.BDP($A6,"BEST_EPS","BEST_FPERIOD_OVERRIDE","1BF") | L6: =_xll.BDP($A6,"BEST_EPS","BEST_FPERIOD_OVERRIDE","1BF","BEST_DATA_DATE_OVERRIDE",TEXT(YEAR($D$4),"0000")&TEXT(MONTH($D$4),"00")&TEXT(DAY($D$4),"00")) | M6: =_xll.BDP($A6,"BEST_EPS","BEST_FPERIOD_OVERRIDE","1BF","BEST_DATA_DATE_OVERRIDE",TEXT(YEAR($E$4),"0000")&TEXT(MONTH($E$4),"00")&TEXT(DAY($E$4),"00")) | N6: =_xll.BDP($A6,"BEST_EPS","BEST_FPERIOD_OVERRIDE","1BF","BEST_DATA_DATE_OVERRIDE",TEXT(YEAR($F$4),"0000")&TEXT(MONTH($F$4),"00")&TEXT(DAY($F$4),"00")) | O6: =IFERROR(IF(AND(ISNUMBER($K6),ISNUMBER(L6),L6<>0),$K6/L6-1,""),"") | P6: =IFERROR(IF(AND(ISNUMBER($K6),ISNUMBER(M6),M6<>0),$K6/M6-1,""),"") | Q6: =IFERROR(IF(AND(ISNUMBER($K6),ISNUMBER(N6),N6<>0),$K6/N6-1,""),"")
A7: =Tickers!$A$6 | C7: =_xll.BDP($A7,"BEST_SALES","BEST_FPERIOD_OVERRIDE","1BF") | D7: =_xll.BDP($A7,"BEST_SALES","BEST_FPERIOD_OVERRIDE","1BF","BEST_DATA_DATE_OVERRIDE",TEXT(YEAR($D$4),"0000")&TEXT(MONTH($D$4),"00")&TEXT(DAY($D$4),"00")) | E7: =_xll.BDP($A7,"BEST_SALES","BEST_FPERIOD_OVERRIDE","1BF","BEST_DATA_DATE_OVERRIDE",TEXT(YEAR($E$4),"0000")&TEXT(MONTH($E$4),"00")&TEXT(DAY($E$4),"00")) | F7: =_xll.BDP($A7,"BEST_SALES","BEST_FPERIOD_OVERRIDE","1BF","BEST_DATA_DATE_OVERRIDE",TEXT(YEAR($F$4),"0000")&TEXT(MONTH($F$4),"00")&TEXT(DAY($F$4),"00")) | G7: =IFERROR(IF(AND(ISNUMBER($C7),ISNUMBER(D7),D7<>0),$C7/D7-1,""),"") | H7: =IFERROR(IF(AND(ISNUMBER($C7),ISNUMBER(E7),E7<>0),$C7/E7-1,""),"") | I7: =IFERROR(IF(AND(ISNUMBER($C7),ISNUMBER(F7),F7<>0),$C7/F7-1,""),"") | K7: =_xll.BDP($A7,"BEST_EPS","BEST_FPERIOD_OVERRIDE","1BF") | L7: =_xll.BDP($A7,"BEST_EPS","BEST_FPERIOD_OVERRIDE","1BF","BEST_DATA_DATE_OVERRIDE",TEXT(YEAR($D$4),"0000")&TEXT(MONTH($D$4),"00")&TEXT(DAY($D$4),"00")) | M7: =_xll.BDP($A7,"BEST_EPS","BEST_FPERIOD_OVERRIDE","1BF","BEST_DATA_DATE_OVERRIDE",TEXT(YEAR($E$4),"0000")&TEXT(MONTH($E$4),"00")&TEXT(DAY($E$4),"00")) | N7: =_xll.BDP($A7,"BEST_EPS","BEST_FPERIOD_OVERRIDE","1BF","BEST_DATA_DATE_OVERRIDE",TEXT(YEAR($F$4),"0000")&TEXT(MONTH($F$4),"00")&TEXT(DAY($F$4),"00")) | O7: =IFERROR(IF(AND(ISNUMBER($K7),ISNUMBER(L7),L7<>0),$K7/L7-1,""),"") | P7: =IFERROR(IF(AND(ISNUMBER($K7),ISNUMBER(M7),M7<>0),$K7/M7-1,""),"") | Q7: =IFERROR(IF(AND(ISNUMBER($K7),ISNUMBER(N7),N7<>0),$K7/N7-1,""),"")
A8: =Tickers!$A$7 | C8: =_xll.BDP($A8,"BEST_SALES","BEST_FPERIOD_OVERRIDE","1BF") | D8: =_xll.BDP($A8,"BEST_SALES","BEST_FPERIOD_OVERRIDE","1BF","BEST_DATA_DATE_OVERRIDE",TEXT(YEAR($D$4),"0000")&TEXT(MONTH($D$4),"00")&TEXT(DAY($D$4),"00")) | E8: =_xll.BDP($A8,"BEST_SALES","BEST_FPERIOD_OVERRIDE","1BF","BEST_DATA_DATE_OVERRIDE",TEXT(YEAR($E$4),"0000")&TEXT(MONTH($E$4),"00")&TEXT(DAY($E$4),"00")) | F8: =_xll.BDP($A8,"BEST_SALES","BEST_FPERIOD_OVERRIDE","1BF","BEST_DATA_DATE_OVERRIDE",TEXT(YEAR($F$4),"0000")&TEXT(MONTH($F$4),"00")&TEXT(DAY($F$4),"00")) | G8: =IFERROR(IF(AND(ISNUMBER($C8),ISNUMBER(D8),D8<>0),$C8/D8-1,""),"") | H8: =IFERROR(IF(AND(ISNUMBER($C8),ISNUMBER(E8),E8<>0),$C8/E8-1,""),"") | I8: =IFERROR(IF(AND(ISNUMBER($C8),ISNUMBER(F8),F8<>0),$C8/F8-1,""),"") | K8: =_xll.BDP($A8,"BEST_EPS","BEST_FPERIOD_OVERRIDE","1BF") | L8: =_xll.BDP($A8,"BEST_EPS","BEST_FPERIOD_OVERRIDE","1BF","BEST_DATA_DATE_OVERRIDE",TEXT(YEAR($D$4),"0000")&TEXT(MONTH($D$4),"00")&TEXT(DAY($D$4),"00")) | M8: =_xll.BDP($A8,"BEST_EPS","BEST_FPERIOD_OVERRIDE","1BF","BEST_DATA_DATE_OVERRIDE",TEXT(YEAR($E$4),"0000")&TEXT(MONTH($E$4),"00")&TEXT(DAY($E$4),"00")) | N8: =_xll.BDP($A8,"BEST_EPS","BEST_FPERIOD_OVERRIDE","1BF","BEST_DATA_DATE_OVERRIDE",TEXT(YEAR($F$4),"0000")&TEXT(MONTH($F$4),"00")&TEXT(DAY($F$4),"00")) | O8: =IFERROR(IF(AND(ISNUMBER($K8),ISNUMBER(L8),L8<>0),$K8/L8-1,""),"") | P8: =IFERROR(IF(AND(ISNUMBER($K8),ISNUMBER(M8),M8<>0),$K8/M8-1,""),"") | Q8: =IFERROR(IF(AND(ISNUMBER($K8),ISNUMBER(N8),N8<>0),$K8/N8-1,""),"")
A9: =Tickers!$A$8 | C9: =_xll.BDP($A9,"BEST_SALES","BEST_FPERIOD_OVERRIDE","1BF") | D9: =_xll.BDP($A9,"BEST_SALES","BEST_FPERIOD_OVERRIDE","1BF","BEST_DATA_DATE_OVERRIDE",TEXT(YEAR($D$4),"0000")&TEXT(MONTH($D$4),"00")&TEXT(DAY($D$4),"00")) | E9: =_xll.BDP($A9,"BEST_SALES","BEST_FPERIOD_OVERRIDE","1BF","BEST_DATA_DATE_OVERRIDE",TEXT(YEAR($E$4),"0000")&TEXT(MONTH($E$4),"00")&TEXT(DAY($E$4),"00")) | F9: =_xll.BDP($A9,"BEST_SALES","BEST_FPERIOD_OVERRIDE","1BF","BEST_DATA_DATE_OVERRIDE",TEXT(YEAR($F$4),"0000")&TEXT(MONTH($F$4),"00")&TEXT(DAY($F$4),"00")) | G9: =IFERROR(IF(AND(ISNUMBER($C9),ISNUMBER(D9),D9<>0),$C9/D9-1,""),"") | H9: =IFERROR(IF(AND(ISNUMBER($C9),ISNUMBER(E9),E9<>0),$C9/E9-1,""),"") | I9: =IFERROR(IF(AND(ISNUMBER($C9),ISNUMBER(F9),F9<>0),$C9/F9-1,""),"") | K9: =_xll.BDP($A9,"BEST_EPS","BEST_FPERIOD_OVERRIDE","1BF") | L9: =_xll.BDP($A9,"BEST_EPS","BEST_FPERIOD_OVERRIDE","1BF","BEST_DATA_DATE_OVERRIDE",TEXT(YEAR($D$4),"0000")&TEXT(MONTH($D$4),"00")&TEXT(DAY($D$4),"00")) | M9: =_xll.BDP($A9,"BEST_EPS","BEST_FPERIOD_OVERRIDE","1BF","BEST_DATA_DATE_OVERRIDE",TEXT(YEAR($E$4),"0000")&TEXT(MONTH($E$4),"00")&TEXT(DAY($E$4),"00")) | N9: =_xll.BDP($A9,"BEST_EPS","BEST_FPERIOD_OVERRIDE","1BF","BEST_DATA_DATE_OVERRIDE",TEXT(YEAR($F$4),"0000")&TEXT(MONTH($F$4),"00")&TEXT(DAY($F$4),"00")) | O9: =IFERROR(IF(AND(ISNUMBER($K9),ISNUMBER(L9),L9<>0),$K9/L9-1,""),"") | P9: =IFERROR(IF(AND(ISNUMBER($K9),ISNUMBER(M9),M9<>0),$K9/M9-1,""),"") | Q9: =IFERROR(IF(AND(ISNUMBER($K9),ISNUMBER(N9),N9<>0),$K9/N9-1,""),"")
A10: =Tickers!$A$9 | C10: =_xll.BDP($A10,"BEST_SALES","BEST_FPERIOD_OVERRIDE","1BF") | D10: =_xll.BDP($A10,"BEST_SALES","BEST_FPERIOD_OVERRIDE","1BF","BEST_DATA_DATE_OVERRIDE",TEXT(YEAR($D$4),"0000")&TEXT(MONTH($D$4),"00")&TEXT(DAY($D$4),"00")) | E10: =_xll.BDP($A10,"BEST_SALES","BEST_FPERIOD_OVERRIDE","1BF","BEST_DATA_DATE_OVERRIDE",TEXT(YEAR($E$4),"0000")&TEXT(MONTH($E$4),"00")&TEXT(DAY($E$4),"00")) | F10: =_xll.BDP($A10,"BEST_SALES","BEST_FPERIOD_OVERRIDE","1BF","BEST_DATA_DATE_OVERRIDE",TEXT(YEAR($F$4),"0000")&TEXT(MONTH($F$4),"00")&TEXT(DAY($F$4),"00")) | G10: =IFERROR(IF(AND(ISNUMBER($C10),ISNUMBER(D10),D10<>0),$C10/D10-1,""),"") | H10: =IFERROR(IF(AND(ISNUMBER($C10),ISNUMBER(E10),E10<>0),$C10/E10-1,""),"") | I10: =IFERROR(IF(AND(ISNUMBER($C10),ISNUMBER(F10),F10<>0),$C10/F10-1,""),"") | K10: =_xll.BDP($A10,"BEST_EPS","BEST_FPERIOD_OVERRIDE","1BF") | L10: =_xll.BDP($A10,"BEST_EPS","BEST_FPERIOD_OVERRIDE","1BF","BEST_DATA_DATE_OVERRIDE",TEXT(YEAR($D$4),"0000")&TEXT(MONTH($D$4),"00")&TEXT(DAY($D$4),"00")) | M10: =_xll.BDP($A10,"BEST_EPS","BEST_FPERIOD_OVERRIDE","1BF","BEST_DATA_DATE_OVERRIDE",TEXT(YEAR($E$4),"0000")&TEXT(MONTH($E$4),"00")&TEXT(DAY($E$4),"00")) | N10: =_xll.BDP($A10,"BEST_EPS","BEST_FPERIOD_OVERRIDE","1BF","BEST_DATA_DATE_OVERRIDE",TEXT(YEAR($F$4),"0000")&TEXT(MONTH($F$4),"00")&TEXT(DAY($F$4),"00")) | O10: =IFERROR(IF(AND(ISNUMBER($K10),ISNUMBER(L10),L10<>0),$K10/L10-1,""),"") | P10: =IFERROR(IF(AND(ISNUMBER($K10),ISNUMBER(M10),M10<>0),$K10/M10-1,""),"") | Q10: =IFERROR(IF(AND(ISNUMBER($K10),ISNUMBER(N10),N10<>0),$K10/N10-1,""),"")
A11: =Tickers!$A$10 | C11: =_xll.BDP($A11,"BEST_SALES","BEST_FPERIOD_OVERRIDE","1BF") | D11: =_xll.BDP($A11,"BEST_SALES","BEST_FPERIOD_OVERRIDE","1BF","BEST_DATA_DATE_OVERRIDE",TEXT(YEAR($D$4),"0000")&TEXT(MONTH($D$4),"00")&TEXT(DAY($D$4),"00")) | E11: =_xll.BDP($A11,"BEST_SALES","BEST_FPERIOD_OVERRIDE","1BF","BEST_DATA_DATE_OVERRIDE",TEXT(YEAR($E$4),"0000")&TEXT(MONTH($E$4),"00")&TEXT(DAY($E$4),"00")) | F11: =_xll.BDP($A11,"BEST_SALES","BEST_FPERIOD_OVERRIDE","1BF","BEST_DATA_DATE_OVERRIDE",TEXT(YEAR($F$4),"0000")&TEXT(MONTH($F$4),"00")&TEXT(DAY($F$4),"00")) | G11: =IFERROR(IF(AND(ISNUMBER($C11),ISNUMBER(D11),D11<>0),$C11/D11-1,""),"") | H11: =IFERROR(IF(AND(ISNUMBER($C11),ISNUMBER(E11),E11<>0),$C11/E11-1,""),"") | I11: =IFERROR(IF(AND(ISNUMBER($C11),ISNUMBER(F11),F11<>0),$C11/F11-1,""),"") | K11: =_xll.BDP($A11,"BEST_EPS","BEST_FPERIOD_OVERRIDE","1BF") | L11: =_xll.BDP($A11,"BEST_EPS","BEST_FPERIOD_OVERRIDE","1BF","BEST_DATA_DATE_OVERRIDE",TEXT(YEAR($D$4),"0000")&TEXT(MONTH($D$4),"00")&TEXT(DAY($D$4),"00")) | M11: =_xll.BDP($A11,"BEST_EPS","BEST_FPERIOD_OVERRIDE","1BF","BEST_DATA_DATE_OVERRIDE",TEXT(YEAR($E$4),"0000")&TEXT(MONTH($E$4),"00")&TEXT(DAY($E$4),"00")) | N11: =_xll.BDP($A11,"BEST_EPS","BEST_FPERIOD_OVERRIDE","1BF","BEST_DATA_DATE_OVERRIDE",TEXT(YEAR($F$4),"0000")&TEXT(MONTH($F$4),"00")&TEXT(DAY($F$4),"00")) | O11: =IFERROR(IF(AND(ISNUMBER($K11),ISNUMBER(L11),L11<>0),$K11/L11-1,""),"") | P11: =IFERROR(IF(AND(ISNUMBER($K11),ISNUMBER(M11),M11<>0),$K11/M11-1,""),"") | Q11: =IFERROR(IF(AND(ISNUMBER($K11),ISNUMBER(N11),N11<>0),$K11/N11-1,""),"")
A12: =Tickers!$A$11 | C12: =_xll.BDP($A12,"BEST_SALES","BEST_FPERIOD_OVERRIDE","1BF") | D12: =_xll.BDP($A12,"BEST_SALES","BEST_FPERIOD_OVERRIDE","1BF","BEST_DATA_DATE_OVERRIDE",TEXT(YEAR($D$4),"0000")&TEXT(MONTH($D$4),"00")&TEXT(DAY($D$4),"00")) | E12: =_xll.BDP($A12,"BEST_SALES","BEST_FPERIOD_OVERRIDE","1BF","BEST_DATA_DATE_OVERRIDE",TEXT(YEAR($E$4),"0000")&TEXT(MONTH($E$4),"00")&TEXT(DAY($E$4),"00")) | F12: =_xll.BDP($A12,"BEST_SALES","BEST_FPERIOD_OVERRIDE","1BF","BEST_DATA_DATE_OVERRIDE",TEXT(YEAR($F$4),"0000")&TEXT(MONTH($F$4),"00")&TEXT(DAY($F$4),"00")) | G12: =IFERROR(IF(AND(ISNUMBER($C12),ISNUMBER(D12),D12<>0),$C12/D12-1,""),"") | H12: =IFERROR(IF(AND(ISNUMBER($C12),ISNUMBER(E12),E12<>0),$C12/E12-1,""),"") | I12: =IFERROR(IF(AND(ISNUMBER($C12),ISNUMBER(F12),F12<>0),$C12/F12-1,""),"") | K12: =_xll.BDP($A12,"BEST_EPS","BEST_FPERIOD_OVERRIDE","1BF") | L12: =_xll.BDP($A12,"BEST_EPS","BEST_FPERIOD_OVERRIDE","1BF","BEST_DATA_DATE_OVERRIDE",TEXT(YEAR($D$4),"0000")&TEXT(MONTH($D$4),"00")&TEXT(DAY($D$4),"00")) | M12: =_xll.BDP($A12,"BEST_EPS","BEST_FPERIOD_OVERRIDE","1BF","BEST_DATA_DATE_OVERRIDE",TEXT(YEAR($E$4),"0000")&TEXT(MONTH($E$4),"00")&TEXT(DAY($E$4),"00")) | N12: =_xll.BDP($A12,"BEST_EPS","BEST_FPERIOD_OVERRIDE","1BF","BEST_DATA_DATE_OVERRIDE",TEXT(YEAR($F$4),"0000")&TEXT(MONTH($F$4),"00")&TEXT(DAY($F$4),"00")) | O12: =IFERROR(IF(AND(ISNUMBER($K12),ISNUMBER(L12),L12<>0),$K12/L12-1,""),"") | P12: =IFERROR(IF(AND(ISNUMBER($K12),ISNUMBER(M12),M12<>0),$K12/M12-1,""),"") | Q12: =IFERROR(IF(AND(ISNUMBER($K12),ISNUMBER(N12),N12<>0),$K12/N12-1,""),"")
A13: =Tickers!$A$12 | C13: =_xll.BDP($A13,"BEST_SALES","BEST_FPERIOD_OVERRIDE","1BF") | D13: =_xll.BDP($A13,"BEST_SALES","BEST_FPERIOD_OVERRIDE","1BF","BEST_DATA_DATE_OVERRIDE",TEXT(YEAR($D$4),"0000")&TEXT(MONTH($D$4),"00")&TEXT(DAY($D$4),"00")) | E13: =_xll.BDP($A13,"BEST_SALES","BEST_FPERIOD_OVERRIDE","1BF","BEST_DATA_DATE_OVERRIDE",TEXT(YEAR($E$4),"0000")&TEXT(MONTH($E$4),"00")&TEXT(DAY($E$4),"00")) | F13: =_xll.BDP($A13,"BEST_SALES","BEST_FPERIOD_OVERRIDE","1BF","BEST_DATA_DATE_OVERRIDE",TEXT(YEAR($F$4),"0000")&TEXT(MONTH($F$4),"00")&TEXT(DAY($F$4),"00")) | G13: =IFERROR(IF(AND(ISNUMBER($C13),ISNUMBER(D13),D13<>0),$C13/D13-1,""),"") | H13: =IFERROR(IF(AND(ISNUMBER($C13),ISNUMBER(E13),E13<>0),$C13/E13-1,""),"") | I13: =IFERROR(IF(AND(ISNUMBER($C13),ISNUMBER(F13),F13<>0),$C13/F13-1,""),"") | K13: =_xll.BDP($A13,"BEST_EPS","BEST_FPERIOD_OVERRIDE","1BF") | L13: =_xll.BDP($A13,"BEST_EPS","BEST_FPERIOD_OVERRIDE","1BF","BEST_DATA_DATE_OVERRIDE",TEXT(YEAR($D$4),"0000")&TEXT(MONTH($D$4),"00")&TEXT(DAY($D$4),"00")) | M13: =_xll.BDP($A13,"BEST_EPS","BEST_FPERIOD_OVERRIDE","1BF","BEST_DATA_DATE_OVERRIDE",TEXT(YEAR($E$4),"0000")&TEXT(MONTH($E$4),"00")&TEXT(DAY($E$4),"00")) | N13: =_xll.BDP($A13,"BEST_EPS","BEST_FPERIOD_OVERRIDE","1BF","BEST_DATA_DATE_OVERRIDE",TEXT(YEAR($F$4),"0000")&TEXT(MONTH($F$4),"00")&TEXT(DAY($F$4),"00")) | O13: =IFERROR(IF(AND(ISNUMBER($K13),ISNUMBER(L13),L13<>0),$K13/L13-1,""),"") | P13: =IFERROR(IF(AND(ISNUMBER($K13),ISNUMBER(M13),M13<>0),$K13/M13-1,""),"") | Q13: =IFERROR(IF(AND(ISNUMBER($K13),ISNUMBER(N13),N13<>0),$K13/N13-1,""),"")
A14: =Tickers!$A$13 | C14: =_xll.BDP($A14,"BEST_SALES","BEST_FPERIOD_OVERRIDE","1BF") | D14: =_xll.BDP($A14,"BEST_SALES","BEST_FPERIOD_OVERRIDE","1BF","BEST_DATA_DATE_OVERRIDE",TEXT(YEAR($D$4),"0000")&TEXT(MONTH($D$4),"00")&TEXT(DAY($D$4),"00")) | E14: =_xll.BDP($A14,"BEST_SALES","BEST_FPERIOD_OVERRIDE","1BF","BEST_DATA_DATE_OVERRIDE",TEXT(YEAR($E$4),"0000")&TEXT(MONTH($E$4),"00")&TEXT(DAY($E$4),"00")) | F14: =_xll.BDP($A14,"BEST_SALES","BEST_FPERIOD_OVERRIDE","1BF","BEST_DATA_DATE_OVERRIDE",TEXT(YEAR($F$4),"0000")&TEXT(MONTH($F$4),"00")&TEXT(DAY($F$4),"00")) | G14: =IFERROR(IF(AND(ISNUMBER($C14),ISNUMBER(D14),D14<>0),$C14/D14-1,""),"") | H14: =IFERROR(IF(AND(ISNUMBER($C14),ISNUMBER(E14),E14<>0),$C14/E14-1,""),"") | I14: =IFERROR(IF(AND(ISNUMBER($C14),ISNUMBER(F14),F14<>0),$C14/F14-1,""),"") | K14: =_xll.BDP($A14,"BEST_EPS","BEST_FPERIOD_OVERRIDE","1BF") | L14: =_xll.BDP($A14,"BEST_EPS","BEST_FPERIOD_OVERRIDE","1BF","BEST_DATA_DATE_OVERRIDE",TEXT(YEAR($D$4),"0000")&TEXT(MONTH($D$4),"00")&TEXT(DAY($D$4),"00")) | M14: =_xll.BDP($A14,"BEST_EPS","BEST_FPERIOD_OVERRIDE","1BF","BEST_DATA_DATE_OVERRIDE",TEXT(YEAR($E$4),"0000")&TEXT(MONTH($E$4),"00")&TEXT(DAY($E$4),"00")) | N14: =_xll.BDP($A14,"BEST_EPS","BEST_FPERIOD_OVERRIDE","1BF","BEST_DATA_DATE_OVERRIDE",TEXT(YEAR($F$4),"0000")&TEXT(MONTH($F$4),"00")&TEXT(DAY($F$4),"00")) | O14: =IFERROR(IF(AND(ISNUMBER($K14),ISNUMBER(L14),L14<>0),$K14/L14-1,""),"") | P14: =IFERROR(IF(AND(ISNUMBER($K14),ISNUMBER(M14),M14<>0),$K14/M14-1,""),"") | Q14: =IFERROR(IF(AND(ISNUMBER($K14),ISNUMBER(N14),N14<>0),$K14/N14-1,""),"")
A15: =Tickers!$A$14 | C15: =_xll.BDP($A15,"BEST_SALES","BEST_FPERIOD_OVERRIDE","1BF") | D15: =_xll.BDP($A15,"BEST_SALES","BEST_FPERIOD_OVERRIDE","1BF","BEST_DATA_DATE_OVERRIDE",TEXT(YEAR($D$4),"0000")&TEXT(MONTH($D$4),"00")&TEXT(DAY($D$4),"00")) | E15: =_xll.BDP($A15,"BEST_SALES","BEST_FPERIOD_OVERRIDE","1BF","BEST_DATA_DATE_OVERRIDE",TEXT(YEAR($E$4),"0000")&TEXT(MONTH($E$4),"00")&TEXT(DAY($E$4),"00")) | F15: =_xll.BDP($A15,"BEST_SALES","BEST_FPERIOD_OVERRIDE","1BF","BEST_DATA_DATE_OVERRIDE",TEXT(YEAR($F$4),"0000")&TEXT(MONTH($F$4),"00")&TEXT(DAY($F$4),"00")) | G15: =IFERROR(IF(AND(ISNUMBER($C15),ISNUMBER(D15),D15<>0),$C15/D15-1,""),"") | H15: =IFERROR(IF(AND(ISNUMBER($C15),ISNUMBER(E15),E15<>0),$C15/E15-1,""),"") | I15: =IFERROR(IF(AND(ISNUMBER($C15),ISNUMBER(F15),F15<>0),$C15/F15-1,""),"") | K15: =_xll.BDP($A15,"BEST_EPS","BEST_FPERIOD_OVERRIDE","1BF") | L15: =_xll.BDP($A15,"BEST_EPS","BEST_FPERIOD_OVERRIDE","1BF","BEST_DATA_DATE_OVERRIDE",TEXT(YEAR($D$4),"0000")&TEXT(MONTH($D$4),"00")&TEXT(DAY($D$4),"00")) | M15: =_xll.BDP($A15,"BEST_EPS","BEST_FPERIOD_OVERRIDE","1BF","BEST_DATA_DATE_OVERRIDE",TEXT(YEAR($E$4),"0000")&TEXT(MONTH($E$4),"00")&TEXT(DAY($E$4),"00")) | N15: =_xll.BDP($A15,"BEST_EPS","BEST_FPERIOD_OVERRIDE","1BF","BEST_DATA_DATE_OVERRIDE",TEXT(YEAR($F$4),"0000")&TEXT(MONTH($F$4),"00")&TEXT(DAY($F$4),"00")) | O15: =IFERROR(IF(AND(ISNUMBER($K15),ISNUMBER(L15),L15<>0),$K15/L15-1,""),"") | P15: =IFERROR(IF(AND(ISNUMBER($K15),ISNUMBER(M15),M15<>0),$K15/M15-1,""),"") | Q15: =IFERROR(IF(AND(ISNUMBER($K15),ISNUMBER(N15),N15<>0),$K15/N15-1,""),"")
A16: =Tickers!$A$15 | C16: =_xll.BDP($A16,"BEST_SALES","BEST_FPERIOD_OVERRIDE","1BF") | D16: =_xll.BDP($A16,"BEST_SALES","BEST_FPERIOD_OVERRIDE","1BF","BEST_DATA_DATE_OVERRIDE",TEXT(YEAR($D$4),"0000")&TEXT(MONTH($D$4),"00")&TEXT(DAY($D$4),"00")) | E16: =_xll.BDP($A16,"BEST_SALES","BEST_FPERIOD_OVERRIDE","1BF","BEST_DATA_DATE_OVERRIDE",TEXT(YEAR($E$4),"0000")&TEXT(MONTH($E$4),"00")&TEXT(DAY($E$4),"00")) | F16: =_xll.BDP($A16,"BEST_SALES","BEST_FPERIOD_OVERRIDE","1BF","BEST_DATA_DATE_OVERRIDE",TEXT(YEAR($F$4),"0000")&TEXT(MONTH($F$4),"00")&TEXT(DAY($F$4),"00")) | G16: =IFERROR(IF(AND(ISNUMBER($C16),ISNUMBER(D16),D16<>0),$C16/D16-1,""),"") | H16: =IFERROR(IF(AND(ISNUMBER($C16),ISNUMBER(E16),E16<>0),$C16/E16-1,""),"") | I16: =IFERROR(IF(AND(ISNUMBER($C16),ISNUMBER(F16),F16<>0),$C16/F16-1,""),"") | K16: =_xll.BDP($A16,"BEST_EPS","BEST_FPERIOD_OVERRIDE","1BF") | L16: =_xll.BDP($A16,"BEST_EPS","BEST_FPERIOD_OVERRIDE","1BF","BEST_DATA_DATE_OVERRIDE",TEXT(YEAR($D$4),"0000")&TEXT(MONTH($D$4),"00")&TEXT(DAY($D$4),"00")) | M16: =_xll.BDP($A16,"BEST_EPS","BEST_FPERIOD_OVERRIDE","1BF","BEST_DATA_DATE_OVERRIDE",TEXT(YEAR($E$4),"0000")&TEXT(MONTH($E$4),"00")&TEXT(DAY($E$4),"00")) | N16: =_xll.BDP($A16,"BEST_EPS","BEST_FPERIOD_OVERRIDE","1BF","BEST_DATA_DATE_OVERRIDE",TEXT(YEAR($F$4),"0000")&TEXT(MONTH($F$4),"00")&TEXT(DAY($F$4),"00")) | O16: =IFERROR(IF(AND(ISNUMBER($K16),ISNUMBER(L16),L16<>0),$K16/L16-1,""),"") | P16: =IFERROR(IF(AND(ISNUMBER($K16),ISNUMBER(M16),M16<>0),$K16/M16-1,""),"") | Q16: =IFERROR(IF(AND(ISNUMBER($K16),ISNUMBER(N16),N16<>0),$K16/N16-1,""),"")
A17: =Tickers!$A$16 | C17: =_xll.BDP($A17,"BEST_SALES","BEST_FPERIOD_OVERRIDE","1BF") | D17: =_xll.BDP($A17,"BEST_SALES","BEST_FPERIOD_OVERRIDE","1BF","BEST_DATA_DATE_OVERRIDE",TEXT(YEAR($D$4),"0000")&TEXT(MONTH($D$4),"00")&TEXT(DAY($D$4),"00")) | E17: =_xll.BDP($A17,"BEST_SALES","BEST_FPERIOD_OVERRIDE","1BF","BEST_DATA_DATE_OVERRIDE",TEXT(YEAR($E$4),"0000")&TEXT(MONTH($E$4),"00")&TEXT(DAY($E$4),"00")) | F17: =_xll.BDP($A17,"BEST_SALES","BEST_FPERIOD_OVERRIDE","1BF","BEST_DATA_DATE_OVERRIDE",TEXT(YEAR($F$4),"0000")&TEXT(MONTH($F$4),"00")&TEXT(DAY($F$4),"00")) | G17: =IFERROR(IF(AND(ISNUMBER($C17),ISNUMBER(D17),D17<>0),$C17/D17-1,""),"") | H17: =IFERROR(IF(AND(ISNUMBER($C17),ISNUMBER(E17),E17<>0),$C17/E17-1,""),"") | I17: =IFERROR(IF(AND(ISNUMBER($C17),ISNUMBER(F17),F17<>0),$C17/F17-1,""),"") | K17: =_xll.BDP($A17,"BEST_EPS","BEST_FPERIOD_OVERRIDE","1BF") | L17: =_xll.BDP($A17,"BEST_EPS","BEST_FPERIOD_OVERRIDE","1BF","BEST_DATA_DATE_OVERRIDE",TEXT(YEAR($D$4),"0000")&TEXT(MONTH($D$4),"00")&TEXT(DAY($D$4),"00")) | M17: =_xll.BDP($A17,"BEST_EPS","BEST_FPERIOD_OVERRIDE","1BF","BEST_DATA_DATE_OVERRIDE",TEXT(YEAR($E$4),"0000")&TEXT(MONTH($E$4),"00")&TEXT(DAY($E$4),"00")) | N17: =_xll.BDP($A17,"BEST_EPS","BEST_FPERIOD_OVERRIDE","1BF","BEST_DATA_DATE_OVERRIDE",TEXT(YEAR($F$4),"0000")&TEXT(MONTH($F$4),"00")&TEXT(DAY($F$4),"00")) | O17: =IFERROR(IF(AND(ISNUMBER($K17),ISNUMBER(L17),L17<>0),$K17/L17-1,""),"") | P17: =IFERROR(IF(AND(ISNUMBER($K17),ISNUMBER(M17),M17<>0),$K17/M17-1,""),"") | Q17: =IFERROR(IF(AND(ISNUMBER($K17),ISNUMBER(N17),N17<>0),$K17/N17-1,""),"")
A18: =Tickers!$A$17 | C18: =_xll.BDP($A18,"BEST_SALES","BEST_FPERIOD_OVERRIDE","1BF") | D18: =_xll.BDP($A18,"BEST_SALES","BEST_FPERIOD_OVERRIDE","1BF","BEST_DATA_DATE_OVERRIDE",TEXT(YEAR($D$4),"0000")&TEXT(MONTH($D$4),"00")&TEXT(DAY($D$4),"00")) | E18: =_xll.BDP($A18,"BEST_SALES","BEST_FPERIOD_OVERRIDE","1BF","BEST_DATA_DATE_OVERRIDE",TEXT(YEAR($E$4),"0000")&TEXT(MONTH($E$4),"00")&TEXT(DAY($E$4),"00")) | F18: =_xll.BDP($A18,"BEST_SALES","BEST_FPERIOD_OVERRIDE","1BF","BEST_DATA_DATE_OVERRIDE",TEXT(YEAR($F$4),"0000")&TEXT(MONTH($F$4),"00")&TEXT(DAY($F$4),"00")) | G18: =IFERROR(IF(AND(ISNUMBER($C18),ISNUMBER(D18),D18<>0),$C18/D18-1,""),"") | H18: =IFERROR(IF(AND(ISNUMBER($C18),ISNUMBER(E18),E18<>0),$C18/E18-1,""),"") | I18: =IFERROR(IF(AND(ISNUMBER($C18),ISNUMBER(F18),F18<>0),$C18/F18-1,""),"") | K18: =_xll.BDP($A18,"BEST_EPS","BEST_FPERIOD_OVERRIDE","1BF") | L18: =_xll.BDP($A18,"BEST_EPS","BEST_FPERIOD_OVERRIDE","1BF","BEST_DATA_DATE_OVERRIDE",TEXT(YEAR($D$4),"0000")&TEXT(MONTH($D$4),"00")&TEXT(DAY($D$4),"00")) | M18: =_xll.BDP($A18,"BEST_EPS","BEST_FPERIOD_OVERRIDE","1BF","BEST_DATA_DATE_OVERRIDE",TEXT(YEAR($E$4),"0000")&TEXT(MONTH($E$4),"00")&TEXT(DAY($E$4),"00")) | N18: =_xll.BDP($A18,"BEST_EPS","BEST_FPERIOD_OVERRIDE","1BF","BEST_DATA_DATE_OVERRIDE",TEXT(YEAR($F$4),"0000")&TEXT(MONTH($F$4),"00")&TEXT(DAY($F$4),"00")) | O18: =IFERROR(IF(AND(ISNUMBER($K18),ISNUMBER(L18),L18<>0),$K18/L18-1,""),"") | P18: =IFERROR(IF(AND(ISNUMBER($K18),ISNUMBER(M18),M18<>0),$K18/M18-1,""),"") | Q18: =IFERROR(IF(AND(ISNUMBER($K18),ISNUMBER(N18),N18<>0),$K18/N18-1,""),"")
A19: =Tickers!$A$18 | C19: =_xll.BDP($A19,"BEST_SALES","BEST_FPERIOD_OVERRIDE","1BF") | D19: =_xll.BDP($A19,"BEST_SALES","BEST_FPERIOD_OVERRIDE","1BF","BEST_DATA_DATE_OVERRIDE",TEXT(YEAR($D$4),"0000")&TEXT(MONTH($D$4),"00")&TEXT(DAY($D$4),"00")) | E19: =_xll.BDP($A19,"BEST_SALES","BEST_FPERIOD_OVERRIDE","1BF","BEST_DATA_DATE_OVERRIDE",TEXT(YEAR($E$4),"0000")&TEXT(MONTH($E$4),"00")&TEXT(DAY($E$4),"00")) | F19: =_xll.BDP($A19,"BEST_SALES","BEST_FPERIOD_OVERRIDE","1BF","BEST_DATA_DATE_OVERRIDE",TEXT(YEAR($F$4),"0000")&TEXT(MONTH($F$4),"00")&TEXT(DAY($F$4),"00")) | G19: =IFERROR(IF(AND(ISNUMBER($C19),ISNUMBER(D19),D19<>0),$C19/D19-1,""),"") | H19: =IFERROR(IF(AND(ISNUMBER($C19),ISNUMBER(E19),E19<>0),$C19/E19-1,""),"") | I19: =IFERROR(IF(AND(ISNUMBER($C19),ISNUMBER(F19),F19<>0),$C19/F19-1,""),"") | K19: =_xll.BDP($A19,"BEST_EPS","BEST_FPERIOD_OVERRIDE","1BF") | L19: =_xll.BDP($A19,"BEST_EPS","BEST_FPERIOD_OVERRIDE","1BF","BEST_DATA_DATE_OVERRIDE",TEXT(YEAR($D$4),"0000")&TEXT(MONTH($D$4),"00")&TEXT(DAY($D$4),"00")) | M19: =_xll.BDP($A19,"BEST_EPS","BEST_FPERIOD_OVERRIDE","1BF","BEST_DATA_DATE_OVERRIDE",TEXT(YEAR($E$4),"0000")&TEXT(MONTH($E$4),"00")&TEXT(DAY($E$4),"00")) | N19: =_xll.BDP($A19,"BEST_EPS","BEST_FPERIOD_OVERRIDE","1BF","BEST_DATA_DATE_OVERRIDE",TEXT(YEAR($F$4),"0000")&TEXT(MONTH($F$4),"00")&TEXT(DAY($F$4),"00")) | O19: =IFERROR(IF(AND(ISNUMBER($K19),ISNUMBER(L19),L19<>0),$K19/L19-1,""),"") | P19: =IFERROR(IF(AND(ISNUMBER($K19),ISNUMBER(M19),M19<>0),$K19/M19-1,""),"") | Q19: =IFERROR(IF(AND(ISNUMBER($K19),ISNUMBER(N19),N19<>0),$K19/N19-1,""),"")
A20: =Tickers!$A$19 | C20: =_xll.BDP($A20,"BEST_SALES","BEST_FPERIOD_OVERRIDE","1BF") | D20: =_xll.BDP($A20,"BEST_SALES","BEST_FPERIOD_OVERRIDE","1BF","BEST_DATA_DATE_OVERRIDE",TEXT(YEAR($D$4),"0000")&TEXT(MONTH($D$4),"00")&TEXT(DAY($D$4),"00")) | E20: =_xll.BDP($A20,"BEST_SALES","BEST_FPERIOD_OVERRIDE","1BF","BEST_DATA_DATE_OVERRIDE",TEXT(YEAR($E$4),"0000")&TEXT(MONTH($E$4),"00")&TEXT(DAY($E$4),"00")) | F20: =_xll.BDP($A20,"BEST_SALES","BEST_FPERIOD_OVERRIDE","1BF","BEST_DATA_DATE_OVERRIDE",TEXT(YEAR($F$4),"0000")&TEXT(MONTH($F$4),"00")&TEXT(DAY($F$4),"00")) | G20: =IFERROR(IF(AND(ISNUMBER($C20),ISNUMBER(D20),D20<>0),$C20/D20-1,""),"") | H20: =IFERROR(IF(AND(ISNUMBER($C20),ISNUMBER(E20),E20<>0),$C20/E20-1,""),"") | I20: =IFERROR(IF(AND(ISNUMBER($C20),ISNUMBER(F20),F20<>0),$C20/F20-1,""),"") | K20: =_xll.BDP($A20,"BEST_EPS","BEST_FPERIOD_OVERRIDE","1BF") | L20: =_xll.BDP($A20,"BEST_EPS","BEST_FPERIOD_OVERRIDE","1BF","BEST_DATA_DATE_OVERRIDE",TEXT(YEAR($D$4),"0000")&TEXT(MONTH($D$4),"00")&TEXT(DAY($D$4),"00")) | M20: =_xll.BDP($A20,"BEST_EPS","BEST_FPERIOD_OVERRIDE","1BF","BEST_DATA_DATE_OVERRIDE",TEXT(YEAR($E$4),"0000")&TEXT(MONTH($E$4),"00")&TEXT(DAY($E$4),"00")) | N20: =_xll.BDP($A20,"BEST_EPS","BEST_FPERIOD_OVERRIDE","1BF","BEST_DATA_DATE_OVERRIDE",TEXT(YEAR($F$4),"0000")&TEXT(MONTH($F$4),"00")&TEXT(DAY($F$4),"00")) | O20: =IFERROR(IF(AND(ISNUMBER($K20),ISNUMBER(L20),L20<>0),$K20/L20-1,""),"") | P20: =IFERROR(IF(AND(ISNUMBER($K20),ISNUMBER(M20),M20<>0),$K20/M20-1,""),"") | Q20: =IFERROR(IF(AND(ISNUMBER($K20),ISNUMBER(N20),N20<>0),$K20/N20-1,""),"")
A21: =Tickers!$A$20 | C21: =_xll.BDP($A21,"BEST_SALES","BEST_FPERIOD_OVERRIDE","1BF") | D21: =_xll.BDP($A21,"BEST_SALES","BEST_FPERIOD_OVERRIDE","1BF","BEST_DATA_DATE_OVERRIDE",TEXT(YEAR($D$4),"0000")&TEXT(MONTH($D$4),"00")&TEXT(DAY($D$4),"00")) | E21: =_xll.BDP($A21,"BEST_SALES","BEST_FPERIOD_OVERRIDE","1BF","BEST_DATA_DATE_OVERRIDE",TEXT(YEAR($E$4),"0000")&TEXT(MONTH($E$4),"00")&TEXT(DAY($E$4),"00")) | F21: =_xll.BDP($A21,"BEST_SALES","BEST_FPERIOD_OVERRIDE","1BF","BEST_DATA_DATE_OVERRIDE",TEXT(YEAR($F$4),"0000")&TEXT(MONTH($F$4),"00")&TEXT(DAY($F$4),"00")) | G21: =IFERROR(IF(AND(ISNUMBER($C21),ISNUMBER(D21),D21<>0),$C21/D21-1,""),"") | H21: =IFERROR(IF(AND(ISNUMBER($C21),ISNUMBER(E21),E21<>0),$C21/E21-1,""),"") | I21: =IFERROR(IF(AND(ISNUMBER($C21),ISNUMBER(F21),F21<>0),$C21/F21-1,""),"") | K21: =_xll.BDP($A21,"BEST_EPS","BEST_FPERIOD_OVERRIDE","1BF") | L21: =_xll.BDP($A21,"BEST_EPS","BEST_FPERIOD_OVERRIDE","1BF","BEST_DATA_DATE_OVERRIDE",TEXT(YEAR($D$4),"0000")&TEXT(MONTH($D$4),"00")&TEXT(DAY($D$4),"00")) | M21: =_xll.BDP($A21,"BEST_EPS","BEST_FPERIOD_OVERRIDE","1BF","BEST_DATA_DATE_OVERRIDE",TEXT(YEAR($E$4),"0000")&TEXT(MONTH($E$4),"00")&TEXT(DAY($E$4),"00")) | N21: =_xll.BDP($A21,"BEST_EPS","BEST_FPERIOD_OVERRIDE","1BF","BEST_DATA_DATE_OVERRIDE",TEXT(YEAR($F$4),"0000")&TEXT(MONTH($F$4),"00")&TEXT(DAY($F$4),"00")) | O21: =IFERROR(IF(AND(ISNUMBER($K21),ISNUMBER(L21),L21<>0),$K21/L21-1,""),"") | P21: =IFERROR(IF(AND(ISNUMBER($K21),ISNUMBER(M21),M21<>0),$K21/M21-1,""),"") | Q21: =IFERROR(IF(AND(ISNUMBER($K21),ISNUMBER(N21),N21<>0),$K21/N21-1,""),"")
A22: =Tickers!$A$21 | C22: =_xll.BDP($A22,"BEST_SALES","BEST_FPERIOD_OVERRIDE","1BF") | D22: =_xll.BDP($A22,"BEST_SALES","BEST_FPERIOD_OVERRIDE","1BF","BEST_DATA_DATE_OVERRIDE",TEXT(YEAR($D$4),"0000")&TEXT(MONTH($D$4),"00")&TEXT(DAY($D$4),"00")) | E22: =_xll.BDP($A22,"BEST_SALES","BEST_FPERIOD_OVERRIDE","1BF","BEST_DATA_DATE_OVERRIDE",TEXT(YEAR($E$4),"0000")&TEXT(MONTH($E$4),"00")&TEXT(DAY($E$4),"00")) | F22: =_xll.BDP($A22,"BEST_SALES","BEST_FPERIOD_OVERRIDE","1BF","BEST_DATA_DATE_OVERRIDE",TEXT(YEAR($F$4),"0000")&TEXT(MONTH($F$4),"00")&TEXT(DAY($F$4),"00")) | G22: =IFERROR(IF(AND(ISNUMBER($C22),ISNUMBER(D22),D22<>0),$C22/D22-1,""),"") | H22: =IFERROR(IF(AND(ISNUMBER($C22),ISNUMBER(E22),E22<>0),$C22/E22-1,""),"") | I22: =IFERROR(IF(AND(ISNUMBER($C22),ISNUMBER(F22),F22<>0),$C22/F22-1,""),"") | K22: =_xll.BDP($A22,"BEST_EPS","BEST_FPERIOD_OVERRIDE","1BF") | L22: =_xll.BDP($A22,"BEST_EPS","BEST_FPERIOD_OVERRIDE","1BF","BEST_DATA_DATE_OVERRIDE",TEXT(YEAR($D$4),"0000")&TEXT(MONTH($D$4),"00")&TEXT(DAY($D$4),"00")) | M22: =_xll.BDP($A22,"BEST_EPS","BEST_FPERIOD_OVERRIDE","1BF","BEST_DATA_DATE_OVERRIDE",TEXT(YEAR($E$4),"0000")&TEXT(MONTH($E$4),"00")&TEXT(DAY($E$4),"00")) | N22: =_xll.BDP($A22,"BEST_EPS","BEST_FPERIOD_OVERRIDE","1BF","BEST_DATA_DATE_OVERRIDE",TEXT(YEAR($F$4),"0000")&TEXT(MONTH($F$4),"00")&TEXT(DAY($F$4),"00")) | O22: =IFERROR(IF(AND(ISNUMBER($K22),ISNUMBER(L22),L22<>0),$K22/L22-1,""),"") | P22: =IFERROR(IF(AND(ISNUMBER($K22),ISNUMBER(M22),M22<>0),$K22/M22-1,""),"") | Q22: =IFERROR(IF(AND(ISNUMBER($K22),ISNUMBER(N22),N22<>0),$K22/N22-1,""),"")
A23: =Tickers!$A$22 | C23: =_xll.BDP($A23,"BEST_SALES","BEST_FPERIOD_OVERRIDE","1BF") | D23: =_xll.BDP($A23,"BEST_SALES","BEST_FPERIOD_OVERRIDE","1BF","BEST_DATA_DATE_OVERRIDE",TEXT(YEAR($D$4),"0000")&TEXT(MONTH($D$4),"00")&TEXT(DAY($D$4),"00")) | E23: =_xll.BDP($A23,"BEST_SALES","BEST_FPERIOD_OVERRIDE","1BF","BEST_DATA_DATE_OVERRIDE",TEXT(YEAR($E$4),"0000")&TEXT(MONTH($E$4),"00")&TEXT(DAY($E$4),"00")) | F23: =_xll.BDP($A23,"BEST_SALES","BEST_FPERIOD_OVERRIDE","1BF","BEST_DATA_DATE_OVERRIDE",TEXT(YEAR($F$4),"0000")&TEXT(MONTH($F$4),"00")&TEXT(DAY($F$4),"00")) | G23: =IFERROR(IF(AND(ISNUMBER($C23),ISNUMBER(D23),D23<>0),$C23/D23-1,""),"") | H23: =IFERROR(IF(AND(ISNUMBER($C23),ISNUMBER(E23),E23<>0),$C23/E23-1,""),"") | I23: =IFERROR(IF(AND(ISNUMBER($C23),ISNUMBER(F23),F23<>0),$C23/F23-1,""),"") | K23: =_xll.BDP($A23,"BEST_EPS","BEST_FPERIOD_OVERRIDE","1BF") | L23: =_xll.BDP($A23,"BEST_EPS","BEST_FPERIOD_OVERRIDE","1BF","BEST_DATA_DATE_OVERRIDE",TEXT(YEAR($D$4),"0000")&TEXT(MONTH($D$4),"00")&TEXT(DAY($D$4),"00")) | M23: =_xll.BDP($A23,"BEST_EPS","BEST_FPERIOD_OVERRIDE","1BF","BEST_DATA_DATE_OVERRIDE",TEXT(YEAR($E$4),"0000")&TEXT(MONTH($E$4),"00")&TEXT(DAY($E$4),"00")) | N23: =_xll.BDP($A23,"BEST_EPS","BEST_FPERIOD_OVERRIDE","1BF","BEST_DATA_DATE_OVERRIDE",TEXT(YEAR($F$4),"0000")&TEXT(MONTH($F$4),"00")&TEXT(DAY($F$4),"00")) | O23: =IFERROR(IF(AND(ISNUMBER($K23),ISNUMBER(L23),L23<>0),$K23/L23-1,""),"") | P23: =IFERROR(IF(AND(ISNUMBER($K23),ISNUMBER(M23),M23<>0),$K23/M23-1,""),"") | Q23: =IFERROR(IF(AND(ISNUMBER($K23),ISNUMBER(N23),N23<>0),$K23/N23-1,""),"")
A24: =Tickers!$A$23 | C24: =_xll.BDP($A24,"BEST_SALES","BEST_FPERIOD_OVERRIDE","1BF") | D24: =_xll.BDP($A24,"BEST_SALES","BEST_FPERIOD_OVERRIDE","1BF","BEST_DATA_DATE_OVERRIDE",TEXT(YEAR($D$4),"0000")&TEXT(MONTH($D$4),"00")&TEXT(DAY($D$4),"00")) | E24: =_xll.BDP($A24,"BEST_SALES","BEST_FPERIOD_OVERRIDE","1BF","BEST_DATA_DATE_OVERRIDE",TEXT(YEAR($E$4),"0000")&TEXT(MONTH($E$4),"00")&TEXT(DAY($E$4),"00")) | F24: =_xll.BDP($A24,"BEST_SALES","BEST_FPERIOD_OVERRIDE","1BF","BEST_DATA_DATE_OVERRIDE",TEXT(YEAR($F$4),"0000")&TEXT(MONTH($F$4),"00")&TEXT(DAY($F$4),"00")) | G24: =IFERROR(IF(AND(ISNUMBER($C24),ISNUMBER(D24),D24<>0),$C24/D24-1,""),"") | H24: =IFERROR(IF(AND(ISNUMBER($C24),ISNUMBER(E24),E24<>0),$C24/E24-1,""),"") | I24: =IFERROR(IF(AND(ISNUMBER($C24),ISNUMBER(F24),F24<>0),$C24/F24-1,""),"") | K24: =_xll.BDP($A24,"BEST_EPS","BEST_FPERIOD_OVERRIDE","1BF") | L24: =_xll.BDP($A24,"BEST_EPS","BEST_FPERIOD_OVERRIDE","1BF","BEST_DATA_DATE_OVERRIDE",TEXT(YEAR($D$4),"0000")&TEXT(MONTH($D$4),"00")&TEXT(DAY($D$4),"00")) | M24: =_xll.BDP($A24,"BEST_EPS","BEST_FPERIOD_OVERRIDE","1BF","BEST_DATA_DATE_OVERRIDE",TEXT(YEAR($E$4),"0000")&TEXT(MONTH($E$4),"00")&TEXT(DAY($E$4),"00")) | N24: =_xll.BDP($A24,"BEST_EPS","BEST_FPERIOD_OVERRIDE","1BF","BEST_DATA_DATE_OVERRIDE",TEXT(YEAR($F$4),"0000")&TEXT(MONTH($F$4),"00")&TEXT(DAY($F$4),"00")) | O24: =IFERROR(IF(AND(ISNUMBER($K24),ISNUMBER(L24),L24<>0),$K24/L24-1,""),"") | P24: =IFERROR(IF(AND(ISNUMBER($K24),ISNUMBER(M24),M24<>0),$K24/M24-1,""),"") | Q24: =IFERROR(IF(AND(ISNUMBER($K24),ISNUMBER(N24),N24<>0),$K24/N24-1,""),"")
A25: =Tickers!$A$24 | C25: =_xll.BDP($A25,"BEST_SALES","BEST_FPERIOD_OVERRIDE","1BF") | D25: =_xll.BDP($A25,"BEST_SALES","BEST_FPERIOD_OVERRIDE","1BF","BEST_DATA_DATE_OVERRIDE",TEXT(YEAR($D$4),"0000")&TEXT(MONTH($D$4),"00")&TEXT(DAY($D$4),"00")) | E25: =_xll.BDP($A25,"BEST_SALES","BEST_FPERIOD_OVERRIDE","1BF","BEST_DATA_DATE_OVERRIDE",TEXT(YEAR($E$4),"0000")&TEXT(MONTH($E$4),"00")&TEXT(DAY($E$4),"00")) | F25: =_xll.BDP($A25,"BEST_SALES","BEST_FPERIOD_OVERRIDE","1BF","BEST_DATA_DATE_OVERRIDE",TEXT(YEAR($F$4),"0000")&TEXT(MONTH($F$4),"00")&TEXT(DAY($F$4),"00")) | G25: =IFERROR(IF(AND(ISNUMBER($C25),ISNUMBER(D25),D25<>0),$C25/D25-1,""),"") | H25: =IFERROR(IF(AND(ISNUMBER($C25),ISNUMBER(E25),E25<>0),$C25/E25-1,""),"") | I25: =IFERROR(IF(AND(ISNUMBER($C25),ISNUMBER(F25),F25<>0),$C25/F25-1,""),"") | K25: =_xll.BDP($A25,"BEST_EPS","BEST_FPERIOD_OVERRIDE","1BF") | L25: =_xll.BDP($A25,"BEST_EPS","BEST_FPERIOD_OVERRIDE","1BF","BEST_DATA_DATE_OVERRIDE",TEXT(YEAR($D$4),"0000")&TEXT(MONTH($D$4),"00")&TEXT(DAY($D$4),"00")) | M25: =_xll.BDP($A25,"BEST_EPS","BEST_FPERIOD_OVERRIDE","1BF","BEST_DATA_DATE_OVERRIDE",TEXT(YEAR($E$4),"0000")&TEXT(MONTH($E$4),"00")&TEXT(DAY($E$4),"00")) | N25: =_xll.BDP($A25,"BEST_EPS","BEST_FPERIOD_OVERRIDE","1BF","BEST_DATA_DATE_OVERRIDE",TEXT(YEAR($F$4),"0000")&TEXT(MONTH($F$4),"00")&TEXT(DAY($F$4),"00")) | O25: =IFERROR(IF(AND(ISNUMBER($K25),ISNUMBER(L25),L25<>0),$K25/L25-1,""),"") | P25: =IFERROR(IF(AND(ISNUMBER($K25),ISNUMBER(M25),M25<>0),$K25/M25-1,""),"") | Q25: =IFERROR(IF(AND(ISNUMBER($K25),ISNUMBER(N25),N25<>0),$K25/N25-1,""),"")
A26: =Tickers!$A$25 | C26: =_xll.BDP($A26,"BEST_SALES","BEST_FPERIOD_OVERRIDE","1BF") | D26: =_xll.BDP($A26,"BEST_SALES","BEST_FPERIOD_OVERRIDE","1BF","BEST_DATA_DATE_OVERRIDE",TEXT(YEAR($D$4),"0000")&TEXT(MONTH($D$4),"00")&TEXT(DAY($D$4),"00")) | E26: =_xll.BDP($A26,"BEST_SALES","BEST_FPERIOD_OVERRIDE","1BF","BEST_DATA_DATE_OVERRIDE",TEXT(YEAR($E$4),"0000")&TEXT(MONTH($E$4),"00")&TEXT(DAY($E$4),"00")) | F26: =_xll.BDP($A26,"BEST_SALES","BEST_FPERIOD_OVERRIDE","1BF","BEST_DATA_DATE_OVERRIDE",TEXT(YEAR($F$4),"0000")&TEXT(MONTH($F$4),"00")&TEXT(DAY($F$4),"00")) | G26: =IFERROR(IF(AND(ISNUMBER($C26),ISNUMBER(D26),D26<>0),$C26/D26-1,""),"") | H26: =IFERROR(IF(AND(ISNUMBER($C26),ISNUMBER(E26),E26<>0),$C26/E26-1,""),"") | I26: =IFERROR(IF(AND(ISNUMBER($C26),ISNUMBER(F26),F26<>0),$C26/F26-1,""),"") | K26: =_xll.BDP($A26,"BEST_EPS","BEST_FPERIOD_OVERRIDE","1BF") | L26: =_xll.BDP($A26,"BEST_EPS","BEST_FPERIOD_OVERRIDE","1BF","BEST_DATA_DATE_OVERRIDE",TEXT(YEAR($D$4),"0000")&TEXT(MONTH($D$4),"00")&TEXT(DAY($D$4),"00")) | M26: =_xll.BDP($A26,"BEST_EPS","BEST_FPERIOD_OVERRIDE","1BF","BEST_DATA_DATE_OVERRIDE",TEXT(YEAR($E$4),"0000")&TEXT(MONTH($E$4),"00")&TEXT(DAY($E$4),"00")) | N26: =_xll.BDP($A26,"BEST_EPS","BEST_FPERIOD_OVERRIDE","1BF","BEST_DATA_DATE_OVERRIDE",TEXT(YEAR($F$4),"0000")&TEXT(MONTH($F$4),"00")&TEXT(DAY($F$4),"00")) | O26: =IFERROR(IF(AND(ISNUMBER($K26),ISNUMBER(L26),L26<>0),$K26/L26-1,""),"") | P26: =IFERROR(IF(AND(ISNUMBER($K26),ISNUMBER(M26),M26<>0),$K26/M26-1,""),"") | Q26: =IFERROR(IF(AND(ISNUMBER($K26),ISNUMBER(N26),N26<>0),$K26/N26-1,""),"")
A27: =Tickers!$A$26 | C27: =_xll.BDP($A27,"BEST_SALES","BEST_FPERIOD_OVERRIDE","1BF") | D27: =_xll.BDP($A27,"BEST_SALES","BEST_FPERIOD_OVERRIDE","1BF","BEST_DATA_DATE_OVERRIDE",TEXT(YEAR($D$4),"0000")&TEXT(MONTH($D$4),"00")&TEXT(DAY($D$4),"00")) | E27: =_xll.BDP($A27,"BEST_SALES","BEST_FPERIOD_OVERRIDE","1BF","BEST_DATA_DATE_OVERRIDE",TEXT(YEAR($E$4),"0000")&TEXT(MONTH($E$4),"00")&TEXT(DAY($E$4),"00")) | F27: =_xll.BDP($A27,"BEST_SALES","BEST_FPERIOD_OVERRIDE","1BF","BEST_DATA_DATE_OVERRIDE",TEXT(YEAR($F$4),"0000")&TEXT(MONTH($F$4),"00")&TEXT(DAY($F$4),"00")) | G27: =IFERROR(IF(AND(ISNUMBER($C27),ISNUMBER(D27),D27<>0),$C27/D27-1,""),"") | H27: =IFERROR(IF(AND(ISNUMBER($C27),ISNUMBER(E27),E27<>0),$C27/E27-1,""),"") | I27: =IFERROR(IF(AND(ISNUMBER($C27),ISNUMBER(F27),F27<>0),$C27/F27-1,""),"") | K27: =_xll.BDP($A27,"BEST_EPS","BEST_FPERIOD_OVERRIDE","1BF") | L27: =_xll.BDP($A27,"BEST_EPS","BEST_FPERIOD_OVERRIDE","1BF","BEST_DATA_DATE_OVERRIDE",TEXT(YEAR($D$4),"0000")&TEXT(MONTH($D$4),"00")&TEXT(DAY($D$4),"00")) | M27: =_xll.BDP($A27,"BEST_EPS","BEST_FPERIOD_OVERRIDE","1BF","BEST_DATA_DATE_OVERRIDE",TEXT(YEAR($E$4),"0000")&TEXT(MONTH($E$4),"00")&TEXT(DAY($E$4),"00")) | N27: =_xll.BDP($A27,"BEST_EPS","BEST_FPERIOD_OVERRIDE","1BF","BEST_DATA_DATE_OVERRIDE",TEXT(YEAR($F$4),"0000")&TEXT(MONTH($F$4),"00")&TEXT(DAY($F$4),"00")) | O27: =IFERROR(IF(AND(ISNUMBER($K27),ISNUMBER(L27),L27<>0),$K27/L27-1,""),"") | P27: =IFERROR(IF(AND(ISNUMBER($K27),ISNUMBER(M27),M27<>0),$K27/M27-1,""),"") | Q27: =IFERROR(IF(AND(ISNUMBER($K27),ISNUMBER(N27),N27<>0),$K27/N27-1,""),"")
A28: =Tickers!$A$27 | C28: =_xll.BDP($A28,"BEST_SALES","BEST_FPERIOD_OVERRIDE","1BF") | D28: =_xll.BDP($A28,"BEST_SALES","BEST_FPERIOD_OVERRIDE","1BF","BEST_DATA_DATE_OVERRIDE",TEXT(YEAR($D$4),"0000")&TEXT(MONTH($D$4),"00")&TEXT(DAY($D$4),"00")) | E28: =_xll.BDP($A28,"BEST_SALES","BEST_FPERIOD_OVERRIDE","1BF","BEST_DATA_DATE_OVERRIDE",TEXT(YEAR($E$4),"0000")&TEXT(MONTH($E$4),"00")&TEXT(DAY($E$4),"00")) | F28: =_xll.BDP($A28,"BEST_SALES","BEST_FPERIOD_OVERRIDE","1BF","BEST_DATA_DATE_OVERRIDE",TEXT(YEAR($F$4),"0000")&TEXT(MONTH($F$4),"00")&TEXT(DAY($F$4),"00")) | G28: =IFERROR(IF(AND(ISNUMBER($C28),ISNUMBER(D28),D28<>0),$C28/D28-1,""),"") | H28: =IFERROR(IF(AND(ISNUMBER($C28),ISNUMBER(E28),E28<>0),$C28/E28-1,""),"") | I28: =IFERROR(IF(AND(ISNUMBER($C28),ISNUMBER(F28),F28<>0),$C28/F28-1,""),"") | K28: =_xll.BDP($A28,"BEST_EPS","BEST_FPERIOD_OVERRIDE","1BF") | L28: =_xll.BDP($A28,"BEST_EPS","BEST_FPERIOD_OVERRIDE","1BF","BEST_DATA_DATE_OVERRIDE",TEXT(YEAR($D$4),"0000")&TEXT(MONTH($D$4),"00")&TEXT(DAY($D$4),"00")) | M28: =_xll.BDP($A28,"BEST_EPS","BEST_FPERIOD_OVERRIDE","1BF","BEST_DATA_DATE_OVERRIDE",TEXT(YEAR($E$4),"0000")&TEXT(MONTH($E$4),"00")&TEXT(DAY($E$4),"00")) | N28: =_xll.BDP($A28,"BEST_EPS","BEST_FPERIOD_OVERRIDE","1BF","BEST_DATA_DATE_OVERRIDE",TEXT(YEAR($F$4),"0000")&TEXT(MONTH($F$4),"00")&TEXT(DAY($F$4),"00")) | O28: =IFERROR(IF(AND(ISNUMBER($K28),ISNUMBER(L28),L28<>0),$K28/L28-1,""),"") | P28: =IFERROR(IF(AND(ISNUMBER($K28),ISNUMBER(M28),M28<>0),$K28/M28-1,""),"") | Q28: =IFERROR(IF(AND(ISNUMBER($K28),ISNUMBER(N28),N28<>0),$K28/N28-1,""),"")
A29: =Tickers!$A$28 | C29: =_xll.BDP($A29,"BEST_SALES","BEST_FPERIOD_OVERRIDE","1BF") | D29: =_xll.BDP($A29,"BEST_SALES","BEST_FPERIOD_OVERRIDE","1BF","BEST_DATA_DATE_OVERRIDE",TEXT(YEAR($D$4),"0000")&TEXT(MONTH($D$4),"00")&TEXT(DAY($D$4),"00")) | E29: =_xll.BDP($A29,"BEST_SALES","BEST_FPERIOD_OVERRIDE","1BF","BEST_DATA_DATE_OVERRIDE",TEXT(YEAR($E$4),"0000")&TEXT(MONTH($E$4),"00")&TEXT(DAY($E$4),"00")) | F29: =_xll.BDP($A29,"BEST_SALES","BEST_FPERIOD_OVERRIDE","1BF","BEST_DATA_DATE_OVERRIDE",TEXT(YEAR($F$4),"0000")&TEXT(MONTH($F$4),"00")&TEXT(DAY($F$4),"00")) | G29: =IFERROR(IF(AND(ISNUMBER($C29),ISNUMBER(D29),D29<>0),$C29/D29-1,""),"") | H29: =IFERROR(IF(AND(ISNUMBER($C29),ISNUMBER(E29),E29<>0),$C29/E29-1,""),"") | I29: =IFERROR(IF(AND(ISNUMBER($C29),ISNUMBER(F29),F29<>0),$C29/F29-1,""),"") | K29: =_xll.BDP($A29,"BEST_EPS","BEST_FPERIOD_OVERRIDE","1BF") | L29: =_xll.BDP($A29,"BEST_EPS","BEST_FPERIOD_OVERRIDE","1BF","BEST_DATA_DATE_OVERRIDE",TEXT(YEAR($D$4),"0000")&TEXT(MONTH($D$4),"00")&TEXT(DAY($D$4),"00")) | M29: =_xll.BDP($A29,"BEST_EPS","BEST_FPERIOD_OVERRIDE","1BF","BEST_DATA_DATE_OVERRIDE",TEXT(YEAR($E$4),"0000")&TEXT(MONTH($E$4),"00")&TEXT(DAY($E$4),"00")) | N29: =_xll.BDP($A29,"BEST_EPS","BEST_FPERIOD_OVERRIDE","1BF","BEST_DATA_DATE_OVERRIDE",TEXT(YEAR($F$4),"0000")&TEXT(MONTH($F$4),"00")&TEXT(DAY($F$4),"00")) | O29: =IFERROR(IF(AND(ISNUMBER($K29),ISNUMBER(L29),L29<>0),$K29/L29-1,""),"") | P29: =IFERROR(IF(AND(ISNUMBER($K29),ISNUMBER(M29),M29<>0),$K29/M29-1,""),"") | Q29: =IFERROR(IF(AND(ISNUMBER($K29),ISNUMBER(N29),N29<>0),$K29/N29-1,""),"")
A30: =Tickers!$A$29 | C30: =_xll.BDP($A30,"BEST_SALES","BEST_FPERIOD_OVERRIDE","1BF") | D30: =_xll.BDP($A30,"BEST_SALES","BEST_FPERIOD_OVERRIDE","1BF","BEST_DATA_DATE_OVERRIDE",TEXT(YEAR($D$4),"0000")&TEXT(MONTH($D$4),"00")&TEXT(DAY($D$4),"00")) | E30: =_xll.BDP($A30,"BEST_SALES","BEST_FPERIOD_OVERRIDE","1BF","BEST_DATA_DATE_OVERRIDE",TEXT(YEAR($E$4),"0000")&TEXT(MONTH($E$4),"00")&TEXT(DAY($E$4),"00")) | F30: =_xll.BDP($A30,"BEST_SALES","BEST_FPERIOD_OVERRIDE","1BF","BEST_DATA_DATE_OVERRIDE",TEXT(YEAR($F$4),"0000")&TEXT(MONTH($F$4),"00")&TEXT(DAY($F$4),"00")) | G30: =IFERROR(IF(AND(ISNUMBER($C30),ISNUMBER(D30),D30<>0),$C30/D30-1,""),"") | H30: =IFERROR(IF(AND(ISNUMBER($C30),ISNUMBER(E30),E30<>0),$C30/E30-1,""),"") | I30: =IFERROR(IF(AND(ISNUMBER($C30),ISNUMBER(F30),F30<>0),$C30/F30-1,""),"") | K30: =_xll.BDP($A30,"BEST_EPS","BEST_FPERIOD_OVERRIDE","1BF") | L30: =_xll.BDP($A30,"BEST_EPS","BEST_FPERIOD_OVERRIDE","1BF","BEST_DATA_DATE_OVERRIDE",TEXT(YEAR($D$4),"0000")&TEXT(MONTH($D$4),"00")&TEXT(DAY($D$4),"00")) | M30: =_xll.BDP($A30,"BEST_EPS","BEST_FPERIOD_OVERRIDE","1BF","BEST_DATA_DATE_OVERRIDE",TEXT(YEAR($E$4),"0000")&TEXT(MONTH($E$4),"00")&TEXT(DAY($E$4),"00")) | N30: =_xll.BDP($A30,"BEST_EPS","BEST_FPERIOD_OVERRIDE","1BF","BEST_DATA_DATE_OVERRIDE",TEXT(YEAR($F$4),"0000")&TEXT(MONTH($F$4),"00")&TEXT(DAY($F$4),"00")) | O30: =IFERROR(IF(AND(ISNUMBER($K30),ISNUMBER(L30),L30<>0),$K30/L30-1,""),"") | P30: =IFERROR(IF(AND(ISNUMBER($K30),ISNUMBER(M30),M30<>0),$K30/M30-1,""),"") | Q30: =IFERROR(IF(AND(ISNUMBER($K30),ISNUMBER(N30),N30<>0),$K30/N30-1,""),"")
A31: =Tickers!$A$30 | C31: =_xll.BDP($A31,"BEST_SALES","BEST_FPERIOD_OVERRIDE","1BF") | D31: =_xll.BDP($A31,"BEST_SALES","BEST_FPERIOD_OVERRIDE","1BF","BEST_DATA_DATE_OVERRIDE",TEXT(YEAR($D$4),"0000")&TEXT(MONTH($D$4),"00")&TEXT(DAY($D$4),"00")) | E31: =_xll.BDP($A31,"BEST_SALES","BEST_FPERIOD_OVERRIDE","1BF","BEST_DATA_DATE_OVERRIDE",TEXT(YEAR($E$4),"0000")&TEXT(MONTH($E$4),"00")&TEXT(DAY($E$4),"00")) | F31: =_xll.BDP($A31,"BEST_SALES","BEST_FPERIOD_OVERRIDE","1BF","BEST_DATA_DATE_OVERRIDE",TEXT(YEAR($F$4),"0000")&TEXT(MONTH($F$4),"00")&TEXT(DAY($F$4),"00")) | G31: =IFERROR(IF(AND(ISNUMBER($C31),ISNUMBER(D31),D31<>0),$C31/D31-1,""),"") | H31: =IFERROR(IF(AND(ISNUMBER($C31),ISNUMBER(E31),E31<>0),$C31/E31-1,""),"") | I31: =IFERROR(IF(AND(ISNUMBER($C31),ISNUMBER(F31),F31<>0),$C31/F31-1,""),"") | K31: =_xll.BDP($A31,"BEST_EPS","BEST_FPERIOD_OVERRIDE","1BF") | L31: =_xll.BDP($A31,"BEST_EPS","BEST_FPERIOD_OVERRIDE","1BF","BEST_DATA_DATE_OVERRIDE",TEXT(YEAR($D$4),"0000")&TEXT(MONTH($D$4),"00")&TEXT(DAY($D$4),"00")) | M31: =_xll.BDP($A31,"BEST_EPS","BEST_FPERIOD_OVERRIDE","1BF","BEST_DATA_DATE_OVERRIDE",TEXT(YEAR($E$4),"0000")&TEXT(MONTH($E$4),"00")&TEXT(DAY($E$4),"00")) | N31: =_xll.BDP($A31,"BEST_EPS","BEST_FPERIOD_OVERRIDE","1BF","BEST_DATA_DATE_OVERRIDE",TEXT(YEAR($F$4),"0000")&TEXT(MONTH($F$4),"00")&TEXT(DAY($F$4),"00")) | O31: =IFERROR(IF(AND(ISNUMBER($K31),ISNUMBER(L31),L31<>0),$K31/L31-1,""),"") | P31: =IFERROR(IF(AND(ISNUMBER($K31),ISNUMBER(M31),M31<>0),$K31/M31-1,""),"") | Q31: =IFERROR(IF(AND(ISNUMBER($K31),ISNUMBER(N31),N31<>0),$K31/N31-1,""),"")
A32: =Tickers!$A$31 | C32: =_xll.BDP($A32,"BEST_SALES","BEST_FPERIOD_OVERRIDE","1BF") | D32: =_xll.BDP($A32,"BEST_SALES","BEST_FPERIOD_OVERRIDE","1BF","BEST_DATA_DATE_OVERRIDE",TEXT(YEAR($D$4),"0000")&TEXT(MONTH($D$4),"00")&TEXT(DAY($D$4),"00")) | E32: =_xll.BDP($A32,"BEST_SALES","BEST_FPERIOD_OVERRIDE","1BF","BEST_DATA_DATE_OVERRIDE",TEXT(YEAR($E$4),"0000")&TEXT(MONTH($E$4),"00")&TEXT(DAY($E$4),"00")) | F32: =_xll.BDP($A32,"BEST_SALES","BEST_FPERIOD_OVERRIDE","1BF","BEST_DATA_DATE_OVERRIDE",TEXT(YEAR($F$4),"0000")&TEXT(MONTH($F$4),"00")&TEXT(DAY($F$4),"00")) | G32: =IFERROR(IF(AND(ISNUMBER($C32),ISNUMBER(D32),D32<>0),$C32/D32-1,""),"") | H32: =IFERROR(IF(AND(ISNUMBER($C32),ISNUMBER(E32),E32<>0),$C32/E32-1,""),"") | I32: =IFERROR(IF(AND(ISNUMBER($C32),ISNUMBER(F32),F32<>0),$C32/F32-1,""),"") | K32: =_xll.BDP($A32,"BEST_EPS","BEST_FPERIOD_OVERRIDE","1BF") | L32: =_xll.BDP($A32,"BEST_EPS","BEST_FPERIOD_OVERRIDE","1BF","BEST_DATA_DATE_OVERRIDE",TEXT(YEAR($D$4),"0000")&TEXT(MONTH($D$4),"00")&TEXT(DAY($D$4),"00")) | M32: =_xll.BDP($A32,"BEST_EPS","BEST_FPERIOD_OVERRIDE","1BF","BEST_DATA_DATE_OVERRIDE",TEXT(YEAR($E$4),"0000")&TEXT(MONTH($E$4),"00")&TEXT(DAY($E$4),"00")) | N32: =_xll.BDP($A32,"BEST_EPS","BEST_FPERIOD_OVERRIDE","1BF","BEST_DATA_DATE_OVERRIDE",TEXT(YEAR($F$4),"0000")&TEXT(MONTH($F$4),"00")&TEXT(DAY($F$4),"00")) | O32: =IFERROR(IF(AND(ISNUMBER($K32),ISNUMBER(L32),L32<>0),$K32/L32-1,""),"") | P32: =IFERROR(IF(AND(ISNUMBER($K32),ISNUMBER(M32),M32<>0),$K32/M32-1,""),"") | Q32: =IFERROR(IF(AND(ISNUMBER($K32),ISNUMBER(N32),N32<>0),$K32/N32-1,""),"")
A33: =Tickers!$A$32 | C33: =_xll.BDP($A33,"BEST_SALES","BEST_FPERIOD_OVERRIDE","1BF") | D33: =_xll.BDP($A33,"BEST_SALES","BEST_FPERIOD_OVERRIDE","1BF","BEST_DATA_DATE_OVERRIDE",TEXT(YEAR($D$4),"0000")&TEXT(MONTH($D$4),"00")&TEXT(DAY($D$4),"00")) | E33: =_xll.BDP($A33,"BEST_SALES","BEST_FPERIOD_OVERRIDE","1BF","BEST_DATA_DATE_OVERRIDE",TEXT(YEAR($E$4),"0000")&TEXT(MONTH($E$4),"00")&TEXT(DAY($E$4),"00")) | F33: =_xll.BDP($A33,"BEST_SALES","BEST_FPERIOD_OVERRIDE","1BF","BEST_DATA_DATE_OVERRIDE",TEXT(YEAR($F$4),"0000")&TEXT(MONTH($F$4),"00")&TEXT(DAY($F$4),"00")) | G33: =IFERROR(IF(AND(ISNUMBER($C33),ISNUMBER(D33),D33<>0),$C33/D33-1,""),"") | H33: =IFERROR(IF(AND(ISNUMBER($C33),ISNUMBER(E33),E33<>0),$C33/E33-1,""),"") | I33: =IFERROR(IF(AND(ISNUMBER($C33),ISNUMBER(F33),F33<>0),$C33/F33-1,""),"") | K33: =_xll.BDP($A33,"BEST_EPS","BEST_FPERIOD_OVERRIDE","1BF") | L33: =_xll.BDP($A33,"BEST_EPS","BEST_FPERIOD_OVERRIDE","1BF","BEST_DATA_DATE_OVERRIDE",TEXT(YEAR($D$4),"0000")&TEXT(MONTH($D$4),"00")&TEXT(DAY($D$4),"00")) | M33: =_xll.BDP($A33,"BEST_EPS","BEST_FPERIOD_OVERRIDE","1BF","BEST_DATA_DATE_OVERRIDE",TEXT(YEAR($E$4),"0000")&TEXT(MONTH($E$4),"00")&TEXT(DAY($E$4),"00")) | N33: =_xll.BDP($A33,"BEST_EPS","BEST_FPERIOD_OVERRIDE","1BF","BEST_DATA_DATE_OVERRIDE",TEXT(YEAR($F$4),"0000")&TEXT(MONTH($F$4),"00")&TEXT(DAY($F$4),"00")) | O33: =IFERROR(IF(AND(ISNUMBER($K33),ISNUMBER(L33),L33<>0),$K33/L33-1,""),"") | P33: =IFERROR(IF(AND(ISNUMBER($K33),ISNUMBER(M33),M33<>0),$K33/M33-1,""),"") | Q33: =IFERROR(IF(AND(ISNUMBER($K33),ISNUMBER(N33),N33<>0),$K33/N33-1,""),"")
A34: =Tickers!$A$33 | C34: =_xll.BDP($A34,"BEST_SALES","BEST_FPERIOD_OVERRIDE","1BF") | D34: =_xll.BDP($A34,"BEST_SALES","BEST_FPERIOD_OVERRIDE","1BF","BEST_DATA_DATE_OVERRIDE",TEXT(YEAR($D$4),"0000")&TEXT(MONTH($D$4),"00")&TEXT(DAY($D$4),"00")) | E34: =_xll.BDP($A34,"BEST_SALES","BEST_FPERIOD_OVERRIDE","1BF","BEST_DATA_DATE_OVERRIDE",TEXT(YEAR($E$4),"0000")&TEXT(MONTH($E$4),"00")&TEXT(DAY($E$4),"00")) | F34: =_xll.BDP($A34,"BEST_SALES","BEST_FPERIOD_OVERRIDE","1BF","BEST_DATA_DATE_OVERRIDE",TEXT(YEAR($F$4),"0000")&TEXT(MONTH($F$4),"00")&TEXT(DAY($F$4),"00")) | G34: =IFERROR(IF(AND(ISNUMBER($C34),ISNUMBER(D34),D34<>0),$C34/D34-1,""),"") | H34: =IFERROR(IF(AND(ISNUMBER($C34),ISNUMBER(E34),E34<>0),$C34/E34-1,""),"") | I34: =IFERROR(IF(AND(ISNUMBER($C34),ISNUMBER(F34),F34<>0),$C34/F34-1,""),"") | K34: =_xll.BDP($A34,"BEST_EPS","BEST_FPERIOD_OVERRIDE","1BF") | L34: =_xll.BDP($A34,"BEST_EPS","BEST_FPERIOD_OVERRIDE","1BF","BEST_DATA_DATE_OVERRIDE",TEXT(YEAR($D$4),"0000")&TEXT(MONTH($D$4),"00")&TEXT(DAY($D$4),"00")) | M34: =_xll.BDP($A34,"BEST_EPS","BEST_FPERIOD_OVERRIDE","1BF","BEST_DATA_DATE_OVERRIDE",TEXT(YEAR($E$4),"0000")&TEXT(MONTH($E$4),"00")&TEXT(DAY($E$4),"00")) | N34: =_xll.BDP($A34,"BEST_EPS","BEST_FPERIOD_OVERRIDE","1BF","BEST_DATA_DATE_OVERRIDE",TEXT(YEAR($F$4),"0000")&TEXT(MONTH($F$4),"00")&TEXT(DAY($F$4),"00")) | O34: =IFERROR(IF(AND(ISNUMBER($K34),ISNUMBER(L34),L34<>0),$K34/L34-1,""),"") | P34: =IFERROR(IF(AND(ISNUMBER($K34),ISNUMBER(M34),M34<>0),$K34/M34-1,""),"") | Q34: =IFERROR(IF(AND(ISNUMBER($K34),ISNUMBER(N34),N34<>0),$K34/N34-1,""),"")
A35: =Tickers!$A$34 | C35: =_xll.BDP($A35,"BEST_SALES","BEST_FPERIOD_OVERRIDE","1BF") | D35: =_xll.BDP($A35,"BEST_SALES","BEST_FPERIOD_OVERRIDE","1BF","BEST_DATA_DATE_OVERRIDE",TEXT(YEAR($D$4),"0000")&TEXT(MONTH($D$4),"00")&TEXT(DAY($D$4),"00")) | E35: =_xll.BDP($A35,"BEST_SALES","BEST_FPERIOD_OVERRIDE","1BF","BEST_DATA_DATE_OVERRIDE",TEXT(YEAR($E$4),"0000")&TEXT(MONTH($E$4),"00")&TEXT(DAY($E$4),"00")) | F35: =_xll.BDP($A35,"BEST_SALES","BEST_FPERIOD_OVERRIDE","1BF","BEST_DATA_DATE_OVERRIDE",TEXT(YEAR($F$4),"0000")&TEXT(MONTH($F$4),"00")&TEXT(DAY($F$4),"00")) | G35: =IFERROR(IF(AND(ISNUMBER($C35),ISNUMBER(D35),D35<>0),$C35/D35-1,""),"") | H35: =IFERROR(IF(AND(ISNUMBER($C35),ISNUMBER(E35),E35<>0),$C35/E35-1,""),"") | I35: =IFERROR(IF(AND(ISNUMBER($C35),ISNUMBER(F35),F35<>0),$C35/F35-1,""),"") | K35: =_xll.BDP($A35,"BEST_EPS","BEST_FPERIOD_OVERRIDE","1BF") | L35: =_xll.BDP($A35,"BEST_EPS","BEST_FPERIOD_OVERRIDE","1BF","BEST_DATA_DATE_OVERRIDE",TEXT(YEAR($D$4),"0000")&TEXT(MONTH($D$4),"00")&TEXT(DAY($D$4),"00")) | M35: =_xll.BDP($A35,"BEST_EPS","BEST_FPERIOD_OVERRIDE","1BF","BEST_DATA_DATE_OVERRIDE",TEXT(YEAR($E$4),"0000")&TEXT(MONTH($E$4),"00")&TEXT(DAY($E$4),"00")) | N35: =_xll.BDP($A35,"BEST_EPS","BEST_FPERIOD_OVERRIDE","1BF","BEST_DATA_DATE_OVERRIDE",TEXT(YEAR($F$4),"0000")&TEXT(MONTH($F$4),"00")&TEXT(DAY($F$4),"00")) | O35: =IFERROR(IF(AND(ISNUMBER($K35),ISNUMBER(L35),L35<>0),$K35/L35-1,""),"") | P35: =IFERROR(IF(AND(ISNUMBER($K35),ISNUMBER(M35),M35<>0),$K35/M35-1,""),"") | Q35: =IFERROR(IF(AND(ISNUMBER($K35),ISNUMBER(N35),N35<>0),$K35/N35-1,""),"")
A36: =Tickers!$A$35 | C36: =_xll.BDP($A36,"BEST_SALES","BEST_FPERIOD_OVERRIDE","1BF") | D36: =_xll.BDP($A36,"BEST_SALES","BEST_FPERIOD_OVERRIDE","1BF","BEST_DATA_DATE_OVERRIDE",TEXT(YEAR($D$4),"0000")&TEXT(MONTH($D$4),"00")&TEXT(DAY($D$4),"00")) | E36: =_xll.BDP($A36,"BEST_SALES","BEST_FPERIOD_OVERRIDE","1BF","BEST_DATA_DATE_OVERRIDE",TEXT(YEAR($E$4),"0000")&TEXT(MONTH($E$4),"00")&TEXT(DAY($E$4),"00")) | F36: =_xll.BDP($A36,"BEST_SALES","BEST_FPERIOD_OVERRIDE","1BF","BEST_DATA_DATE_OVERRIDE",TEXT(YEAR($F$4),"0000")&TEXT(MONTH($F$4),"00")&TEXT(DAY($F$4),"00")) | G36: =IFERROR(IF(AND(ISNUMBER($C36),ISNUMBER(D36),D36<>0),$C36/D36-1,""),"") | H36: =IFERROR(IF(AND(ISNUMBER($C36),ISNUMBER(E36),E36<>0),$C36/E36-1,""),"") | I36: =IFERROR(IF(AND(ISNUMBER($C36),ISNUMBER(F36),F36<>0),$C36/F36-1,""),"") | K36: =_xll.BDP($A36,"BEST_EPS","BEST_FPERIOD_OVERRIDE","1BF") | L36: =_xll.BDP($A36,"BEST_EPS","BEST_FPERIOD_OVERRIDE","1BF","BEST_DATA_DATE_OVERRIDE",TEXT(YEAR($D$4),"0000")&TEXT(MONTH($D$4),"00")&TEXT(DAY($D$4),"00")) | M36: =_xll.BDP($A36,"BEST_EPS","BEST_FPERIOD_OVERRIDE","1BF","BEST_DATA_DATE_OVERRIDE",TEXT(YEAR($E$4),"0000")&TEXT(MONTH($E$4),"00")&TEXT(DAY($E$4),"00")) | N36: =_xll.BDP($A36,"BEST_EPS","BEST_FPERIOD_OVERRIDE","1BF","BEST_DATA_DATE_OVERRIDE",TEXT(YEAR($F$4),"0000")&TEXT(MONTH($F$4),"00")&TEXT(DAY($F$4),"00")) | O36: =IFERROR(IF(AND(ISNUMBER($K36),ISNUMBER(L36),L36<>0),$K36/L36-1,""),"") | P36: =IFERROR(IF(AND(ISNUMBER($K36),ISNUMBER(M36),M36<>0),$K36/M36-1,""),"") | Q36: =IFERROR(IF(AND(ISNUMBER($K36),ISNUMBER(N36),N36<>0),$K36/N36-1,""),"")
A37: =Tickers!$A$36 | C37: =_xll.BDP($A37,"BEST_SALES","BEST_FPERIOD_OVERRIDE","1BF") | D37: =_xll.BDP($A37,"BEST_SALES","BEST_FPERIOD_OVERRIDE","1BF","BEST_DATA_DATE_OVERRIDE",TEXT(YEAR($D$4),"0000")&TEXT(MONTH($D$4),"00")&TEXT(DAY($D$4),"00")) | E37: =_xll.BDP($A37,"BEST_SALES","BEST_FPERIOD_OVERRIDE","1BF","BEST_DATA_DATE_OVERRIDE",TEXT(YEAR($E$4),"0000")&TEXT(MONTH($E$4),"00")&TEXT(DAY($E$4),"00")) | F37: =_xll.BDP($A37,"BEST_SALES","BEST_FPERIOD_OVERRIDE","1BF","BEST_DATA_DATE_OVERRIDE",TEXT(YEAR($F$4),"0000")&TEXT(MONTH($F$4),"00")&TEXT(DAY($F$4),"00")) | G37: =IFERROR(IF(AND(ISNUMBER($C37),ISNUMBER(D37),D37<>0),$C37/D37-1,""),"") | H37: =IFERROR(IF(AND(ISNUMBER($C37),ISNUMBER(E37),E37<>0),$C37/E37-1,""),"") | I37: =IFERROR(IF(AND(ISNUMBER($C37),ISNUMBER(F37),F37<>0),$C37/F37-1,""),"") | K37: =_xll.BDP($A37,"BEST_EPS","BEST_FPERIOD_OVERRIDE","1BF") | L37: =_xll.BDP($A37,"BEST_EPS","BEST_FPERIOD_OVERRIDE","1BF","BEST_DATA_DATE_OVERRIDE",TEXT(YEAR($D$4),"0000")&TEXT(MONTH($D$4),"00")&TEXT(DAY($D$4),"00")) | M37: =_xll.BDP($A37,"BEST_EPS","BEST_FPERIOD_OVERRIDE","1BF","BEST_DATA_DATE_OVERRIDE",TEXT(YEAR($E$4),"0000")&TEXT(MONTH($E$4),"00")&TEXT(DAY($E$4),"00")) | N37: =_xll.BDP($A37,"BEST_EPS","BEST_FPERIOD_OVERRIDE","1BF","BEST_DATA_DATE_OVERRIDE",TEXT(YEAR($F$4),"0000")&TEXT(MONTH($F$4),"00")&TEXT(DAY($F$4),"00")) | O37: =IFERROR(IF(AND(ISNUMBER($K37),ISNUMBER(L37),L37<>0),$K37/L37-1,""),"") | P37: =IFERROR(IF(AND(ISNUMBER($K37),ISNUMBER(M37),M37<>0),$K37/M37-1,""),"") | Q37: =IFERROR(IF(AND(ISNUMBER($K37),ISNUMBER(N37),N37<>0),$K37/N37-1,""),"")
A38: =Tickers!$A$37 | C38: =_xll.BDP($A38,"BEST_SALES","BEST_FPERIOD_OVERRIDE","1BF") | D38: =_xll.BDP($A38,"BEST_SALES","BEST_FPERIOD_OVERRIDE","1BF","BEST_DATA_DATE_OVERRIDE",TEXT(YEAR($D$4),"0000")&TEXT(MONTH($D$4),"00")&TEXT(DAY($D$4),"00")) | E38: =_xll.BDP($A38,"BEST_SALES","BEST_FPERIOD_OVERRIDE","1BF","BEST_DATA_DATE_OVERRIDE",TEXT(YEAR($E$4),"0000")&TEXT(MONTH($E$4),"00")&TEXT(DAY($E$4),"00")) | F38: =_xll.BDP($A38,"BEST_SALES","BEST_FPERIOD_OVERRIDE","1BF","BEST_DATA_DATE_OVERRIDE",TEXT(YEAR($F$4),"0000")&TEXT(MONTH($F$4),"00")&TEXT(DAY($F$4),"00")) | G38: =IFERROR(IF(AND(ISNUMBER($C38),ISNUMBER(D38),D38<>0),$C38/D38-1,""),"") | H38: =IFERROR(IF(AND(ISNUMBER($C38),ISNUMBER(E38),E38<>0),$C38/E38-1,""),"") | I38: =IFERROR(IF(AND(ISNUMBER($C38),ISNUMBER(F38),F38<>0),$C38/F38-1,""),"") | K38: =_xll.BDP($A38,"BEST_EPS","BEST_FPERIOD_OVERRIDE","1BF") | L38: =_xll.BDP($A38,"BEST_EPS","BEST_FPERIOD_OVERRIDE","1BF","BEST_DATA_DATE_OVERRIDE",TEXT(YEAR($D$4),"0000")&TEXT(MONTH($D$4),"00")&TEXT(DAY($D$4),"00")) | M38: =_xll.BDP($A38,"BEST_EPS","BEST_FPERIOD_OVERRIDE","1BF","BEST_DATA_DATE_OVERRIDE",TEXT(YEAR($E$4),"0000")&TEXT(MONTH($E$4),"00")&TEXT(DAY($E$4),"00")) | N38: =_xll.BDP($A38,"BEST_EPS","BEST_FPERIOD_OVERRIDE","1BF","BEST_DATA_DATE_OVERRIDE",TEXT(YEAR($F$4),"0000")&TEXT(MONTH($F$4),"00")&TEXT(DAY($F$4),"00")) | O38: =IFERROR(IF(AND(ISNUMBER($K38),ISNUMBER(L38),L38<>0),$K38/L38-1,""),"") | P38: =IFERROR(IF(AND(ISNUMBER($K38),ISNUMBER(M38),M38<>0),$K38/M38-1,""),"") | Q38: =IFERROR(IF(AND(ISNUMBER($K38),ISNUMBER(N38),N38<>0),$K38/N38-1,""),"")
A39: =Tickers!$A$38 | C39: =_xll.BDP($A39,"BEST_SALES","BEST_FPERIOD_OVERRIDE","1BF") | D39: =_xll.BDP($A39,"BEST_SALES","BEST_FPERIOD_OVERRIDE","1BF","BEST_DATA_DATE_OVERRIDE",TEXT(YEAR($D$4),"0000")&TEXT(MONTH($D$4),"00")&TEXT(DAY($D$4),"00")) | E39: =_xll.BDP($A39,"BEST_SALES","BEST_FPERIOD_OVERRIDE","1BF","BEST_DATA_DATE_OVERRIDE",TEXT(YEAR($E$4),"0000")&TEXT(MONTH($E$4),"00")&TEXT(DAY($E$4),"00")) | F39: =_xll.BDP($A39,"BEST_SALES","BEST_FPERIOD_OVERRIDE","1BF","BEST_DATA_DATE_OVERRIDE",TEXT(YEAR($F$4),"0000")&TEXT(MONTH($F$4),"00")&TEXT(DAY($F$4),"00")) | G39: =IFERROR(IF(AND(ISNUMBER($C39),ISNUMBER(D39),D39<>0),$C39/D39-1,""),"") | H39: =IFERROR(IF(AND(ISNUMBER($C39),ISNUMBER(E39),E39<>0),$C39/E39-1,""),"") | I39: =IFERROR(IF(AND(ISNUMBER($C39),ISNUMBER(F39),F39<>0),$C39/F39-1,""),"") | K39: =_xll.BDP($A39,"BEST_EPS","BEST_FPERIOD_OVERRIDE","1BF") | L39: =_xll.BDP($A39,"BEST_EPS","BEST_FPERIOD_OVERRIDE","1BF","BEST_DATA_DATE_OVERRIDE",TEXT(YEAR($D$4),"0000")&TEXT(MONTH($D$4),"00")&TEXT(DAY($D$4),"00")) | M39: =_xll.BDP($A39,"BEST_EPS","BEST_FPERIOD_OVERRIDE","1BF","BEST_DATA_DATE_OVERRIDE",TEXT(YEAR($E$4),"0000")&TEXT(MONTH($E$4),"00")&TEXT(DAY($E$4),"00")) | N39: =_xll.BDP($A39,"BEST_EPS","BEST_FPERIOD_OVERRIDE","1BF","BEST_DATA_DATE_OVERRIDE",TEXT(YEAR($F$4),"0000")&TEXT(MONTH($F$4),"00")&TEXT(DAY($F$4),"00")) | O39: =IFERROR(IF(AND(ISNUMBER($K39),ISNUMBER(L39),L39<>0),$K39/L39-1,""),"") | P39: =IFERROR(IF(AND(ISNUMBER($K39),ISNUMBER(M39),M39<>0),$K39/M39-1,""),"") | Q39: =IFERROR(IF(AND(ISNUMBER($K39),ISNUMBER(N39),N39<>0),$K39/N39-1,""),"")
A40: =Tickers!$A$39 | C40: =_xll.BDP($A40,"BEST_SALES","BEST_FPERIOD_OVERRIDE","1BF") | D40: =_xll.BDP($A40,"BEST_SALES","BEST_FPERIOD_OVERRIDE","1BF","BEST_DATA_DATE_OVERRIDE",TEXT(YEAR($D$4),"0000")&TEXT(MONTH($D$4),"00")&TEXT(DAY($D$4),"00")) | E40: =_xll.BDP($A40,"BEST_SALES","BEST_FPERIOD_OVERRIDE","1BF","BEST_DATA_DATE_OVERRIDE",TEXT(YEAR($E$4),"0000")&TEXT(MONTH($E$4),"00")&TEXT(DAY($E$4),"00")) | F40: =_xll.BDP($A40,"BEST_SALES","BEST_FPERIOD_OVERRIDE","1BF","BEST_DATA_DATE_OVERRIDE",TEXT(YEAR($F$4),"0000")&TEXT(MONTH($F$4),"00")&TEXT(DAY($F$4),"00")) | G40: =IFERROR(IF(AND(ISNUMBER($C40),ISNUMBER(D40),D40<>0),$C40/D40-1,""),"") | H40: =IFERROR(IF(AND(ISNUMBER($C40),ISNUMBER(E40),E40<>0),$C40/E40-1,""),"") | I40: =IFERROR(IF(AND(ISNUMBER($C40),ISNUMBER(F40),F40<>0),$C40/F40-1,""),"") | K40: =_xll.BDP($A40,"BEST_EPS","BEST_FPERIOD_OVERRIDE","1BF") | L40: =_xll.BDP($A40,"BEST_EPS","BEST_FPERIOD_OVERRIDE","1BF","BEST_DATA_DATE_OVERRIDE",TEXT(YEAR($D$4),"0000")&TEXT(MONTH($D$4),"00")&TEXT(DAY($D$4),"00")) | M40: =_xll.BDP($A40,"BEST_EPS","BEST_FPERIOD_OVERRIDE","1BF","BEST_DATA_DATE_OVERRIDE",TEXT(YEAR($E$4),"0000")&TEXT(MONTH($E$4),"00")&TEXT(DAY($E$4),"00")) | N40: =_xll.BDP($A40,"BEST_EPS","BEST_FPERIOD_OVERRIDE","1BF","BEST_DATA_DATE_OVERRIDE",TEXT(YEAR($F$4),"0000")&TEXT(MONTH($F$4),"00")&TEXT(DAY($F$4),"00")) | O40: =IFERROR(IF(AND(ISNUMBER($K40),ISNUMBER(L40),L40<>0),$K40/L40-1,""),"") | P40: =IFERROR(IF(AND(ISNUMBER($K40),ISNUMBER(M40),M40<>0),$K40/M40-1,""),"") | Q40: =IFERROR(IF(AND(ISNUMBER($K40),ISNUMBER(N40),N40<>0),$K40/N40-1,""),"")
A41: =Tickers!$A$40 | C41: =_xll.BDP($A41,"BEST_SALES","BEST_FPERIOD_OVERRIDE","1BF") | D41: =_xll.BDP($A41,"BEST_SALES","BEST_FPERIOD_OVERRIDE","1BF","BEST_DATA_DATE_OVERRIDE",TEXT(YEAR($D$4),"0000")&TEXT(MONTH($D$4),"00")&TEXT(DAY($D$4),"00")) | E41: =_xll.BDP($A41,"BEST_SALES","BEST_FPERIOD_OVERRIDE","1BF","BEST_DATA_DATE_OVERRIDE",TEXT(YEAR($E$4),"0000")&TEXT(MONTH($E$4),"00")&TEXT(DAY($E$4),"00")) | F41: =_xll.BDP($A41,"BEST_SALES","BEST_FPERIOD_OVERRIDE","1BF","BEST_DATA_DATE_OVERRIDE",TEXT(YEAR($F$4),"0000")&TEXT(MONTH($F$4),"00")&TEXT(DAY($F$4),"00")) | G41: =IFERROR(IF(AND(ISNUMBER($C41),ISNUMBER(D41),D41<>0),$C41/D41-1,""),"") | H41: =IFERROR(IF(AND(ISNUMBER($C41),ISNUMBER(E41),E41<>0),$C41/E41-1,""),"") | I41: =IFERROR(IF(AND(ISNUMBER($C41),ISNUMBER(F41),F41<>0),$C41/F41-1,""),"") | K41: =_xll.BDP($A41,"BEST_EPS","BEST_FPERIOD_OVERRIDE","1BF") | L41: =_xll.BDP($A41,"BEST_EPS","BEST_FPERIOD_OVERRIDE","1BF","BEST_DATA_DATE_OVERRIDE",TEXT(YEAR($D$4),"0000")&TEXT(MONTH($D$4),"00")&TEXT(DAY($D$4),"00")) | M41: =_xll.BDP($A41,"BEST_EPS","BEST_FPERIOD_OVERRIDE","1BF","BEST_DATA_DATE_OVERRIDE",TEXT(YEAR($E$4),"0000")&TEXT(MONTH($E$4),"00")&TEXT(DAY($E$4),"00")) | N41: =_xll.BDP($A41,"BEST_EPS","BEST_FPERIOD_OVERRIDE","1BF","BEST_DATA_DATE_OVERRIDE",TEXT(YEAR($F$4),"0000")&TEXT(MONTH($F$4),"00")&TEXT(DAY($F$4),"00")) | O41: =IFERROR(IF(AND(ISNUMBER($K41),ISNUMBER(L41),L41<>0),$K41/L41-1,""),"") | P41: =IFERROR(IF(AND(ISNUMBER($K41),ISNUMBER(M41),M41<>0),$K41/M41-1,""),"") | Q41: =IFERROR(IF(AND(ISNUMBER($K41),ISNUMBER(N41),N41<>0),$K41/N41-1,""),"")
A42: =Tickers!$A$41 | C42: =_xll.BDP($A42,"BEST_SALES","BEST_FPERIOD_OVERRIDE","1BF") | D42: =_xll.BDP($A42,"BEST_SALES","BEST_FPERIOD_OVERRIDE","1BF","BEST_DATA_DATE_OVERRIDE",TEXT(YEAR($D$4),"0000")&TEXT(MONTH($D$4),"00")&TEXT(DAY($D$4),"00")) | E42: =_xll.BDP($A42,"BEST_SALES","BEST_FPERIOD_OVERRIDE","1BF","BEST_DATA_DATE_OVERRIDE",TEXT(YEAR($E$4),"0000")&TEXT(MONTH($E$4),"00")&TEXT(DAY($E$4),"00")) | F42: =_xll.BDP($A42,"BEST_SALES","BEST_FPERIOD_OVERRIDE","1BF","BEST_DATA_DATE_OVERRIDE",TEXT(YEAR($F$4),"0000")&TEXT(MONTH($F$4),"00")&TEXT(DAY($F$4),"00")) | G42: =IFERROR(IF(AND(ISNUMBER($C42),ISNUMBER(D42),D42<>0),$C42/D42-1,""),"") | H42: =IFERROR(IF(AND(ISNUMBER($C42),ISNUMBER(E42),E42<>0),$C42/E42-1,""),"") | I42: =IFERROR(IF(AND(ISNUMBER($C42),ISNUMBER(F42),F42<>0),$C42/F42-1,""),"") | K42: =_xll.BDP($A42,"BEST_EPS","BEST_FPERIOD_OVERRIDE","1BF") | L42: =_xll.BDP($A42,"BEST_EPS","BEST_FPERIOD_OVERRIDE","1BF","BEST_DATA_DATE_OVERRIDE",TEXT(YEAR($D$4),"0000")&TEXT(MONTH($D$4),"00")&TEXT(DAY($D$4),"00")) | M42: =_xll.BDP($A42,"BEST_EPS","BEST_FPERIOD_OVERRIDE","1BF","BEST_DATA_DATE_OVERRIDE",TEXT(YEAR($E$4),"0000")&TEXT(MONTH($E$4),"00")&TEXT(DAY($E$4),"00")) | N42: =_xll.BDP($A42,"BEST_EPS","BEST_FPERIOD_OVERRIDE","1BF","BEST_DATA_DATE_OVERRIDE",TEXT(YEAR($F$4),"0000")&TEXT(MONTH($F$4),"00")&TEXT(DAY($F$4),"00")) | O42: =IFERROR(IF(AND(ISNUMBER($K42),ISNUMBER(L42),L42<>0),$K42/L42-1,""),"") | P42: =IFERROR(IF(AND(ISNUMBER($K42),ISNUMBER(M42),M42<>0),$K42/M42-1,""),"") | Q42: =IFERROR(IF(AND(ISNUMBER($K42),ISNUMBER(N42),N42<>0),$K42/N42-1,""),"")
A43: =Tickers!$A$42 | C43: =_xll.BDP($A43,"BEST_SALES","BEST_FPERIOD_OVERRIDE","1BF") | D43: =_xll.BDP($A43,"BEST_SALES","BEST_FPERIOD_OVERRIDE","1BF","BEST_DATA_DATE_OVERRIDE",TEXT(YEAR($D$4),"0000")&TEXT(MONTH($D$4),"00")&TEXT(DAY($D$4),"00")) | E43: =_xll.BDP($A43,"BEST_SALES","BEST_FPERIOD_OVERRIDE","1BF","BEST_DATA_DATE_OVERRIDE",TEXT(YEAR($E$4),"0000")&TEXT(MONTH($E$4),"00")&TEXT(DAY($E$4),"00")) | F43: =_xll.BDP($A43,"BEST_SALES","BEST_FPERIOD_OVERRIDE","1BF","BEST_DATA_DATE_OVERRIDE",TEXT(YEAR($F$4),"0000")&TEXT(MONTH($F$4),"00")&TEXT(DAY($F$4),"00")) | G43: =IFERROR(IF(AND(ISNUMBER($C43),ISNUMBER(D43),D43<>0),$C43/D43-1,""),"") | H43: =IFERROR(IF(AND(ISNUMBER($C43),ISNUMBER(E43),E43<>0),$C43/E43-1,""),"") | I43: =IFERROR(IF(AND(ISNUMBER($C43),ISNUMBER(F43),F43<>0),$C43/F43-1,""),"") | K43: =_xll.BDP($A43,"BEST_EPS","BEST_FPERIOD_OVERRIDE","1BF") | L43: =_xll.BDP($A43,"BEST_EPS","BEST_FPERIOD_OVERRIDE","1BF","BEST_DATA_DATE_OVERRIDE",TEXT(YEAR($D$4),"0000")&TEXT(MONTH($D$4),"00")&TEXT(DAY($D$4),"00")) | M43: =_xll.BDP($A43,"BEST_EPS","BEST_FPERIOD_OVERRIDE","1BF","BEST_DATA_DATE_OVERRIDE",TEXT(YEAR($E$4),"0000")&TEXT(MONTH($E$4),"00")&TEXT(DAY($E$4),"00")) | N43: =_xll.BDP($A43,"BEST_EPS","BEST_FPERIOD_OVERRIDE","1BF","BEST_DATA_DATE_OVERRIDE",TEXT(YEAR($F$4),"0000")&TEXT(MONTH($F$4),"00")&TEXT(DAY($F$4),"00")) | O43: =IFERROR(IF(AND(ISNUMBER($K43),ISNUMBER(L43),L43<>0),$K43/L43-1,""),"") | P43: =IFERROR(IF(AND(ISNUMBER($K43),ISNUMBER(M43),M43<>0),$K43/M43-1,""),"") | Q43: =IFERROR(IF(AND(ISNUMBER($K43),ISNUMBER(N43),N43<>0),$K43/N43-1,""),"")
A44: =Tickers!$A$43 | C44: =_xll.BDP($A44,"BEST_SALES","BEST_FPERIOD_OVERRIDE","1BF") | D44: =_xll.BDP($A44,"BEST_SALES","BEST_FPERIOD_OVERRIDE","1BF","BEST_DATA_DATE_OVERRIDE",TEXT(YEAR($D$4),"0000")&TEXT(MONTH($D$4),"00")&TEXT(DAY($D$4),"00")) | E44: =_xll.BDP($A44,"BEST_SALES","BEST_FPERIOD_OVERRIDE","1BF","BEST_DATA_DATE_OVERRIDE",TEXT(YEAR($E$4),"0000")&TEXT(MONTH($E$4),"00")&TEXT(DAY($E$4),"00")) | F44: =_xll.BDP($A44,"BEST_SALES","BEST_FPERIOD_OVERRIDE","1BF","BEST_DATA_DATE_OVERRIDE",TEXT(YEAR($F$4),"0000")&TEXT(MONTH($F$4),"00")&TEXT(DAY($F$4),"00")) | G44: =IFERROR(IF(AND(ISNUMBER($C44),ISNUMBER(D44),D44<>0),$C44/D44-1,""),"") | H44: =IFERROR(IF(AND(ISNUMBER($C44),ISNUMBER(E44),E44<>0),$C44/E44-1,""),"") | I44: =IFERROR(IF(AND(ISNUMBER($C44),ISNUMBER(F44),F44<>0),$C44/F44-1,""),"") | K44: =_xll.BDP($A44,"BEST_EPS","BEST_FPERIOD_OVERRIDE","1BF") | L44: =_xll.BDP($A44,"BEST_EPS","BEST_FPERIOD_OVERRIDE","1BF","BEST_DATA_DATE_OVERRIDE",TEXT(YEAR($D$4),"0000")&TEXT(MONTH($D$4),"00")&TEXT(DAY($D$4),"00")) | M44: =_xll.BDP($A44,"BEST_EPS","BEST_FPERIOD_OVERRIDE","1BF","BEST_DATA_DATE_OVERRIDE",TEXT(YEAR($E$4),"0000")&TEXT(MONTH($E$4),"00")&TEXT(DAY($E$4),"00")) | N44: =_xll.BDP($A44,"BEST_EPS","BEST_FPERIOD_OVERRIDE","1BF","BEST_DATA_DATE_OVERRIDE",TEXT(YEAR($F$4),"0000")&TEXT(MONTH($F$4),"00")&TEXT(DAY($F$4),"00")) | O44: =IFERROR(IF(AND(ISNUMBER($K44),ISNUMBER(L44),L44<>0),$K44/L44-1,""),"") | P44: =IFERROR(IF(AND(ISNUMBER($K44),ISNUMBER(M44),M44<>0),$K44/M44-1,""),"") | Q44: =IFERROR(IF(AND(ISNUMBER($K44),ISNUMBER(N44),N44<>0),$K44/N44-1,""),"")
A45: =Tickers!$A$44 | C45: =_xll.BDP($A45,"BEST_SALES","BEST_FPERIOD_OVERRIDE","1BF") | D45: =_xll.BDP($A45,"BEST_SALES","BEST_FPERIOD_OVERRIDE","1BF","BEST_DATA_DATE_OVERRIDE",TEXT(YEAR($D$4),"0000")&TEXT(MONTH($D$4),"00")&TEXT(DAY($D$4),"00")) | E45: =_xll.BDP($A45,"BEST_SALES","BEST_FPERIOD_OVERRIDE","1BF","BEST_DATA_DATE_OVERRIDE",TEXT(YEAR($E$4),"0000")&TEXT(MONTH($E$4),"00")&TEXT(DAY($E$4),"00")) | F45: =_xll.BDP($A45,"BEST_SALES","BEST_FPERIOD_OVERRIDE","1BF","BEST_DATA_DATE_OVERRIDE",TEXT(YEAR($F$4),"0000")&TEXT(MONTH($F$4),"00")&TEXT(DAY($F$4),"00")) | G45: =IFERROR(IF(AND(ISNUMBER($C45),ISNUMBER(D45),D45<>0),$C45/D45-1,""),"") | H45: =IFERROR(IF(AND(ISNUMBER($C45),ISNUMBER(E45),E45<>0),$C45/E45-1,""),"") | I45: =IFERROR(IF(AND(ISNUMBER($C45),ISNUMBER(F45),F45<>0),$C45/F45-1,""),"") | K45: =_xll.BDP($A45,"BEST_EPS","BEST_FPERIOD_OVERRIDE","1BF") | L45: =_xll.BDP($A45,"BEST_EPS","BEST_FPERIOD_OVERRIDE","1BF","BEST_DATA_DATE_OVERRIDE",TEXT(YEAR($D$4),"0000")&TEXT(MONTH($D$4),"00")&TEXT(DAY($D$4),"00")) | M45: =_xll.BDP($A45,"BEST_EPS","BEST_FPERIOD_OVERRIDE","1BF","BEST_DATA_DATE_OVERRIDE",TEXT(YEAR($E$4),"0000")&TEXT(MONTH($E$4),"00")&TEXT(DAY($E$4),"00")) | N45: =_xll.BDP($A45,"BEST_EPS","BEST_FPERIOD_OVERRIDE","1BF","BEST_DATA_DATE_OVERRIDE",TEXT(YEAR($F$4),"0000")&TEXT(MONTH($F$4),"00")&TEXT(DAY($F$4),"00")) | O45: =IFERROR(IF(AND(ISNUMBER($K45),ISNUMBER(L45),L45<>0),$K45/L45-1,""),"") | P45: =IFERROR(IF(AND(ISNUMBER($K45),ISNUMBER(M45),M45<>0),$K45/M45-1,""),"") | Q45: =IFERROR(IF(AND(ISNUMBER($K45),ISNUMBER(N45),N45<>0),$K45/N45-1,""),"")
A46: =Tickers!$A$45 | C46: =_xll.BDP($A46,"BEST_SALES","BEST_FPERIOD_OVERRIDE","1BF") | D46: =_xll.BDP($A46,"BEST_SALES","BEST_FPERIOD_OVERRIDE","1BF","BEST_DATA_DATE_OVERRIDE",TEXT(YEAR($D$4),"0000")&TEXT(MONTH($D$4),"00")&TEXT(DAY($D$4),"00")) | E46: =_xll.BDP($A46,"BEST_SALES","BEST_FPERIOD_OVERRIDE","1BF","BEST_DATA_DATE_OVERRIDE",TEXT(YEAR($E$4),"0000")&TEXT(MONTH($E$4),"00")&TEXT(DAY($E$4),"00")) | F46: =_xll.BDP($A46,"BEST_SALES","BEST_FPERIOD_OVERRIDE","1BF","BEST_DATA_DATE_OVERRIDE",TEXT(YEAR($F$4),"0000")&TEXT(MONTH($F$4),"00")&TEXT(DAY($F$4),"00")) | G46: =IFERROR(IF(AND(ISNUMBER($C46),ISNUMBER(D46),D46<>0),$C46/D46-1,""),"") | H46: =IFERROR(IF(AND(ISNUMBER($C46),ISNUMBER(E46),E46<>0),$C46/E46-1,""),"") | I46: =IFERROR(IF(AND(ISNUMBER($C46),ISNUMBER(F46),F46<>0),$C46/F46-1,""),"") | K46: =_xll.BDP($A46,"BEST_EPS","BEST_FPERIOD_OVERRIDE","1BF") | L46: =_xll.BDP($A46,"BEST_EPS","BEST_FPERIOD_OVERRIDE","1BF","BEST_DATA_DATE_OVERRIDE",TEXT(YEAR($D$4),"0000")&TEXT(MONTH($D$4),"00")&TEXT(DAY($D$4),"00")) | M46: =_xll.BDP($A46,"BEST_EPS","BEST_FPERIOD_OVERRIDE","1BF","BEST_DATA_DATE_OVERRIDE",TEXT(YEAR($E$4),"0000")&TEXT(MONTH($E$4),"00")&TEXT(DAY($E$4),"00")) | N46: =_xll.BDP($A46,"BEST_EPS","BEST_FPERIOD_OVERRIDE","1BF","BEST_DATA_DATE_OVERRIDE",TEXT(YEAR($F$4),"0000")&TEXT(MONTH($F$4),"00")&TEXT(DAY($F$4),"00")) | O46: =IFERROR(IF(AND(ISNUMBER($K46),ISNUMBER(L46),L46<>0),$K46/L46-1,""),"") | P46: =IFERROR(IF(AND(ISNUMBER($K46),ISNUMBER(M46),M46<>0),$K46/M46-1,""),"") | Q46: =IFERROR(IF(AND(ISNUMBER($K46),ISNUMBER(N46),N46<>0),$K46/N46-1,""),"")
